Workbook

Sheet Cover
C3: Análise Same Sellers Tik Tok
C7: xxx
C9: xxx
C11: Amz x Shopee Comparisons
C12: xxx

Sheet Analysis Table
B3: TABELA DE SUPORTE PARA ANÁLISE
C7: shop_id_shp | D7: shop_name_shp | E7: shop_id_tts | F7: shop_name_tts | G7: cluster | H7: net_ado_shp | I7: net_adnmv_usd_shp | J7: net_ado_tts | K7: net_adnmv_usd_tts | L7: source | M7: top_at_shp | N7: top_at_tts | O7: top_at_both | P7: bigger_at_shp | Q7: duplicates
C8: 291174073 | D8: ZSZ_Official Store | E8: =_xlfn.XLOOKUP(C8,'Same Seller Hist'!E:E,'Same Seller Hist'!I:I) -> 7.4961635e+18 | F8: =_xlfn.XLOOKUP(C8,'Same Seller Hist'!E:E,'Same Seller Hist'!H:H) -> ZSZ BR | G8: CN | H8: 1622 | I8: 9436.935 | J8: =_xlfn.IFNA(_xlfn.XLOOKUP(F8,'Fastmoss 500'!D:D,'Fastmoss 500'!O:O),0) -> 700 | K8: =_xlfn.IFNA(_xlfn.XLOOKUP(F8,'Fastmoss 500'!D:D,'Fastmoss 500'!N:N),0) -> 14158.065 | L8: Shp 500 | M8: =IF(L8="Shp 500","Sim",IF(ISNA(_xlfn.XLOOKUP(C8,'Shp 500'!D:D,'Shp 500'!D:D)),"Não","Sim")) -> Sim | N8: =IF(L8="Fastmoss 500","Sim",IF(ISNA(_xlfn.XLOOKUP(_xlfn.XLOOKUP(C8,'Same Seller Hist'!E:E,'Same Seller Hist'!H:H),'Fastmoss 500'!D:D,'Fastmoss 500'!D:D)),"Não","Sim")) -> Sim | O8: =IF(AND(M8="Sim",N8="Sim"),"Sim","Não") -> Sim | P8: =IF(I8>K8,"Sim","Não") -> Não | Q8: =COUNTIFS(C:C,C8) -> 1
C9: 552896405 | D9: Casa_Completa_Enxovais | E9: =_xlfn.XLOOKUP(C9,'Same Seller Hist'!E:E,'Same Seller Hist'!I:I) -> 7.49626e+18 | F9: =_xlfn.XLOOKUP(C9,'Same Seller Hist'!E:E,'Same Seller Hist'!H:H) -> Casa Completa Enxovais | G9: Lifestyle | H9: 5043.8387 | I9: 53289.304 | J9: =_xlfn.IFNA(_xlfn.XLOOKUP(F9,'Fastmoss 500'!D:D,'Fastmoss 500'!O:O),0) -> 0 | K9: =_xlfn.IFNA(_xlfn.XLOOKUP(F9,'Fastmoss 500'!D:D,'Fastmoss 500'!N:N),0) -> 0 | L9: Shp 500 | M9: =IF(L9="Shp 500","Sim",IF(ISNA(_xlfn.XLOOKUP(C9,'Shp 500'!D:D,'Shp 500'!D:D)),"Não","Sim")) -> Sim | N9: =IF(L9="Fastmoss 500","Sim",IF(ISNA(_xlfn.XLOOKUP(_xlfn.XLOOKUP(C9,'Same Seller Hist'!E:E,'Same Seller Hist'!H:H),'Fastmoss 500'!D:D,'Fastmoss 500'!D:D)),"Não","Sim")) -> Não | O9: =IF(AND(M9="Sim",N9="Sim"),"Sim","Não") -> Não | P9: =IF(I9>K9,"Sim","Não") -> Sim | Q9: =COUNTIFS(C:C,C9) -> 1
C10: 974102638 | D10: Loja 128 | E10: =_xlfn.XLOOKUP(C10,'Same Seller Hist'!E:E,'Same Seller Hist'!I:I) -> 7.4962283e+18 | F10: =_xlfn.XLOOKUP(C10,'Same Seller Hist'!E:E,'Same Seller Hist'!H:H) -> blueepulse | G10: CN | H10: 4870.1613 | I10: 49065.871 | J10: =_xlfn.IFNA(_xlfn.XLOOKUP(F10,'Fastmoss 500'!D:D,'Fastmoss 500'!O:O),0) -> 0 | K10: =_xlfn.IFNA(_xlfn.XLOOKUP(F10,'Fastmoss 500'!D:D,'Fastmoss 500'!N:N),0) -> 0 | L10: Shp 500 | M10: =IF(L10="Shp 500","Sim",IF(ISNA(_xlfn.XLOOKUP(C10,'Shp 500'!D:D,'Shp 500'!D:D)),"Não","Sim")) -> Sim | N10: =IF(L10="Fastmoss 500","Sim",IF(ISNA(_xlfn.XLOOKUP(_xlfn.XLOOKUP(C10,'Same Seller Hist'!E:E,'Same Seller Hist'!H:H),'Fastmoss 500'!D:D,'Fastmoss 500'!D:D)),"Não","Sim")) -> Não | O10: =IF(AND(M10="Sim",N10="Sim"),"Sim","Não") -> Não | P10: =IF(I10>K10,"Sim","Não") -> Sim | Q10: =COUNTIFS(C:C,C10) -> 1
C11: 362859393 | D11: ALFA MERCEARIA.BR | E11: =_xlfn.XLOOKUP(C11,'Same Seller Hist'!E:E,'Same Seller Hist'!I:I) -> 7.4961597e+18 | F11: =_xlfn.XLOOKUP(C11,'Same Seller Hist'!E:E,'Same Seller Hist'!H:H) -> ALFA SHOP.BR | G11: CN | H11: 4604.9355 | I11: 14928.731 | J11: =_xlfn.IFNA(_xlfn.XLOOKUP(F11,'Fastmoss 500'!D:D,'Fastmoss 500'!O:O),0) -> 0 | K11: =_xlfn.IFNA(_xlfn.XLOOKUP(F11,'Fastmoss 500'!D:D,'Fastmoss 500'!N:N),0) -> 0 | L11: Shp 500 | M11: =IF(L11="Shp 500","Sim",IF(ISNA(_xlfn.XLOOKUP(C11,'Shp 500'!D:D,'Shp 500'!D:D)),"Não","Sim")) -> Sim | N11: =IF(L11="Fastmoss 500","Sim",IF(ISNA(_xlfn.XLOOKUP(_xlfn.XLOOKUP(C11,'Same Seller Hist'!E:E,'Same Seller Hist'!H:H),'Fastmoss 500'!D:D,'Fastmoss 500'!D:D)),"Não","Sim")) -> Não | O11: =IF(AND(M11="Sim",N11="Sim"),"Sim","Não") -> Não | P11: =IF(I11>K11,"Sim","Não") -> Sim | Q11: =COUNTIFS(C:C,C11) -> 1
C12: 1045085918 | D12: Droga Clara | E12: =_xlfn.XLOOKUP(C12,'Same Seller Hist'!E:E,'Same Seller Hist'!I:I) -> 7.4941815e+18 | F12: =_xlfn.XLOOKUP(C12,'Same Seller Hist'!E:E,'Same Seller Hist'!H:H) -> YUMI CELL BR | G12: FMCG | H12: 4299.4839 | I12: 22995.675 | J12: =_xlfn.IFNA(_xlfn.XLOOKUP(F12,'Fastmoss 500'!D:D,'Fastmoss 500'!O:O),0) -> 235.48387 | K12: =_xlfn.IFNA(_xlfn.XLOOKUP(F12,'Fastmoss 500'!D:D,'Fastmoss 500'!N:N),0) -> 17706.452 | L12: Shp 500 | M12: =IF(L12="Shp 500","Sim",IF(ISNA(_xlfn.XLOOKUP(C12,'Shp 500'!D:D,'Shp 500'!D:D)),"Não","Sim")) -> Sim | N12: =IF(L12="Fastmoss 500","Sim",IF(ISNA(_xlfn.XLOOKUP(_xlfn.XLOOKUP(C12,'Same Seller Hist'!E:E,'Same Seller Hist'!H:H),'Fastmoss 500'!D:D,'Fastmoss 500'!D:D)),"Não","Sim")) -> Sim | O12: =IF(AND(M12="Sim",N12="Sim"),"Sim","Não") -> Sim | P12: =IF(I12>K12,"Sim","Não") -> Sim | Q12: =COUNTIFS(C:C,C12) -> 1
C13: 296363855 | D13: CasaLauraEnxovais | E13: =_xlfn.XLOOKUP(C13,'Same Seller Hist'!E:E,'Same Seller Hist'!I:I) -> 7.4955619e+18 | F13: =_xlfn.XLOOKUP(C13,'Same Seller Hist'!E:E,'Same Seller Hist'!H:H) -> Casa Laura Enxovais | G13: Lifestyle | H13: 1873.9355 | I13: 15155.613 | J13: =_xlfn.IFNA(_xlfn.XLOOKUP(F13,'Fastmoss 500'!D:D,'Fastmoss 500'!O:O),0) -> 280.64516 | K13: =_xlfn.IFNA(_xlfn.XLOOKUP(F13,'Fastmoss 500'!D:D,'Fastmoss 500'!N:N),0) -> 16445.161 | L13: Shp 500 | M13: =IF(L13="Shp 500","Sim",IF(ISNA(_xlfn.XLOOKUP(C13,'Shp 500'!D:D,'Shp 500'!D:D)),"Não","Sim")) -> Sim | N13: =IF(L13="Fastmoss 500","Sim",IF(ISNA(_xlfn.XLOOKUP(_xlfn.XLOOKUP(C13,'Same Seller Hist'!E:E,'Same Seller Hist'!H:H),'Fastmoss 500'!D:D,'Fastmoss 500'!D:D)),"Não","Sim")) -> Sim | O13: =IF(AND(M13="Sim",N13="Sim"),"Sim","Não") -> Sim | P13: =IF(I13>K13,"Sim","Não") -> Não | Q13: =COUNTIFS(C:C,C13) -> 1
C14: 872424585 | D14: Mega TechStore | E14: =_xlfn.XLOOKUP(C14,'Same Seller Hist'!E:E,'Same Seller Hist'!I:I) -> 7.4961817e+18 | F14: =_xlfn.XLOOKUP(C14,'Same Seller Hist'!E:E,'Same Seller Hist'!H:H) -> mega tech store | G14: CN | H14: 3866.0645 | I14: 31272.972 | J14: =_xlfn.IFNA(_xlfn.XLOOKUP(F14,'Fastmoss 500'!D:D,'Fastmoss 500'!O:O),0) -> 0 | K14: =_xlfn.IFNA(_xlfn.XLOOKUP(F14,'Fastmoss 500'!D:D,'Fastmoss 500'!N:N),0) -> 0 | L14: Shp 500 | M14: =IF(L14="Shp 500","Sim",IF(ISNA(_xlfn.XLOOKUP(C14,'Shp 500'!D:D,'Shp 500'!D:D)),"Não","Sim")) -> Sim | N14: =IF(L14="Fastmoss 500","Sim",IF(ISNA(_xlfn.XLOOKUP(_xlfn.XLOOKUP(C14,'Same Seller Hist'!E:E,'Same Seller Hist'!H:H),'Fastmoss 500'!D:D,'Fastmoss 500'!D:D)),"Não","Sim")) -> Não | O14: =IF(AND(M14="Sim",N14="Sim"),"Sim","Não") -> Não | P14: =IF(I14>K14,"Sim","Não") -> Sim | Q14: =COUNTIFS(C:C,C14) -> 1
C15: 643719371 | D15: NEWCOOL | E15: =_xlfn.XLOOKUP(C15,'Same Seller Hist'!E:E,'Same Seller Hist'!I:I) -> 7.496184e+18 | F15: =_xlfn.XLOOKUP(C15,'Same Seller Hist'!E:E,'Same Seller Hist'!H:H) -> NEWCOOL.BR | G15: CN | H15: 3826.9355 | I15: 19013.021 | J15: =_xlfn.IFNA(_xlfn.XLOOKUP(F15,'Fastmoss 500'!D:D,'Fastmoss 500'!O:O),0) -> 0 | K15: =_xlfn.IFNA(_xlfn.XLOOKUP(F15,'Fastmoss 500'!D:D,'Fastmoss 500'!N:N),0) -> 0 | L15: Shp 500 | M15: =IF(L15="Shp 500","Sim",IF(ISNA(_xlfn.XLOOKUP(C15,'Shp 500'!D:D,'Shp 500'!D:D)),"Não","Sim")) -> Sim | N15: =IF(L15="Fastmoss 500","Sim",IF(ISNA(_xlfn.XLOOKUP(_xlfn.XLOOKUP(C15,'Same Seller Hist'!E:E,'Same Seller Hist'!H:H),'Fastmoss 500'!D:D,'Fastmoss 500'!D:D)),"Não","Sim")) -> Não | O15: =IF(AND(M15="Sim",N15="Sim"),"Sim","Não") -> Não | P15: =IF(I15>K15,"Sim","Não") -> Sim | Q15: =COUNTIFS(C:C,C15) -> 1
C16: 299222557 | D16: RIven Bazar | E16: =_xlfn.XLOOKUP(C16,'Same Seller Hist'!E:E,'Same Seller Hist'!I:I) -> 7.4961792e+18 | F16: =_xlfn.XLOOKUP(C16,'Same Seller Hist'!E:E,'Same Seller Hist'!H:H) -> RIVEN BAZAR | G16: CN | H16: 2540.1613 | I16: 9178.8417 | J16: =_xlfn.IFNA(_xlfn.XLOOKUP(F16,'Fastmoss 500'!D:D,'Fastmoss 500'!O:O),0) -> 251.6129 | K16: =_xlfn.IFNA(_xlfn.XLOOKUP(F16,'Fastmoss 500'!D:D,'Fastmoss 500'!N:N),0) -> 10303.226 | L16: Shp 500 | M16: =IF(L16="Shp 500","Sim",IF(ISNA(_xlfn.XLOOKUP(C16,'Shp 500'!D:D,'Shp 500'!D:D)),"Não","Sim")) -> Sim | N16: =IF(L16="Fastmoss 500","Sim",IF(ISNA(_xlfn.XLOOKUP(_xlfn.XLOOKUP(C16,'Same Seller Hist'!E:E,'Same Seller Hist'!H:H),'Fastmoss 500'!D:D,'Fastmoss 500'!D:D)),"Não","Sim")) -> Sim | O16: =IF(AND(M16="Sim",N16="Sim"),"Sim","Não") -> Sim | P16: =IF(I16>K16,"Sim","Não") -> Não | Q16: =COUNTIFS(C:C,C16) -> 1
C17: 1064041485 | D17: LuxeElectra | E17: =_xlfn.XLOOKUP(C17,'Same Seller Hist'!E:E,'Same Seller Hist'!I:I) -> 7.4961859e+18 | F17: =_xlfn.XLOOKUP(C17,'Same Seller Hist'!E:E,'Same Seller Hist'!H:H) -> luxeelectra | G17: CN | H17: 3451.0968 | I17: 33941.769 | J17: =_xlfn.IFNA(_xlfn.XLOOKUP(F17,'Fastmoss 500'!D:D,'Fastmoss 500'!O:O),0) -> 0 | K17: =_xlfn.IFNA(_xlfn.XLOOKUP(F17,'Fastmoss 500'!D:D,'Fastmoss 500'!N:N),0) -> 0 | L17: Shp 500 | M17: =IF(L17="Shp 500","Sim",IF(ISNA(_xlfn.XLOOKUP(C17,'Shp 500'!D:D,'Shp 500'!D:D)),"Não","Sim")) -> Sim | N17: =IF(L17="Fastmoss 500","Sim",IF(ISNA(_xlfn.XLOOKUP(_xlfn.XLOOKUP(C17,'Same Seller Hist'!E:E,'Same Seller Hist'!H:H),'Fastmoss 500'!D:D,'Fastmoss 500'!D:D)),"Não","Sim")) -> Não | O17: =IF(AND(M17="Sim",N17="Sim"),"Sim","Não") -> Não | P17: =IF(I17>K17,"Sim","Não") -> Sim | Q17: =COUNTIFS(C:C,C17) -> 1
C18: 341167297 | D18: Poloinfantil.store | E18: =_xlfn.XLOOKUP(C18,'Same Seller Hist'!E:E,'Same Seller Hist'!I:I) -> 0 | F18: =_xlfn.XLOOKUP(C18,'Same Seller Hist'!E:E,'Same Seller Hist'!H:H) -> 0 | G18: Fashion | H18: 3346.871 | I18: 37236.535 | J18: =_xlfn.IFNA(_xlfn.XLOOKUP(F18,'Fastmoss 500'!D:D,'Fastmoss 500'!O:O),0) -> 0 | K18: =_xlfn.IFNA(_xlfn.XLOOKUP(F18,'Fastmoss 500'!D:D,'Fastmoss 500'!N:N),0) -> 0 | L18: Shp 500 | M18: =IF(L18="Shp 500","Sim",IF(ISNA(_xlfn.XLOOKUP(C18,'Shp 500'!D:D,'Shp 500'!D:D)),"Não","Sim")) -> Sim | N18: =IF(L18="Fastmoss 500","Sim",IF(ISNA(_xlfn.XLOOKUP(_xlfn.XLOOKUP(C18,'Same Seller Hist'!E:E,'Same Seller Hist'!H:H),'Fastmoss 500'!D:D,'Fastmoss 500'!D:D)),"Não","Sim")) -> Não | O18: =IF(AND(M18="Sim",N18="Sim"),"Sim","Não") -> Não | P18: =IF(I18>K18,"Sim","Não") -> Sim | Q18: =COUNTIFS(C:C,C18) -> 1
C19: 313660590 | D19: Nosso Lar Enxovais | E19: =_xlfn.XLOOKUP(C19,'Same Seller Hist'!E:E,'Same Seller Hist'!I:I) -> 7.4940983e+18 | F19: =_xlfn.XLOOKUP(C19,'Same Seller Hist'!E:E,'Same Seller Hist'!H:H) -> Nosso Lar Enxovais | G19: Lifestyle | H19: 3313.3226 | I19: 29155.732 | J19: =_xlfn.IFNA(_xlfn.XLOOKUP(F19,'Fastmoss 500'!D:D,'Fastmoss 500'!O:O),0) -> 0 | K19: =_xlfn.IFNA(_xlfn.XLOOKUP(F19,'Fastmoss 500'!D:D,'Fastmoss 500'!N:N),0) -> 0 | L19: Shp 500 | M19: =IF(L19="Shp 500","Sim",IF(ISNA(_xlfn.XLOOKUP(C19,'Shp 500'!D:D,'Shp 500'!D:D)),"Não","Sim")) -> Sim | N19: =IF(L19="Fastmoss 500","Sim",IF(ISNA(_xlfn.XLOOKUP(_xlfn.XLOOKUP(C19,'Same Seller Hist'!E:E,'Same Seller Hist'!H:H),'Fastmoss 500'!D:D,'Fastmoss 500'!D:D)),"Não","Sim")) -> Não | O19: =IF(AND(M19="Sim",N19="Sim"),"Sim","Não") -> Não | P19: =IF(I19>K19,"Sim","Não") -> Sim | Q19: =COUNTIFS(C:C,C19) -> 1
... C140: 324536294 | D140: Krokodilus Oficial | E140: =_xlfn.XLOOKUP(C140,'Same Seller Hist'!E:E,'Same Seller Hist'!I:I) -> 7.4961604e+18 | F140: =_xlfn.XLOOKUP(C140,'Same Seller Hist'!E:E,'Same Seller Hist'!H:H) -> Krokodilus | G140: Fashion | H140: 819.80645 | I140: 15741.058 | J140: =_xlfn.IFNA(_xlfn.XLOOKUP(F140,'Fastmoss 500'!D:D,'Fastmoss 500'!O:O),0) -> 0 | K140: =_xlfn.IFNA(_xlfn.XLOOKUP(F140,'Fastmoss 500'!D:D,'Fastmoss 500'!N:N),0) -> 0 | L140: Shp 500 | M140: =IF(L140="Shp 500","Sim",IF(ISNA(_xlfn.XLOOKUP(C140,'Shp 500'!D:D,'Shp 500'!D:D)),"Não","Sim")) -> Sim | N140: =IF(L140="Fastmoss 500","Sim",IF(ISNA(_xlfn.XLOOKUP(_xlfn.XLOOKUP(C140,'Same Seller Hist'!E:E,'Same Seller Hist'!H:H),'Fastmoss 500'!D:D,'Fastmoss 500'!D:D)),"Não","Sim")) -> Não | O140: =IF(AND(M140="Sim",N140="Sim"),"Sim","Não") -> Não | P140: =IF(I140>K140,"Sim","Não") -> Sim | Q140: =COUNTIFS(C:C,C140) -> 1
C141: =_xlfn.XLOOKUP(F141,'Same Seller Hist'!H:H,'Same Seller Hist'!E:E) -> 1543591764 | D141: =_xlfn.XLOOKUP(F141,'Same Seller Hist'!H:H,'Same Seller Hist'!D:D) -> Always Fit Suplementos | E141: =_xlfn.XLOOKUP(F141,'Same Seller Hist'!H:H,'Same Seller Hist'!I:I) -> 7.4962164e+18 | F141: Always Fit Suplementos | G141: =_xlfn.XLOOKUP(C141,'Same Seller Hist'!E:E,'Same Seller Hist'!F:F) -> FMCG | H141: =_xlfn.IFNA(_xlfn.XLOOKUP(C141,'Shp 500'!D:D,'Shp 500'!I:I),0) -> 0 | I141: =_xlfn.IFNA(_xlfn.XLOOKUP(C141,'Shp 500'!D:D,'Shp 500'!J:J),0) -> 0 | J141: 5883.871 | K141: 303225.81 | L141: Fastmoss 500 | M141: =IF(L141="Shp 500","Sim",IF(ISNA(_xlfn.XLOOKUP(C141,'Shp 500'!D:D,'Shp 500'!D:D)),"Não","Sim")) -> Não | N141: =IF(L141="Fastmoss 500","Sim",IF(ISNA(_xlfn.XLOOKUP(_xlfn.XLOOKUP(C141,'Same Seller Hist'!E:E,'Same Seller Hist'!H:H),'Fastmoss 500'!D:D,'Fastmoss 500'!D:D)),"Não","Sim")) -> Sim | O141: =IF(AND(M141="Sim",N141="Sim"),"Sim","Não") -> Não | P141: =IF(I141>K141,"Sim","Não") -> Não | Q141: =COUNTIFS(C:C,C141) -> 1
C142: 616222685 | D142: Salon Line | E142: =_xlfn.XLOOKUP(C142,'Same Seller Hist'!E:E,'Same Seller Hist'!I:I) -> 7.496153e+18 | F142: =_xlfn.XLOOKUP(C142,'Same Seller Hist'!E:E,'Same Seller Hist'!H:H) -> Salon Line | G142: FMCG | H142: 5865.1935 | I142: 37595.714 | J142: =_xlfn.IFNA(_xlfn.XLOOKUP(F142,'Fastmoss 500'!D:D,'Fastmoss 500'!O:O),0) -> 541.93548 | K142: =_xlfn.IFNA(_xlfn.XLOOKUP(F142,'Fastmoss 500'!D:D,'Fastmoss 500'!N:N),0) -> 21870.968 | L142: Shp 500 | M142: =IF(L142="Shp 500","Sim",IF(ISNA(_xlfn.XLOOKUP(C142,'Shp 500'!D:D,'Shp 500'!D:D)),"Não","Sim")) -> Sim | N142: =IF(L142="Fastmoss 500","Sim",IF(ISNA(_xlfn.XLOOKUP(_xlfn.XLOOKUP(C142,'Same Seller Hist'!E:E,'Same Seller Hist'!H:H),'Fastmoss 500'!D:D,'Fastmoss 500'!D:D)),"Não","Sim")) -> Sim | O142: =IF(AND(M142="Sim",N142="Sim"),"Sim","Não") -> Sim | P142: =IF(I142>K142,"Sim","Não") -> Sim | Q142: =COUNTIFS(C:C,C142) -> 1
C143: =_xlfn.XLOOKUP(F143,'Same Seller Hist'!H:H,'Same Seller Hist'!E:E) -> 906473022 | D143: =_xlfn.XLOOKUP(F143,'Same Seller Hist'!H:H,'Same Seller Hist'!D:D) -> LUNA SHOP_BRASIL | E143: =_xlfn.XLOOKUP(F143,'Same Seller Hist'!H:H,'Same Seller Hist'!I:I) -> 7.4941342e+18 | F143: LUNA SHOP_BRASIL | G143: =_xlfn.XLOOKUP(C143,'Same Seller Hist'!E:E,'Same Seller Hist'!F:F) -> FMCG | H143: =_xlfn.IFNA(_xlfn.XLOOKUP(C143,'Shp 500'!D:D,'Shp 500'!I:I),0) -> 0 | I143: =_xlfn.IFNA(_xlfn.XLOOKUP(C143,'Shp 500'!D:D,'Shp 500'!J:J),0) -> 0 | J143: 3293.5484 | K143: 93548.387 | L143: Fastmoss 500 | M143: =IF(L143="Shp 500","Sim",IF(ISNA(_xlfn.XLOOKUP(C143,'Shp 500'!D:D,'Shp 500'!D:D)),"Não","Sim")) -> Não | N143: =IF(L143="Fastmoss 500","Sim",IF(ISNA(_xlfn.XLOOKUP(_xlfn.XLOOKUP(C143,'Same Seller Hist'!E:E,'Same Seller Hist'!H:H),'Fastmoss 500'!D:D,'Fastmoss 500'!D:D)),"Não","Sim")) -> Sim | O143: =IF(AND(M143="Sim",N143="Sim"),"Sim","Não") -> Não | P143: =IF(I143>K143,"Sim","Não") -> Não | Q143: =COUNTIFS(C:C,C143) -> 1
C144: =_xlfn.XLOOKUP(F144,'Same Seller Hist'!H:H,'Same Seller Hist'!E:E) -> 1103632656 | D144: =_xlfn.XLOOKUP(F144,'Same Seller Hist'!H:H,'Same Seller Hist'!D:D) -> Express.Loja | E144: =_xlfn.XLOOKUP(F144,'Same Seller Hist'!H:H,'Same Seller Hist'!I:I) -> 7.4961636e+18 | F144: Express.Loja | G144: =_xlfn.XLOOKUP(C144,'Same Seller Hist'!E:E,'Same Seller Hist'!F:F) -> Lifestyle | H144: =_xlfn.IFNA(_xlfn.XLOOKUP(C144,'Shp 500'!D:D,'Shp 500'!I:I),0) -> 0 | I144: =_xlfn.IFNA(_xlfn.XLOOKUP(C144,'Shp 500'!D:D,'Shp 500'!J:J),0) -> 0 | J144: 2551.6129 | K144: 41935.484 | L144: Fastmoss 500 | M144: =IF(L144="Shp 500","Sim",IF(ISNA(_xlfn.XLOOKUP(C144,'Shp 500'!D:D,'Shp 500'!D:D)),"Não","Sim")) -> Não | N144: =IF(L144="Fastmoss 500","Sim",IF(ISNA(_xlfn.XLOOKUP(_xlfn.XLOOKUP(C144,'Same Seller Hist'!E:E,'Same Seller Hist'!H:H),'Fastmoss 500'!D:D,'Fastmoss 500'!D:D)),"Não","Sim")) -> Sim | O144: =IF(AND(M144="Sim",N144="Sim"),"Sim","Não") -> Não | P144: =IF(I144>K144,"Sim","Não") -> Não | Q144: =COUNTIFS(C:C,C144) -> 1
C145: =_xlfn.XLOOKUP(F145,'Same Seller Hist'!H:H,'Same Seller Hist'!E:E) -> 1579330222 | D145: =_xlfn.XLOOKUP(F145,'Same Seller Hist'!H:H,'Same Seller Hist'!D:D) -> Barbour's Beauty | E145: =_xlfn.XLOOKUP(F145,'Same Seller Hist'!H:H,'Same Seller Hist'!I:I) -> 7.4962632e+18 | F145: Barbour's Beauty | G145: =_xlfn.XLOOKUP(C145,'Same Seller Hist'!E:E,'Same Seller Hist'!F:F) -> FMCG | H145: =_xlfn.IFNA(_xlfn.XLOOKUP(C145,'Shp 500'!D:D,'Shp 500'!I:I),0) -> 0 | I145: =_xlfn.IFNA(_xlfn.XLOOKUP(C145,'Shp 500'!D:D,'Shp 500'!J:J),0) -> 0 | J145: 2038.7097 | K145: 112903.23 | L145: Fastmoss 500 | M145: =IF(L145="Shp 500","Sim",IF(ISNA(_xlfn.XLOOKUP(C145,'Shp 500'!D:D,'Shp 500'!D:D)),"Não","Sim")) -> Não | N145: =IF(L145="Fastmoss 500","Sim",IF(ISNA(_xlfn.XLOOKUP(_xlfn.XLOOKUP(C145,'Same Seller Hist'!E:E,'Same Seller Hist'!H:H),'Fastmoss 500'!D:D,'Fastmoss 500'!D:D)),"Não","Sim")) -> Sim | O145: =IF(AND(M145="Sim",N145="Sim"),"Sim","Não") -> Não | P145: =IF(I145>K145,"Sim","Não") -> Não | Q145: =COUNTIFS(C:C,C145) -> 1
C146: =_xlfn.XLOOKUP(F146,'Same Seller Hist'!H:H,'Same Seller Hist'!E:E) -> 443076516 | D146: =_xlfn.XLOOKUP(F146,'Same Seller Hist'!H:H,'Same Seller Hist'!D:D) -> Bodyaction | E146: =_xlfn.XLOOKUP(F146,'Same Seller Hist'!H:H,'Same Seller Hist'!I:I) -> 7.4961818e+18 | F146: Bodyaction | G146: =_xlfn.XLOOKUP(C146,'Same Seller Hist'!E:E,'Same Seller Hist'!F:F) -> FMCG | H146: =_xlfn.IFNA(_xlfn.XLOOKUP(C146,'Shp 500'!D:D,'Shp 500'!I:I),0) -> 0 | I146: =_xlfn.IFNA(_xlfn.XLOOKUP(C146,'Shp 500'!D:D,'Shp 500'!J:J),0) -> 0 | J146: 1958.0645 | K146: 174193.55 | L146: Fastmoss 500 | M146: =IF(L146="Shp 500","Sim",IF(ISNA(_xlfn.XLOOKUP(C146,'Shp 500'!D:D,'Shp 500'!D:D)),"Não","Sim")) -> Não | N146: =IF(L146="Fastmoss 500","Sim",IF(ISNA(_xlfn.XLOOKUP(_xlfn.XLOOKUP(C146,'Same Seller Hist'!E:E,'Same Seller Hist'!H:H),'Fastmoss 500'!D:D,'Fastmoss 500'!D:D)),"Não","Sim")) -> Sim | O146: =IF(AND(M146="Sim",N146="Sim"),"Sim","Não") -> Não | P146: =IF(I146>K146,"Sim","Não") -> Não | Q146: =COUNTIFS(C:C,C146) -> 1
C147: 627750190 | D147: Pichau | E147: =_xlfn.XLOOKUP(C147,'Same Seller Hist'!E:E,'Same Seller Hist'!I:I) -> 7.4961686e+18 | F147: =_xlfn.XLOOKUP(C147,'Same Seller Hist'!E:E,'Same Seller Hist'!H:H) -> Pichau | G147: ELHA | H147: 2017.2903 | I147: 75626.787 | J147: =_xlfn.IFNA(_xlfn.XLOOKUP(F147,'Fastmoss 500'!D:D,'Fastmoss 500'!O:O),0) -> 203.22581 | K147: =_xlfn.IFNA(_xlfn.XLOOKUP(F147,'Fastmoss 500'!D:D,'Fastmoss 500'!N:N),0) -> 22596.774 | L147: Shp 500 | M147: =IF(L147="Shp 500","Sim",IF(ISNA(_xlfn.XLOOKUP(C147,'Shp 500'!D:D,'Shp 500'!D:D)),"Não","Sim")) -> Sim | N147: =IF(L147="Fastmoss 500","Sim",IF(ISNA(_xlfn.XLOOKUP(_xlfn.XLOOKUP(C147,'Same Seller Hist'!E:E,'Same Seller Hist'!H:H),'Fastmoss 500'!D:D,'Fastmoss 500'!D:D)),"Não","Sim")) -> Sim | O147: =IF(AND(M147="Sim",N147="Sim"),"Sim","Não") -> Sim | P147: =IF(I147>K147,"Sim","Não") -> Sim | Q147: =COUNTIFS(C:C,C147) -> 1
C148: 676651970 | D148: Chenjyacessorios | E148: =_xlfn.XLOOKUP(C148,'Same Seller Hist'!E:E,'Same Seller Hist'!I:I) -> 0 | F148: =_xlfn.XLOOKUP(C148,'Same Seller Hist'!E:E,'Same Seller Hist'!H:H) -> 0 | G148: CN | H148: 1106.9355 | I148: 9876.2254 | J148: =_xlfn.IFNA(_xlfn.XLOOKUP(F148,'Fastmoss 500'!D:D,'Fastmoss 500'!O:O),0) -> 0 | K148: =_xlfn.IFNA(_xlfn.XLOOKUP(F148,'Fastmoss 500'!D:D,'Fastmoss 500'!N:N),0) -> 0 | L148: Shp 500 | M148: =IF(L148="Shp 500","Sim",IF(ISNA(_xlfn.XLOOKUP(C148,'Shp 500'!D:D,'Shp 500'!D:D)),"Não","Sim")) -> Sim | N148: =IF(L148="Fastmoss 500","Sim",IF(ISNA(_xlfn.XLOOKUP(_xlfn.XLOOKUP(C148,'Same Seller Hist'!E:E,'Same Seller Hist'!H:H),'Fastmoss 500'!D:D,'Fastmoss 500'!D:D)),"Não","Sim")) -> Sim | O148: =IF(AND(M148="Sim",N148="Sim"),"Sim","Não") -> Sim | P148: =IF(I148>K148,"Sim","Não") -> Sim | Q148: =COUNTIFS(C:C,C148) -> 1
C149: =_xlfn.XLOOKUP(F149,'Same Seller Hist'!H:H,'Same Seller Hist'!E:E) -> 805674361 | D149: =_xlfn.XLOOKUP(F149,'Same Seller Hist'!H:H,'Same Seller Hist'!D:D) -> Danny Enxovais | E149: =_xlfn.XLOOKUP(F149,'Same Seller Hist'!H:H,'Same Seller Hist'!I:I) -> 7.496182e+18 | F149: Danny Enxovais | G149: =_xlfn.XLOOKUP(C149,'Same Seller Hist'!E:E,'Same Seller Hist'!F:F) -> Lifestyle | H149: =_xlfn.IFNA(_xlfn.XLOOKUP(C149,'Shp 500'!D:D,'Shp 500'!I:I),0) -> 0 | I149: =_xlfn.IFNA(_xlfn.XLOOKUP(C149,'Shp 500'!D:D,'Shp 500'!J:J),0) -> 0 | J149: 1625.8065 | K149: 41935.484 | L149: Fastmoss 500 | M149: =IF(L149="Shp 500","Sim",IF(ISNA(_xlfn.XLOOKUP(C149,'Shp 500'!D:D,'Shp 500'!D:D)),"Não","Sim")) -> Não | N149: =IF(L149="Fastmoss 500","Sim",IF(ISNA(_xlfn.XLOOKUP(_xlfn.XLOOKUP(C149,'Same Seller Hist'!E:E,'Same Seller Hist'!H:H),'Fastmoss 500'!D:D,'Fastmoss 500'!D:D)),"Não","Sim")) -> Sim | O149: =IF(AND(M149="Sim",N149="Sim"),"Sim","Não") -> Não | P149: =IF(I149>K149,"Sim","Não") -> Não | Q149: =COUNTIFS(C:C,C149) -> 1
C150: 681570887 | D150: AMOBELEZA | E150: =_xlfn.XLOOKUP(C150,'Same Seller Hist'!E:E,'Same Seller Hist'!I:I) -> 7.4961605e+18 | F150: =_xlfn.XLOOKUP(C150,'Same Seller Hist'!E:E,'Same Seller Hist'!H:H) -> AMOBELEZA | G150: FMCG | H150: 1301 | I150: 15469.541 | J150: =_xlfn.IFNA(_xlfn.XLOOKUP(F150,'Fastmoss 500'!D:D,'Fastmoss 500'!O:O),0) -> 332.25806 | K150: =_xlfn.IFNA(_xlfn.XLOOKUP(F150,'Fastmoss 500'!D:D,'Fastmoss 500'!N:N),0) -> 35483.871 | L150: Shp 500 | M150: =IF(L150="Shp 500","Sim",IF(ISNA(_xlfn.XLOOKUP(C150,'Shp 500'!D:D,'Shp 500'!D:D)),"Não","Sim")) -> Sim | N150: =IF(L150="Fastmoss 500","Sim",IF(ISNA(_xlfn.XLOOKUP(_xlfn.XLOOKUP(C150,'Same Seller Hist'!E:E,'Same Seller Hist'!H:H),'Fastmoss 500'!D:D,'Fastmoss 500'!D:D)),"Não","Sim")) -> Sim | O150: =IF(AND(M150="Sim",N150="Sim"),"Sim","Não") -> Sim | P150: =IF(I150>K150,"Sim","Não") -> Não | Q150: =COUNTIFS(C:C,C150) -> 1
C151: =_xlfn.XLOOKUP(F151,'Same Seller Hist'!H:H,'Same Seller Hist'!E:E) -> 1340867165 | D151: =_xlfn.XLOOKUP(F151,'Same Seller Hist'!H:H,'Same Seller Hist'!D:D) -> LINISO SHOP | E151: =_xlfn.XLOOKUP(F151,'Same Seller Hist'!H:H,'Same Seller Hist'!I:I) -> 7.4962125e+18 | F151: LINISO SHOP | G151: =_xlfn.XLOOKUP(C151,'Same Seller Hist'!E:E,'Same Seller Hist'!F:F) -> Fashion | H151: =_xlfn.IFNA(_xlfn.XLOOKUP(C151,'Shp 500'!D:D,'Shp 500'!I:I),0) -> 0 | I151: =_xlfn.IFNA(_xlfn.XLOOKUP(C151,'Shp 500'!D:D,'Shp 500'!J:J),0) -> 0 | J151: 1248.3871 | K151: 41935.484 | L151: Fastmoss 500 | M151: =IF(L151="Shp 500","Sim",IF(ISNA(_xlfn.XLOOKUP(C151,'Shp 500'!D:D,'Shp 500'!D:D)),"Não","Sim")) -> Não | N151: =IF(L151="Fastmoss 500","Sim",IF(ISNA(_xlfn.XLOOKUP(_xlfn.XLOOKUP(C151,'Same Seller Hist'!E:E,'Same Seller Hist'!H:H),'Fastmoss 500'!D:D,'Fastmoss 500'!D:D)),"Não","Sim")) -> Sim | O151: =IF(AND(M151="Sim",N151="Sim"),"Sim","Não") -> Não | P151: =IF(I151>K151,"Sim","Não") -> Não | Q151: =COUNTIFS(C:C,C151) -> 1
C152: =_xlfn.XLOOKUP(F152,'Same Seller Hist'!H:H,'Same Seller Hist'!E:E) -> 1504994084 | D152: =_xlfn.XLOOKUP(F152,'Same Seller Hist'!H:H,'Same Seller Hist'!D:D) -> QVida MIX | E152: =_xlfn.XLOOKUP(F152,'Same Seller Hist'!H:H,'Same Seller Hist'!I:I) -> 7.4962708e+18 | F152: QVida MIX | G152: =_xlfn.XLOOKUP(C152,'Same Seller Hist'!E:E,'Same Seller Hist'!F:F) -> Fashion | H152: =_xlfn.IFNA(_xlfn.XLOOKUP(C152,'Shp 500'!D:D,'Shp 500'!I:I),0) -> 0 | I152: =_xlfn.IFNA(_xlfn.XLOOKUP(C152,'Shp 500'!D:D,'Shp 500'!J:J),0) -> 0 | J152: 1154.8387 | K152: 32258.065 | L152: Fastmoss 500 | M152: =IF(L152="Shp 500","Sim",IF(ISNA(_xlfn.XLOOKUP(C152,'Shp 500'!D:D,'Shp 500'!D:D)),"Não","Sim")) -> Não | N152: =IF(L152="Fastmoss 500","Sim",IF(ISNA(_xlfn.XLOOKUP(_xlfn.XLOOKUP(C152,'Same Seller Hist'!E:E,'Same Seller Hist'!H:H),'Fastmoss 500'!D:D,'Fastmoss 500'!D:D)),"Não","Sim")) -> Sim | O152: =IF(AND(M152="Sim",N152="Sim"),"Sim","Não") -> Não | P152: =IF(I152>K152,"Sim","Não") -> Não | Q152: =COUNTIFS(C:C,C152) -> 1
C153: =_xlfn.XLOOKUP(F153,'Same Seller Hist'!H:H,'Same Seller Hist'!E:E) -> 283972864 | D153: =_xlfn.XLOOKUP(F153,'Same Seller Hist'!H:H,'Same Seller Hist'!D:D) -> Moderna e Slim | E153: =_xlfn.XLOOKUP(F153,'Same Seller Hist'!H:H,'Same Seller Hist'!I:I) -> 7.4961518e+18 | F153: Moderna e Slim | G153: =_xlfn.XLOOKUP(C153,'Same Seller Hist'!E:E,'Same Seller Hist'!F:F) -> Fashion | H153: =_xlfn.IFNA(_xlfn.XLOOKUP(C153,'Shp 500'!D:D,'Shp 500'!I:I),0) -> 0 | I153: =_xlfn.IFNA(_xlfn.XLOOKUP(C153,'Shp 500'!D:D,'Shp 500'!J:J),0) -> 0 | J153: 1145.1613 | K153: 51612.903 | L153: Fastmoss 500 | M153: =IF(L153="Shp 500","Sim",IF(ISNA(_xlfn.XLOOKUP(C153,'Shp 500'!D:D,'Shp 500'!D:D)),"Não","Sim")) -> Não | N153: =IF(L153="Fastmoss 500","Sim",IF(ISNA(_xlfn.XLOOKUP(_xlfn.XLOOKUP(C153,'Same Seller Hist'!E:E,'Same Seller Hist'!H:H),'Fastmoss 500'!D:D,'Fastmoss 500'!D:D)),"Não","Sim")) -> Sim | O153: =IF(AND(M153="Sim",N153="Sim"),"Sim","Não") -> Não | P153: =IF(I153>K153,"Sim","Não") -> Não | Q153: =COUNTIFS(C:C,C153) -> 1
C154: 717396632 | D154: Ankco Shop | E154: =_xlfn.XLOOKUP(C154,'Same Seller Hist'!E:E,'Same Seller Hist'!I:I) -> 7.4961532e+18 | F154: =_xlfn.XLOOKUP(C154,'Same Seller Hist'!E:E,'Same Seller Hist'!H:H) -> AnkcoShopTK | G154: CN | H154: 1742.4194 | I154: 17676.971 | J154: =_xlfn.IFNA(_xlfn.XLOOKUP(F154,'Fastmoss 500'!D:D,'Fastmoss 500'!O:O),0) -> 258.06452 | K154: =_xlfn.IFNA(_xlfn.XLOOKUP(F154,'Fastmoss 500'!D:D,'Fastmoss 500'!N:N),0) -> 14974.194 | L154: Shp 500 | M154: =IF(L154="Shp 500","Sim",IF(ISNA(_xlfn.XLOOKUP(C154,'Shp 500'!D:D,'Shp 500'!D:D)),"Não","Sim")) -> Sim | N154: =IF(L154="Fastmoss 500","Sim",IF(ISNA(_xlfn.XLOOKUP(_xlfn.XLOOKUP(C154,'Same Seller Hist'!E:E,'Same Seller Hist'!H:H),'Fastmoss 500'!D:D,'Fastmoss 500'!D:D)),"Não","Sim")) -> Sim | O154: =IF(AND(M154="Sim",N154="Sim"),"Sim","Não") -> Sim | P154: =IF(I154>K154,"Sim","Não") -> Sim | Q154: =COUNTIFS(C:C,C154) -> 1
C155: =_xlfn.XLOOKUP(F155,'Same Seller Hist'!H:H,'Same Seller Hist'!E:E) -> 452872883 | D155: =_xlfn.XLOOKUP(F155,'Same Seller Hist'!H:H,'Same Seller Hist'!D:D) -> TomiMitoo | E155: =_xlfn.XLOOKUP(F155,'Same Seller Hist'!H:H,'Same Seller Hist'!I:I) -> 7.4961645e+18 | F155: TomiMitoo | G155: =_xlfn.XLOOKUP(C155,'Same Seller Hist'!E:E,'Same Seller Hist'!F:F) -> Fashion | H155: =_xlfn.IFNA(_xlfn.XLOOKUP(C155,'Shp 500'!D:D,'Shp 500'!I:I),0) -> 0 | I155: =_xlfn.IFNA(_xlfn.XLOOKUP(C155,'Shp 500'!D:D,'Shp 500'!J:J),0) -> 0 | J155: 1103.2258 | K155: 161290.32 | L155: Fastmoss 500 | M155: =IF(L155="Shp 500","Sim",IF(ISNA(_xlfn.XLOOKUP(C155,'Shp 500'!D:D,'Shp 500'!D:D)),"Não","Sim")) -> Não | N155: =IF(L155="Fastmoss 500","Sim",IF(ISNA(_xlfn.XLOOKUP(_xlfn.XLOOKUP(C155,'Same Seller Hist'!E:E,'Same Seller Hist'!H:H),'Fastmoss 500'!D:D,'Fastmoss 500'!D:D)),"Não","Sim")) -> Sim | O155: =IF(AND(M155="Sim",N155="Sim"),"Sim","Não") -> Não | P155: =IF(I155>K155,"Sim","Não") -> Não | Q155: =COUNTIFS(C:C,C155) -> 1
C156: =_xlfn.XLOOKUP(F156,'Same Seller Hist'!H:H,'Same Seller Hist'!E:E) -> 1613760239 | D156: =_xlfn.XLOOKUP(F156,'Same Seller Hist'!H:H,'Same Seller Hist'!D:D) -> SACE LADY BR | E156: =_xlfn.XLOOKUP(F156,'Same Seller Hist'!H:H,'Same Seller Hist'!I:I) -> 7.4962591e+18 | F156: SACE LADY BR | G156: =_xlfn.XLOOKUP(C156,'Same Seller Hist'!E:E,'Same Seller Hist'!F:F) -> FMCG | H156: =_xlfn.IFNA(_xlfn.XLOOKUP(C156,'Shp 500'!D:D,'Shp 500'!I:I),0) -> 0 | I156: =_xlfn.IFNA(_xlfn.XLOOKUP(C156,'Shp 500'!D:D,'Shp 500'!J:J),0) -> 0 | J156: 1035.4839 | K156: 61290.323 | L156: Fastmoss 500 | M156: =IF(L156="Shp 500","Sim",IF(ISNA(_xlfn.XLOOKUP(C156,'Shp 500'!D:D,'Shp 500'!D:D)),"Não","Sim")) -> Não | N156: =IF(L156="Fastmoss 500","Sim",IF(ISNA(_xlfn.XLOOKUP(_xlfn.XLOOKUP(C156,'Same Seller Hist'!E:E,'Same Seller Hist'!H:H),'Fastmoss 500'!D:D,'Fastmoss 500'!D:D)),"Não","Sim")) -> Sim | O156: =IF(AND(M156="Sim",N156="Sim"),"Sim","Não") -> Não | P156: =IF(I156>K156,"Sim","Não") -> Não | Q156: =COUNTIFS(C:C,C156) -> 1
C157: 728534865 | D157: FENG . | E157: =_xlfn.XLOOKUP(C157,'Same Seller Hist'!E:E,'Same Seller Hist'!I:I) -> 7.4961617e+18 | F157: =_xlfn.XLOOKUP(C157,'Same Seller Hist'!E:E,'Same Seller Hist'!H:H) -> Feng.s | G157: CN | H157: 1769.7419 | I157: 8488.8464 | J157: =_xlfn.IFNA(_xlfn.XLOOKUP(F157,'Fastmoss 500'!D:D,'Fastmoss 500'!O:O),0) -> 745.16129 | K157: =_xlfn.IFNA(_xlfn.XLOOKUP(F157,'Fastmoss 500'!D:D,'Fastmoss 500'!N:N),0) -> 26819.355 | L157: Shp 500 | M157: =IF(L157="Shp 500","Sim",IF(ISNA(_xlfn.XLOOKUP(C157,'Shp 500'!D:D,'Shp 500'!D:D)),"Não","Sim")) -> Sim | N157: =IF(L157="Fastmoss 500","Sim",IF(ISNA(_xlfn.XLOOKUP(_xlfn.XLOOKUP(C157,'Same Seller Hist'!E:E,'Same Seller Hist'!H:H),'Fastmoss 500'!D:D,'Fastmoss 500'!D:D)),"Não","Sim")) -> Sim | O157: =IF(AND(M157="Sim",N157="Sim"),"Sim","Não") -> Sim | P157: =IF(I157>K157,"Sim","Não") -> Não | Q157: =COUNTIFS(C:C,C157) -> 1
C158: =_xlfn.XLOOKUP(F158,'Same Seller Hist'!H:H,'Same Seller Hist'!E:E) -> 969401129 | D158: =_xlfn.XLOOKUP(F158,'Same Seller Hist'!H:H,'Same Seller Hist'!D:D) -> Pink Urban | E158: =_xlfn.XLOOKUP(F158,'Same Seller Hist'!H:H,'Same Seller Hist'!I:I) -> 7.4956253e+18 | F158: Pink Urban | G158: =_xlfn.XLOOKUP(C158,'Same Seller Hist'!E:E,'Same Seller Hist'!F:F) -> Fashion | H158: =_xlfn.IFNA(_xlfn.XLOOKUP(C158,'Shp 500'!D:D,'Shp 500'!I:I),0) -> 0 | I158: =_xlfn.IFNA(_xlfn.XLOOKUP(C158,'Shp 500'!D:D,'Shp 500'!J:J),0) -> 0 | J158: 1035.4839 | K158: 58064.516 | L158: Fastmoss 500 | M158: =IF(L158="Shp 500","Sim",IF(ISNA(_xlfn.XLOOKUP(C158,'Shp 500'!D:D,'Shp 500'!D:D)),"Não","Sim")) -> Não | N158: =IF(L158="Fastmoss 500","Sim",IF(ISNA(_xlfn.XLOOKUP(_xlfn.XLOOKUP(C158,'Same Seller Hist'!E:E,'Same Seller Hist'!H:H),'Fastmoss 500'!D:D,'Fastmoss 500'!D:D)),"Não","Sim")) -> Sim | O158: =IF(AND(M158="Sim",N158="Sim"),"Sim","Não") -> Não | P158: =IF(I158>K158,"Sim","Não") -> Não | Q158: =COUNTIFS(C:C,C158) -> 1
C159: =_xlfn.XLOOKUP(F159,'Same Seller Hist'!H:H,'Same Seller Hist'!E:E) -> 999698643 | D159: =_xlfn.XLOOKUP(F159,'Same Seller Hist'!H:H,'Same Seller Hist'!D:D) -> Trevisan Calcados | E159: =_xlfn.XLOOKUP(F159,'Same Seller Hist'!H:H,'Same Seller Hist'!I:I) -> 7.496182e+18 | F159: Trevisan Calcados | G159: =_xlfn.XLOOKUP(C159,'Same Seller Hist'!E:E,'Same Seller Hist'!F:F) -> Fashion | H159: =_xlfn.IFNA(_xlfn.XLOOKUP(C159,'Shp 500'!D:D,'Shp 500'!I:I),0) -> 0 | I159: =_xlfn.IFNA(_xlfn.XLOOKUP(C159,'Shp 500'!D:D,'Shp 500'!J:J),0) -> 0 | J159: 1003.2258 | K159: 32258.065 | L159: Fastmoss 500 | M159: =IF(L159="Shp 500","Sim",IF(ISNA(_xlfn.XLOOKUP(C159,'Shp 500'!D:D,'Shp 500'!D:D)),"Não","Sim")) -> Não | N159: =IF(L159="Fastmoss 500","Sim",IF(ISNA(_xlfn.XLOOKUP(_xlfn.XLOOKUP(C159,'Same Seller Hist'!E:E,'Same Seller Hist'!H:H),'Fastmoss 500'!D:D,'Fastmoss 500'!D:D)),"Não","Sim")) -> Sim | O159: =IF(AND(M159="Sim",N159="Sim"),"Sim","Não") -> Não | P159: =IF(I159>K159,"Sim","Não") -> Não | Q159: =COUNTIFS(C:C,C159) -> 1
C160: =_xlfn.XLOOKUP(F160,'Same Seller Hist'!H:H,'Same Seller Hist'!E:E) -> 1077804858 | D160: =_xlfn.XLOOKUP(F160,'Same Seller Hist'!H:H,'Same Seller Hist'!D:D) -> Amend Cosméticos | E160: =_xlfn.XLOOKUP(F160,'Same Seller Hist'!H:H,'Same Seller Hist'!I:I) -> 7.4961615e+18 | F160: Amend Cosméticos | G160: =_xlfn.XLOOKUP(C160,'Same Seller Hist'!E:E,'Same Seller Hist'!F:F) -> FMCG | H160: =_xlfn.IFNA(_xlfn.XLOOKUP(C160,'Shp 500'!D:D,'Shp 500'!I:I),0) -> 0 | I160: =_xlfn.IFNA(_xlfn.XLOOKUP(C160,'Shp 500'!D:D,'Shp 500'!J:J),0) -> 0 | J160: 990.32258 | K160: 48387.097 | L160: Fastmoss 500 | M160: =IF(L160="Shp 500","Sim",IF(ISNA(_xlfn.XLOOKUP(C160,'Shp 500'!D:D,'Shp 500'!D:D)),"Não","Sim")) -> Não | N160: =IF(L160="Fastmoss 500","Sim",IF(ISNA(_xlfn.XLOOKUP(_xlfn.XLOOKUP(C160,'Same Seller Hist'!E:E,'Same Seller Hist'!H:H),'Fastmoss 500'!D:D,'Fastmoss 500'!D:D)),"Não","Sim")) -> Sim | O160: =IF(AND(M160="Sim",N160="Sim"),"Sim","Não") -> Não | P160: =IF(I160>K160,"Sim","Não") -> Não | Q160: =COUNTIFS(C:C,C160) -> 1
C161: 831272734 | D161: USE AD LINGERIE | E161: =_xlfn.XLOOKUP(C161,'Same Seller Hist'!E:E,'Same Seller Hist'!I:I) -> 7.494146e+18 | F161: =_xlfn.XLOOKUP(C161,'Same Seller Hist'!E:E,'Same Seller Hist'!H:H) -> AD LINGERIE | G161: Fashion | H161: 1124.3226 | I161: 7519.476 | J161: =_xlfn.IFNA(_xlfn.XLOOKUP(F161,'Fastmoss 500'!D:D,'Fastmoss 500'!O:O),0) -> 374.19355 | K161: =_xlfn.IFNA(_xlfn.XLOOKUP(F161,'Fastmoss 500'!D:D,'Fastmoss 500'!N:N),0) -> 14780.645 | L161: Shp 500 | M161: =IF(L161="Shp 500","Sim",IF(ISNA(_xlfn.XLOOKUP(C161,'Shp 500'!D:D,'Shp 500'!D:D)),"Não","Sim")) -> Sim | N161: =IF(L161="Fastmoss 500","Sim",IF(ISNA(_xlfn.XLOOKUP(_xlfn.XLOOKUP(C161,'Same Seller Hist'!E:E,'Same Seller Hist'!H:H),'Fastmoss 500'!D:D,'Fastmoss 500'!D:D)),"Não","Sim")) -> Sim | O161: =IF(AND(M161="Sim",N161="Sim"),"Sim","Não") -> Sim | P161: =IF(I161>K161,"Sim","Não") -> Não | Q161: =COUNTIFS(C:C,C161) -> 1
C162: =_xlfn.XLOOKUP(F162,'Same Seller Hist'!H:H,'Same Seller Hist'!E:E) -> 1609741857 | D162: =_xlfn.XLOOKUP(F162,'Same Seller Hist'!H:H,'Same Seller Hist'!D:D) -> Bloom Body Br | E162: =_xlfn.XLOOKUP(F162,'Same Seller Hist'!H:H,'Same Seller Hist'!I:I) -> 7.4961818e+18 | F162: Bloom Body Br | G162: =_xlfn.XLOOKUP(C162,'Same Seller Hist'!E:E,'Same Seller Hist'!F:F) -> FMCG | H162: =_xlfn.IFNA(_xlfn.XLOOKUP(C162,'Shp 500'!D:D,'Shp 500'!I:I),0) -> 0 | I162: =_xlfn.IFNA(_xlfn.XLOOKUP(C162,'Shp 500'!D:D,'Shp 500'!J:J),0) -> 0 | J162: 958.06452 | K162: 80645.161 | L162: Fastmoss 500 | M162: =IF(L162="Shp 500","Sim",IF(ISNA(_xlfn.XLOOKUP(C162,'Shp 500'!D:D,'Shp 500'!D:D)),"Não","Sim")) -> Não | N162: =IF(L162="Fastmoss 500","Sim",IF(ISNA(_xlfn.XLOOKUP(_xlfn.XLOOKUP(C162,'Same Seller Hist'!E:E,'Same Seller Hist'!H:H),'Fastmoss 500'!D:D,'Fastmoss 500'!D:D)),"Não","Sim")) -> Sim | O162: =IF(AND(M162="Sim",N162="Sim"),"Sim","Não") -> Não | P162: =IF(I162>K162,"Sim","Não") -> Não | Q162: =COUNTIFS(C:C,C162) -> 1
C163: =_xlfn.XLOOKUP(F163,'Same Seller Hist'!H:H,'Same Seller Hist'!E:E) -> 1524383764 | D163: =_xlfn.XLOOKUP(F163,'Same Seller Hist'!H:H,'Same Seller Hist'!D:D) -> KOBAC SHOP | E163: =_xlfn.XLOOKUP(F163,'Same Seller Hist'!H:H,'Same Seller Hist'!I:I) -> 7.4961832e+18 | F163: KOBAC SHOP | G163: =_xlfn.XLOOKUP(C163,'Same Seller Hist'!E:E,'Same Seller Hist'!F:F) -> 0 | H163: =_xlfn.IFNA(_xlfn.XLOOKUP(C163,'Shp 500'!D:D,'Shp 500'!I:I),0) -> 0 | I163: =_xlfn.IFNA(_xlfn.XLOOKUP(C163,'Shp 500'!D:D,'Shp 500'!J:J),0) -> 0 | J163: 954.83871 | K163: 13158.065 | L163: Fastmoss 500 | M163: =IF(L163="Shp 500","Sim",IF(ISNA(_xlfn.XLOOKUP(C163,'Shp 500'!D:D,'Shp 500'!D:D)),"Não","Sim")) -> Não | N163: =IF(L163="Fastmoss 500","Sim",IF(ISNA(_xlfn.XLOOKUP(_xlfn.XLOOKUP(C163,'Same Seller Hist'!E:E,'Same Seller Hist'!H:H),'Fastmoss 500'!D:D,'Fastmoss 500'!D:D)),"Não","Sim")) -> Sim | O163: =IF(AND(M163="Sim",N163="Sim"),"Sim","Não") -> Não | P163: =IF(I163>K163,"Sim","Não") -> Não | Q163: =COUNTIFS(C:C,C163) -> 1
C164: 874603044 | D164: SUPER CHETO | E164: =_xlfn.XLOOKUP(C164,'Same Seller Hist'!E:E,'Same Seller Hist'!I:I) -> 7.4962295e+18 | F164: =_xlfn.XLOOKUP(C164,'Same Seller Hist'!E:E,'Same Seller Hist'!H:H) -> SUPER CHETO | G164: CN | H164: 4215.5484 | I164: 37209.63 | J164: =_xlfn.IFNA(_xlfn.XLOOKUP(F164,'Fastmoss 500'!D:D,'Fastmoss 500'!O:O),0) -> 487.09677 | K164: =_xlfn.IFNA(_xlfn.XLOOKUP(F164,'Fastmoss 500'!D:D,'Fastmoss 500'!N:N),0) -> 35483.871 | L164: Shp 500 | M164: =IF(L164="Shp 500","Sim",IF(ISNA(_xlfn.XLOOKUP(C164,'Shp 500'!D:D,'Shp 500'!D:D)),"Não","Sim")) -> Sim | N164: =IF(L164="Fastmoss 500","Sim",IF(ISNA(_xlfn.XLOOKUP(_xlfn.XLOOKUP(C164,'Same Seller Hist'!E:E,'Same Seller Hist'!H:H),'Fastmoss 500'!D:D,'Fastmoss 500'!D:D)),"Não","Sim")) -> Sim | O164: =IF(AND(M164="Sim",N164="Sim"),"Sim","Não") -> Sim | P164: =IF(I164>K164,"Sim","Não") -> Sim | Q164: =COUNTIFS(C:C,C164) -> 1
C165: =_xlfn.XLOOKUP(F165,'Same Seller Hist'!H:H,'Same Seller Hist'!E:E) -> 1562142458 | D165: =_xlfn.XLOOKUP(F165,'Same Seller Hist'!H:H,'Same Seller Hist'!D:D) -> One Shop Ltda | E165: =_xlfn.XLOOKUP(F165,'Same Seller Hist'!H:H,'Same Seller Hist'!I:I) -> 7.49418e+18 | F165: One Shop Ltda | G165: =_xlfn.XLOOKUP(C165,'Same Seller Hist'!E:E,'Same Seller Hist'!F:F) -> 0 | H165: =_xlfn.IFNA(_xlfn.XLOOKUP(C165,'Shp 500'!D:D,'Shp 500'!I:I),0) -> 0 | I165: =_xlfn.IFNA(_xlfn.XLOOKUP(C165,'Shp 500'!D:D,'Shp 500'!J:J),0) -> 0 | J165: 903.22581 | K165: 35483.871 | L165: Fastmoss 500 | M165: =IF(L165="Shp 500","Sim",IF(ISNA(_xlfn.XLOOKUP(C165,'Shp 500'!D:D,'Shp 500'!D:D)),"Não","Sim")) -> Não | N165: =IF(L165="Fastmoss 500","Sim",IF(ISNA(_xlfn.XLOOKUP(_xlfn.XLOOKUP(C165,'Same Seller Hist'!E:E,'Same Seller Hist'!H:H),'Fastmoss 500'!D:D,'Fastmoss 500'!D:D)),"Não","Sim")) -> Sim | O165: =IF(AND(M165="Sim",N165="Sim"),"Sim","Não") -> Não | P165: =IF(I165>K165,"Sim","Não") -> Não | Q165: =COUNTIFS(C:C,C165) -> 1
C166: =_xlfn.XLOOKUP(F166,'Same Seller Hist'!H:H,'Same Seller Hist'!E:E) -> 1220492895 | D166: =_xlfn.XLOOKUP(F166,'Same Seller Hist'!H:H,'Same Seller Hist'!D:D) -> Han Maquiagem | E166: =_xlfn.XLOOKUP(F166,'Same Seller Hist'!H:H,'Same Seller Hist'!I:I) -> 7.4942101e+18 | F166: Han Maquiagem | G166: =_xlfn.XLOOKUP(C166,'Same Seller Hist'!E:E,'Same Seller Hist'!F:F) -> 0 | H166: =_xlfn.IFNA(_xlfn.XLOOKUP(C166,'Shp 500'!D:D,'Shp 500'!I:I),0) -> 0 | I166: =_xlfn.IFNA(_xlfn.XLOOKUP(C166,'Shp 500'!D:D,'Shp 500'!J:J),0) -> 0 | J166: 874.19355 | K166: 11312.903 | L166: Fastmoss 500 | M166: =IF(L166="Shp 500","Sim",IF(ISNA(_xlfn.XLOOKUP(C166,'Shp 500'!D:D,'Shp 500'!D:D)),"Não","Sim")) -> Não | N166: =IF(L166="Fastmoss 500","Sim",IF(ISNA(_xlfn.XLOOKUP(_xlfn.XLOOKUP(C166,'Same Seller Hist'!E:E,'Same Seller Hist'!H:H),'Fastmoss 500'!D:D,'Fastmoss 500'!D:D)),"Não","Sim")) -> Sim | O166: =IF(AND(M166="Sim",N166="Sim"),"Sim","Não") -> Não | P166: =IF(I166>K166,"Sim","Não") -> Não | Q166: =COUNTIFS(C:C,C166) -> 1
C167: =_xlfn.XLOOKUP(F167,'Same Seller Hist'!H:H,'Same Seller Hist'!E:E) -> 1198407784 | D167: =_xlfn.XLOOKUP(F167,'Same Seller Hist'!H:H,'Same Seller Hist'!D:D) -> ROMANTIC CROWN | E167: =_xlfn.XLOOKUP(F167,'Same Seller Hist'!H:H,'Same Seller Hist'!I:I) -> 7.4961811e+18 | F167: ROMANTIC CROWN | G167: =_xlfn.XLOOKUP(C167,'Same Seller Hist'!E:E,'Same Seller Hist'!F:F) -> Lifestyle | H167: =_xlfn.IFNA(_xlfn.XLOOKUP(C167,'Shp 500'!D:D,'Shp 500'!I:I),0) -> 0 | I167: =_xlfn.IFNA(_xlfn.XLOOKUP(C167,'Shp 500'!D:D,'Shp 500'!J:J),0) -> 0 | J167: 874.19355 | K167: 54838.71 | L167: Fastmoss 500 | M167: =IF(L167="Shp 500","Sim",IF(ISNA(_xlfn.XLOOKUP(C167,'Shp 500'!D:D,'Shp 500'!D:D)),"Não","Sim")) -> Não | N167: =IF(L167="Fastmoss 500","Sim",IF(ISNA(_xlfn.XLOOKUP(_xlfn.XLOOKUP(C167,'Same Seller Hist'!E:E,'Same Seller Hist'!H:H),'Fastmoss 500'!D:D,'Fastmoss 500'!D:D)),"Não","Sim")) -> Sim | O167: =IF(AND(M167="Sim",N167="Sim"),"Sim","Não") -> Não | P167: =IF(I167>K167,"Sim","Não") -> Não | Q167: =COUNTIFS(C:C,C167) -> 1
C168: 883941882 | D168: yiyiyi | E168: =_xlfn.XLOOKUP(C168,'Same Seller Hist'!E:E,'Same Seller Hist'!I:I) -> 7.4962037e+18 | F168: =_xlfn.XLOOKUP(C168,'Same Seller Hist'!E:E,'Same Seller Hist'!H:H) -> yiyiyi TK | G168: CN | H168: 2238.0323 | I168: 19958.814 | J168: =_xlfn.IFNA(_xlfn.XLOOKUP(F168,'Fastmoss 500'!D:D,'Fastmoss 500'!O:O),0) -> 1577.4194 | K168: =_xlfn.IFNA(_xlfn.XLOOKUP(F168,'Fastmoss 500'!D:D,'Fastmoss 500'!N:N),0) -> 41935.484 | L168: Shp 500 | M168: =IF(L168="Shp 500","Sim",IF(ISNA(_xlfn.XLOOKUP(C168,'Shp 500'!D:D,'Shp 500'!D:D)),"Não","Sim")) -> Sim | N168: =IF(L168="Fastmoss 500","Sim",IF(ISNA(_xlfn.XLOOKUP(_xlfn.XLOOKUP(C168,'Same Seller Hist'!E:E,'Same Seller Hist'!H:H),'Fastmoss 500'!D:D,'Fastmoss 500'!D:D)),"Não","Sim")) -> Sim | O168: =IF(AND(M168="Sim",N168="Sim"),"Sim","Não") -> Sim | P168: =IF(I168>K168,"Sim","Não") -> Não | Q168: =COUNTIFS(C:C,C168) -> 1
C169: =_xlfn.XLOOKUP(F169,'Same Seller Hist'!H:H,'Same Seller Hist'!E:E) -> 434178148 | D169: =_xlfn.XLOOKUP(F169,'Same Seller Hist'!H:H,'Same Seller Hist'!D:D) -> Nação Verde | E169: =_xlfn.XLOOKUP(F169,'Same Seller Hist'!H:H,'Same Seller Hist'!I:I) -> 7.4961819e+18 | F169: Nação Verde | G169: =_xlfn.XLOOKUP(C169,'Same Seller Hist'!E:E,'Same Seller Hist'!F:F) -> FMCG | H169: =_xlfn.IFNA(_xlfn.XLOOKUP(C169,'Shp 500'!D:D,'Shp 500'!I:I),0) -> 0 | I169: =_xlfn.IFNA(_xlfn.XLOOKUP(C169,'Shp 500'!D:D,'Shp 500'!J:J),0) -> 0 | J169: 851.6129 | K169: 30006.452 | L169: Fastmoss 500 | M169: =IF(L169="Shp 500","Sim",IF(ISNA(_xlfn.XLOOKUP(C169,'Shp 500'!D:D,'Shp 500'!D:D)),"Não","Sim")) -> Não | N169: =IF(L169="Fastmoss 500","Sim",IF(ISNA(_xlfn.XLOOKUP(_xlfn.XLOOKUP(C169,'Same Seller Hist'!E:E,'Same Seller Hist'!H:H),'Fastmoss 500'!D:D,'Fastmoss 500'!D:D)),"Não","Sim")) -> Sim | O169: =IF(AND(M169="Sim",N169="Sim"),"Sim","Não") -> Não | P169: =IF(I169>K169,"Sim","Não") -> Não | Q169: =COUNTIFS(C:C,C169) -> 1
C170: =_xlfn.XLOOKUP(F170,'Same Seller Hist'!H:H,'Same Seller Hist'!E:E) -> 689225278 | D170: =_xlfn.XLOOKUP(F170,'Same Seller Hist'!H:H,'Same Seller Hist'!D:D) -> L'Oréal Paris Brasil | E170: =_xlfn.XLOOKUP(F170,'Same Seller Hist'!H:H,'Same Seller Hist'!I:I) -> 7.496204e+18 | F170: L'Oréal Paris Brasil | G170: =_xlfn.XLOOKUP(C170,'Same Seller Hist'!E:E,'Same Seller Hist'!F:F) -> FMCG | H170: =_xlfn.IFNA(_xlfn.XLOOKUP(C170,'Shp 500'!D:D,'Shp 500'!I:I),0) -> 0 | I170: =_xlfn.IFNA(_xlfn.XLOOKUP(C170,'Shp 500'!D:D,'Shp 500'!J:J),0) -> 0 | J170: 835.48387 | K170: 51612.903 | L170: Fastmoss 500 | M170: =IF(L170="Shp 500","Sim",IF(ISNA(_xlfn.XLOOKUP(C170,'Shp 500'!D:D,'Shp 500'!D:D)),"Não","Sim")) -> Não | N170: =IF(L170="Fastmoss 500","Sim",IF(ISNA(_xlfn.XLOOKUP(_xlfn.XLOOKUP(C170,'Same Seller Hist'!E:E,'Same Seller Hist'!H:H),'Fastmoss 500'!D:D,'Fastmoss 500'!D:D)),"Não","Sim")) -> Sim | O170: =IF(AND(M170="Sim",N170="Sim"),"Sim","Não") -> Não | P170: =IF(I170>K170,"Sim","Não") -> Não | Q170: =COUNTIFS(C:C,C170) -> 1
C171: =_xlfn.XLOOKUP(F171,'Same Seller Hist'!H:H,'Same Seller Hist'!E:E) -> 498340093 | D171: =_xlfn.XLOOKUP(F171,'Same Seller Hist'!H:H,'Same Seller Hist'!D:D) -> BRASTOY BR | E171: =_xlfn.XLOOKUP(F171,'Same Seller Hist'!H:H,'Same Seller Hist'!I:I) -> 7.4941276e+18 | F171: BRASTOY BR | G171: =_xlfn.XLOOKUP(C171,'Same Seller Hist'!E:E,'Same Seller Hist'!F:F) -> Lifestyle | H171: =_xlfn.IFNA(_xlfn.XLOOKUP(C171,'Shp 500'!D:D,'Shp 500'!I:I),0) -> 0 | I171: =_xlfn.IFNA(_xlfn.XLOOKUP(C171,'Shp 500'!D:D,'Shp 500'!J:J),0) -> 0 | J171: 803.22581 | K171: 129032.26 | L171: Fastmoss 500 | M171: =IF(L171="Shp 500","Sim",IF(ISNA(_xlfn.XLOOKUP(C171,'Shp 500'!D:D,'Shp 500'!D:D)),"Não","Sim")) -> Não | N171: =IF(L171="Fastmoss 500","Sim",IF(ISNA(_xlfn.XLOOKUP(_xlfn.XLOOKUP(C171,'Same Seller Hist'!E:E,'Same Seller Hist'!H:H),'Fastmoss 500'!D:D,'Fastmoss 500'!D:D)),"Não","Sim")) -> Sim | O171: =IF(AND(M171="Sim",N171="Sim"),"Sim","Não") -> Não | P171: =IF(I171>K171,"Sim","Não") -> Não | Q171: =COUNTIFS(C:C,C171) -> 1
C172: 944725778 | D172: Inovar Top | E172: =_xlfn.XLOOKUP(C172,'Same Seller Hist'!E:E,'Same Seller Hist'!I:I) -> 7.4961617e+18 | F172: =_xlfn.XLOOKUP(C172,'Same Seller Hist'!E:E,'Same Seller Hist'!H:H) -> Happy Loja | G172: CN | H172: 1339.871 | I172: 5867.8155 | J172: =_xlfn.IFNA(_xlfn.XLOOKUP(F172,'Fastmoss 500'!D:D,'Fastmoss 500'!O:O),0) -> 1000 | K172: =_xlfn.IFNA(_xlfn.XLOOKUP(F172,'Fastmoss 500'!D:D,'Fastmoss 500'!N:N),0) -> 24296.774 | L172: Shp 500 | M172: =IF(L172="Shp 500","Sim",IF(ISNA(_xlfn.XLOOKUP(C172,'Shp 500'!D:D,'Shp 500'!D:D)),"Não","Sim")) -> Sim | N172: =IF(L172="Fastmoss 500","Sim",IF(ISNA(_xlfn.XLOOKUP(_xlfn.XLOOKUP(C172,'Same Seller Hist'!E:E,'Same Seller Hist'!H:H),'Fastmoss 500'!D:D,'Fastmoss 500'!D:D)),"Não","Sim")) -> Sim | O172: =IF(AND(M172="Sim",N172="Sim"),"Sim","Não") -> Sim | P172: =IF(I172>K172,"Sim","Não") -> Não | Q172: =COUNTIFS(C:C,C172) -> 1
C173: =_xlfn.XLOOKUP(F173,'Same Seller Hist'!H:H,'Same Seller Hist'!E:E) -> 306309956 | D173: =_xlfn.XLOOKUP(F173,'Same Seller Hist'!H:H,'Same Seller Hist'!D:D) -> Cecília casa | E173: =_xlfn.XLOOKUP(F173,'Same Seller Hist'!H:H,'Same Seller Hist'!I:I) -> 7.4961602e+18 | F173: Cecília casa | G173: =_xlfn.XLOOKUP(C173,'Same Seller Hist'!E:E,'Same Seller Hist'!F:F) -> Lifestyle | H173: =_xlfn.IFNA(_xlfn.XLOOKUP(C173,'Shp 500'!D:D,'Shp 500'!I:I),0) -> 0 | I173: =_xlfn.IFNA(_xlfn.XLOOKUP(C173,'Shp 500'!D:D,'Shp 500'!J:J),0) -> 0 | J173: 745.16129 | K173: 20551.613 | L173: Fastmoss 500 | M173: =IF(L173="Shp 500","Sim",IF(ISNA(_xlfn.XLOOKUP(C173,'Shp 500'!D:D,'Shp 500'!D:D)),"Não","Sim")) -> Não | N173: =IF(L173="Fastmoss 500","Sim",IF(ISNA(_xlfn.XLOOKUP(_xlfn.XLOOKUP(C173,'Same Seller Hist'!E:E,'Same Seller Hist'!H:H),'Fastmoss 500'!D:D,'Fastmoss 500'!D:D)),"Não","Sim")) -> Sim | O173: =IF(AND(M173="Sim",N173="Sim"),"Sim","Não") -> Não | P173: =IF(I173>K173,"Sim","Não") -> Não | Q173: =COUNTIFS(C:C,C173) -> 1
C174: =_xlfn.XLOOKUP(F174,'Same Seller Hist'!H:H,'Same Seller Hist'!E:E) -> 387419898 | D174: =_xlfn.XLOOKUP(F174,'Same Seller Hist'!H:H,'Same Seller Hist'!D:D) -> ADD MODAS | E174: =_xlfn.XLOOKUP(F174,'Same Seller Hist'!H:H,'Same Seller Hist'!I:I) -> 7.4961464e+18 | F174: ADD MODAS | G174: =_xlfn.XLOOKUP(C174,'Same Seller Hist'!E:E,'Same Seller Hist'!F:F) -> Fashion | H174: =_xlfn.IFNA(_xlfn.XLOOKUP(C174,'Shp 500'!D:D,'Shp 500'!I:I),0) -> 0 | I174: =_xlfn.IFNA(_xlfn.XLOOKUP(C174,'Shp 500'!D:D,'Shp 500'!J:J),0) -> 0 | J174: 729.03226 | K174: 51612.903 | L174: Fastmoss 500 | M174: =IF(L174="Shp 500","Sim",IF(ISNA(_xlfn.XLOOKUP(C174,'Shp 500'!D:D,'Shp 500'!D:D)),"Não","Sim")) -> Não | N174: =IF(L174="Fastmoss 500","Sim",IF(ISNA(_xlfn.XLOOKUP(_xlfn.XLOOKUP(C174,'Same Seller Hist'!E:E,'Same Seller Hist'!H:H),'Fastmoss 500'!D:D,'Fastmoss 500'!D:D)),"Não","Sim")) -> Sim | O174: =IF(AND(M174="Sim",N174="Sim"),"Sim","Não") -> Não | P174: =IF(I174>K174,"Sim","Não") -> Não | Q174: =COUNTIFS(C:C,C174) -> 1
C175: =_xlfn.XLOOKUP(F175,'Same Seller Hist'!H:H,'Same Seller Hist'!E:E) -> 688975125 | D175: =_xlfn.XLOOKUP(F175,'Same Seller Hist'!H:H,'Same Seller Hist'!D:D) -> Zencial | E175: =_xlfn.XLOOKUP(F175,'Same Seller Hist'!H:H,'Same Seller Hist'!I:I) -> 7.4961803e+18 | F175: Zencial | G175: =_xlfn.XLOOKUP(C175,'Same Seller Hist'!E:E,'Same Seller Hist'!F:F) -> FMCG | H175: =_xlfn.IFNA(_xlfn.XLOOKUP(C175,'Shp 500'!D:D,'Shp 500'!I:I),0) -> 0 | I175: =_xlfn.IFNA(_xlfn.XLOOKUP(C175,'Shp 500'!D:D,'Shp 500'!J:J),0) -> 0 | J175: 725.80645 | K175: 74193.548 | L175: Fastmoss 500 | M175: =IF(L175="Shp 500","Sim",IF(ISNA(_xlfn.XLOOKUP(C175,'Shp 500'!D:D,'Shp 500'!D:D)),"Não","Sim")) -> Não | N175: =IF(L175="Fastmoss 500","Sim",IF(ISNA(_xlfn.XLOOKUP(_xlfn.XLOOKUP(C175,'Same Seller Hist'!E:E,'Same Seller Hist'!H:H),'Fastmoss 500'!D:D,'Fastmoss 500'!D:D)),"Não","Sim")) -> Sim | O175: =IF(AND(M175="Sim",N175="Sim"),"Sim","Não") -> Não | P175: =IF(I175>K175,"Sim","Não") -> Não | Q175: =COUNTIFS(C:C,C175) -> 1
C176: =_xlfn.XLOOKUP(F176,'Same Seller Hist'!H:H,'Same Seller Hist'!E:E) -> 1304513381 | D176: =_xlfn.XLOOKUP(F176,'Same Seller Hist'!H:H,'Same Seller Hist'!D:D) -> Creamy Skincare | E176: =_xlfn.XLOOKUP(F176,'Same Seller Hist'!H:H,'Same Seller Hist'!I:I) -> 7.4961549e+18 | F176: Creamy Skincare | G176: =_xlfn.XLOOKUP(C176,'Same Seller Hist'!E:E,'Same Seller Hist'!F:F) -> FMCG | H176: =_xlfn.IFNA(_xlfn.XLOOKUP(C176,'Shp 500'!D:D,'Shp 500'!I:I),0) -> 0 | I176: =_xlfn.IFNA(_xlfn.XLOOKUP(C176,'Shp 500'!D:D,'Shp 500'!J:J),0) -> 0 | J176: 722.58065 | K176: 64516.129 | L176: Fastmoss 500 | M176: =IF(L176="Shp 500","Sim",IF(ISNA(_xlfn.XLOOKUP(C176,'Shp 500'!D:D,'Shp 500'!D:D)),"Não","Sim")) -> Não | N176: =IF(L176="Fastmoss 500","Sim",IF(ISNA(_xlfn.XLOOKUP(_xlfn.XLOOKUP(C176,'Same Seller Hist'!E:E,'Same Seller Hist'!H:H),'Fastmoss 500'!D:D,'Fastmoss 500'!D:D)),"Não","Sim")) -> Sim | O176: =IF(AND(M176="Sim",N176="Sim"),"Sim","Não") -> Não | P176: =IF(I176>K176,"Sim","Não") -> Não | Q176: =COUNTIFS(C:C,C176) -> 1
C177: =_xlfn.XLOOKUP(F177,'Same Seller Hist'!H:H,'Same Seller Hist'!E:E) -> 370895652 | D177: =_xlfn.XLOOKUP(F177,'Same Seller Hist'!H:H,'Same Seller Hist'!D:D) -> TudoAki. | E177: =_xlfn.XLOOKUP(F177,'Same Seller Hist'!H:H,'Same Seller Hist'!I:I) -> 7.4962721e+18 | F177: TudoAki. | G177: =_xlfn.XLOOKUP(C177,'Same Seller Hist'!E:E,'Same Seller Hist'!F:F) -> ELHA | H177: =_xlfn.IFNA(_xlfn.XLOOKUP(C177,'Shp 500'!D:D,'Shp 500'!I:I),0) -> 0 | I177: =_xlfn.IFNA(_xlfn.XLOOKUP(C177,'Shp 500'!D:D,'Shp 500'!J:J),0) -> 0 | J177: 722.58065 | K177: 27403.226 | L177: Fastmoss 500 | M177: =IF(L177="Shp 500","Sim",IF(ISNA(_xlfn.XLOOKUP(C177,'Shp 500'!D:D,'Shp 500'!D:D)),"Não","Sim")) -> Não | N177: =IF(L177="Fastmoss 500","Sim",IF(ISNA(_xlfn.XLOOKUP(_xlfn.XLOOKUP(C177,'Same Seller Hist'!E:E,'Same Seller Hist'!H:H),'Fastmoss 500'!D:D,'Fastmoss 500'!D:D)),"Não","Sim")) -> Sim | O177: =IF(AND(M177="Sim",N177="Sim"),"Sim","Não") -> Não | P177: =IF(I177>K177,"Sim","Não") -> Não | Q177: =COUNTIFS(C:C,C177) -> 1
C178: 986450286 | D178: Bisdan Cosmeticos | E178: =_xlfn.XLOOKUP(C178,'Same Seller Hist'!E:E,'Same Seller Hist'!I:I) -> 7.4961822e+18 | F178: =_xlfn.XLOOKUP(C178,'Same Seller Hist'!E:E,'Same Seller Hist'!H:H) -> Baisdan | G178: CN | H178: 998.25806 | I178: 2081.7327 | J178: =_xlfn.IFNA(_xlfn.XLOOKUP(F178,'Fastmoss 500'!D:D,'Fastmoss 500'!O:O),0) -> 335.48387 | K178: =_xlfn.IFNA(_xlfn.XLOOKUP(F178,'Fastmoss 500'!D:D,'Fastmoss 500'!N:N),0) -> 5622.5806 | L178: Shp 500 | M178: =IF(L178="Shp 500","Sim",IF(ISNA(_xlfn.XLOOKUP(C178,'Shp 500'!D:D,'Shp 500'!D:D)),"Não","Sim")) -> Sim | N178: =IF(L178="Fastmoss 500","Sim",IF(ISNA(_xlfn.XLOOKUP(_xlfn.XLOOKUP(C178,'Same Seller Hist'!E:E,'Same Seller Hist'!H:H),'Fastmoss 500'!D:D,'Fastmoss 500'!D:D)),"Não","Sim")) -> Sim | O178: =IF(AND(M178="Sim",N178="Sim"),"Sim","Não") -> Sim | P178: =IF(I178>K178,"Sim","Não") -> Não | Q178: =COUNTIFS(C:C,C178) -> 1
C179: =_xlfn.XLOOKUP(F179,'Same Seller Hist'!H:H,'Same Seller Hist'!E:E) -> 1088017491 | D179: =_xlfn.XLOOKUP(F179,'Same Seller Hist'!H:H,'Same Seller Hist'!D:D) -> URSA MAIOR LED | E179: =_xlfn.XLOOKUP(F179,'Same Seller Hist'!H:H,'Same Seller Hist'!I:I) -> 7.4962924e+18 | F179: URSA MAIOR LED | G179: =_xlfn.XLOOKUP(C179,'Same Seller Hist'!E:E,'Same Seller Hist'!F:F) -> 0 | H179: =_xlfn.IFNA(_xlfn.XLOOKUP(C179,'Shp 500'!D:D,'Shp 500'!I:I),0) -> 0 | I179: =_xlfn.IFNA(_xlfn.XLOOKUP(C179,'Shp 500'!D:D,'Shp 500'!J:J),0) -> 0 | J179: 706.45161 | K179: 35483.871 | L179: Fastmoss 500 | M179: =IF(L179="Shp 500","Sim",IF(ISNA(_xlfn.XLOOKUP(C179,'Shp 500'!D:D,'Shp 500'!D:D)),"Não","Sim")) -> Não | N179: =IF(L179="Fastmoss 500","Sim",IF(ISNA(_xlfn.XLOOKUP(_xlfn.XLOOKUP(C179,'Same Seller Hist'!E:E,'Same Seller Hist'!H:H),'Fastmoss 500'!D:D,'Fastmoss 500'!D:D)),"Não","Sim")) -> Sim | O179: =IF(AND(M179="Sim",N179="Sim"),"Sim","Não") -> Não | P179: =IF(I179>K179,"Sim","Não") -> Não | Q179: =COUNTIFS(C:C,C179) -> 1
C180: =_xlfn.XLOOKUP(F180,'Same Seller Hist'!H:H,'Same Seller Hist'!E:E) -> 1299621852 | D180: =_xlfn.XLOOKUP(F180,'Same Seller Hist'!H:H,'Same Seller Hist'!D:D) -> Toem casa | E180: =_xlfn.XLOOKUP(F180,'Same Seller Hist'!H:H,'Same Seller Hist'!I:I) -> 7.4961531e+18 | F180: Toem casa | G180: =_xlfn.XLOOKUP(C180,'Same Seller Hist'!E:E,'Same Seller Hist'!F:F) -> Auto & Moto | H180: =_xlfn.IFNA(_xlfn.XLOOKUP(C180,'Shp 500'!D:D,'Shp 500'!I:I),0) -> 0 | I180: =_xlfn.IFNA(_xlfn.XLOOKUP(C180,'Shp 500'!D:D,'Shp 500'!J:J),0) -> 0 | J180: 677.41935 | K180: 14274.194 | L180: Fastmoss 500 | M180: =IF(L180="Shp 500","Sim",IF(ISNA(_xlfn.XLOOKUP(C180,'Shp 500'!D:D,'Shp 500'!D:D)),"Não","Sim")) -> Não | N180: =IF(L180="Fastmoss 500","Sim",IF(ISNA(_xlfn.XLOOKUP(_xlfn.XLOOKUP(C180,'Same Seller Hist'!E:E,'Same Seller Hist'!H:H),'Fastmoss 500'!D:D,'Fastmoss 500'!D:D)),"Não","Sim")) -> Sim | O180: =IF(AND(M180="Sim",N180="Sim"),"Sim","Não") -> Não | P180: =IF(I180>K180,"Sim","Não") -> Não | Q180: =COUNTIFS(C:C,C180) -> 1
C181: =_xlfn.XLOOKUP(F181,'Same Seller Hist'!H:H,'Same Seller Hist'!E:E) -> 1614658014 | D181: =_xlfn.XLOOKUP(F181,'Same Seller Hist'!H:H,'Same Seller Hist'!D:D) -> TOON STORE BR | E181: =_xlfn.XLOOKUP(F181,'Same Seller Hist'!H:H,'Same Seller Hist'!I:I) -> 7.494126e+18 | F181: TOON STORE BR | G181: =_xlfn.XLOOKUP(C181,'Same Seller Hist'!E:E,'Same Seller Hist'!F:F) -> FMCG | H181: =_xlfn.IFNA(_xlfn.XLOOKUP(C181,'Shp 500'!D:D,'Shp 500'!I:I),0) -> 0 | I181: =_xlfn.IFNA(_xlfn.XLOOKUP(C181,'Shp 500'!D:D,'Shp 500'!J:J),0) -> 0 | J181: 661.29032 | K181: 7254.8387 | L181: Fastmoss 500 | M181: =IF(L181="Shp 500","Sim",IF(ISNA(_xlfn.XLOOKUP(C181,'Shp 500'!D:D,'Shp 500'!D:D)),"Não","Sim")) -> Não | N181: =IF(L181="Fastmoss 500","Sim",IF(ISNA(_xlfn.XLOOKUP(_xlfn.XLOOKUP(C181,'Same Seller Hist'!E:E,'Same Seller Hist'!H:H),'Fastmoss 500'!D:D,'Fastmoss 500'!D:D)),"Não","Sim")) -> Sim | O181: =IF(AND(M181="Sim",N181="Sim"),"Sim","Não") -> Não | P181: =IF(I181>K181,"Sim","Não") -> Não | Q181: =COUNTIFS(C:C,C181) -> 1
C182: =_xlfn.XLOOKUP(F182,'Same Seller Hist'!H:H,'Same Seller Hist'!E:E) -> 908134378 | D182: =_xlfn.XLOOKUP(F182,'Same Seller Hist'!H:H,'Same Seller Hist'!D:D) -> QUEEN SHOP SP | E182: =_xlfn.XLOOKUP(F182,'Same Seller Hist'!H:H,'Same Seller Hist'!I:I) -> 7.4962013e+18 | F182: QUEEN SHOP SP | G182: =_xlfn.XLOOKUP(C182,'Same Seller Hist'!E:E,'Same Seller Hist'!F:F) -> ELHA | H182: =_xlfn.IFNA(_xlfn.XLOOKUP(C182,'Shp 500'!D:D,'Shp 500'!I:I),0) -> 0 | I182: =_xlfn.IFNA(_xlfn.XLOOKUP(C182,'Shp 500'!D:D,'Shp 500'!J:J),0) -> 0 | J182: 661.29032 | K182: 6496.7742 | L182: Fastmoss 500 | M182: =IF(L182="Shp 500","Sim",IF(ISNA(_xlfn.XLOOKUP(C182,'Shp 500'!D:D,'Shp 500'!D:D)),"Não","Sim")) -> Não | N182: =IF(L182="Fastmoss 500","Sim",IF(ISNA(_xlfn.XLOOKUP(_xlfn.XLOOKUP(C182,'Same Seller Hist'!E:E,'Same Seller Hist'!H:H),'Fastmoss 500'!D:D,'Fastmoss 500'!D:D)),"Não","Sim")) -> Sim | O182: =IF(AND(M182="Sim",N182="Sim"),"Sim","Não") -> Não | P182: =IF(I182>K182,"Sim","Não") -> Não | Q182: =COUNTIFS(C:C,C182) -> 1
C183: =_xlfn.XLOOKUP(F183,'Same Seller Hist'!H:H,'Same Seller Hist'!E:E) -> 998268968 | D183: =_xlfn.XLOOKUP(F183,'Same Seller Hist'!H:H,'Same Seller Hist'!D:D) -> Romafam | E183: =_xlfn.XLOOKUP(F183,'Same Seller Hist'!H:H,'Same Seller Hist'!I:I) -> 7.4961833e+18 | F183: Romafam | G183: =_xlfn.XLOOKUP(C183,'Same Seller Hist'!E:E,'Same Seller Hist'!F:F) -> Fashion | H183: =_xlfn.IFNA(_xlfn.XLOOKUP(C183,'Shp 500'!D:D,'Shp 500'!I:I),0) -> 0 | I183: =_xlfn.IFNA(_xlfn.XLOOKUP(C183,'Shp 500'!D:D,'Shp 500'!J:J),0) -> 0 | J183: 648.3871 | K183: 26358.065 | L183: Fastmoss 500 | M183: =IF(L183="Shp 500","Sim",IF(ISNA(_xlfn.XLOOKUP(C183,'Shp 500'!D:D,'Shp 500'!D:D)),"Não","Sim")) -> Não | N183: =IF(L183="Fastmoss 500","Sim",IF(ISNA(_xlfn.XLOOKUP(_xlfn.XLOOKUP(C183,'Same Seller Hist'!E:E,'Same Seller Hist'!H:H),'Fastmoss 500'!D:D,'Fastmoss 500'!D:D)),"Não","Sim")) -> Sim | O183: =IF(AND(M183="Sim",N183="Sim"),"Sim","Não") -> Não | P183: =IF(I183>K183,"Sim","Não") -> Não | Q183: =COUNTIFS(C:C,C183) -> 1
C184: =_xlfn.XLOOKUP(F184,'Same Seller Hist'!H:H,'Same Seller Hist'!E:E) -> 1191862620 | D184: =_xlfn.XLOOKUP(F184,'Same Seller Hist'!H:H,'Same Seller Hist'!D:D) -> Movimento | E184: =_xlfn.XLOOKUP(F184,'Same Seller Hist'!H:H,'Same Seller Hist'!I:I) -> 7.494093e+18 | F184: Movimento | G184: =_xlfn.XLOOKUP(C184,'Same Seller Hist'!E:E,'Same Seller Hist'!F:F) -> 0 | H184: =_xlfn.IFNA(_xlfn.XLOOKUP(C184,'Shp 500'!D:D,'Shp 500'!I:I),0) -> 0 | I184: =_xlfn.IFNA(_xlfn.XLOOKUP(C184,'Shp 500'!D:D,'Shp 500'!J:J),0) -> 0 | J184: 645.16129 | K184: 13154.839 | L184: Fastmoss 500 | M184: =IF(L184="Shp 500","Sim",IF(ISNA(_xlfn.XLOOKUP(C184,'Shp 500'!D:D,'Shp 500'!D:D)),"Não","Sim")) -> Não | N184: =IF(L184="Fastmoss 500","Sim",IF(ISNA(_xlfn.XLOOKUP(_xlfn.XLOOKUP(C184,'Same Seller Hist'!E:E,'Same Seller Hist'!H:H),'Fastmoss 500'!D:D,'Fastmoss 500'!D:D)),"Não","Sim")) -> Sim | O184: =IF(AND(M184="Sim",N184="Sim"),"Sim","Não") -> Não | P184: =IF(I184>K184,"Sim","Não") -> Não | Q184: =COUNTIFS(C:C,C184) -> 1
C185: =_xlfn.XLOOKUP(F185,'Same Seller Hist'!H:H,'Same Seller Hist'!E:E) -> 326857141 | D185: =_xlfn.XLOOKUP(F185,'Same Seller Hist'!H:H,'Same Seller Hist'!D:D) -> Galan Modas | E185: =_xlfn.XLOOKUP(F185,'Same Seller Hist'!H:H,'Same Seller Hist'!I:I) -> 7.4961906e+18 | F185: Galan Modas | G185: =_xlfn.XLOOKUP(C185,'Same Seller Hist'!E:E,'Same Seller Hist'!F:F) -> Fashion | H185: =_xlfn.IFNA(_xlfn.XLOOKUP(C185,'Shp 500'!D:D,'Shp 500'!I:I),0) -> 0 | I185: =_xlfn.IFNA(_xlfn.XLOOKUP(C185,'Shp 500'!D:D,'Shp 500'!J:J),0) -> 0 | J185: 641.93548 | K185: 29080.645 | L185: Fastmoss 500 | M185: =IF(L185="Shp 500","Sim",IF(ISNA(_xlfn.XLOOKUP(C185,'Shp 500'!D:D,'Shp 500'!D:D)),"Não","Sim")) -> Não | N185: =IF(L185="Fastmoss 500","Sim",IF(ISNA(_xlfn.XLOOKUP(_xlfn.XLOOKUP(C185,'Same Seller Hist'!E:E,'Same Seller Hist'!H:H),'Fastmoss 500'!D:D,'Fastmoss 500'!D:D)),"Não","Sim")) -> Sim | O185: =IF(AND(M185="Sim",N185="Sim"),"Sim","Não") -> Não | P185: =IF(I185>K185,"Sim","Não") -> Não | Q185: =COUNTIFS(C:C,C185) -> 1
C186: =_xlfn.XLOOKUP(F186,'Same Seller Hist'!H:H,'Same Seller Hist'!E:E) -> 1598954691 | D186: =_xlfn.XLOOKUP(F186,'Same Seller Hist'!H:H,'Same Seller Hist'!D:D) -> JACK CELL BR | E186: =_xlfn.XLOOKUP(F186,'Same Seller Hist'!H:H,'Same Seller Hist'!I:I) -> 7.4941814e+18 | F186: JACK CELL BR | G186: =_xlfn.XLOOKUP(C186,'Same Seller Hist'!E:E,'Same Seller Hist'!F:F) -> 0 | H186: =_xlfn.IFNA(_xlfn.XLOOKUP(C186,'Shp 500'!D:D,'Shp 500'!I:I),0) -> 0 | I186: =_xlfn.IFNA(_xlfn.XLOOKUP(C186,'Shp 500'!D:D,'Shp 500'!J:J),0) -> 0 | J186: 632.25806 | K186: 38709.677 | L186: Fastmoss 500 | M186: =IF(L186="Shp 500","Sim",IF(ISNA(_xlfn.XLOOKUP(C186,'Shp 500'!D:D,'Shp 500'!D:D)),"Não","Sim")) -> Não | N186: =IF(L186="Fastmoss 500","Sim",IF(ISNA(_xlfn.XLOOKUP(_xlfn.XLOOKUP(C186,'Same Seller Hist'!E:E,'Same Seller Hist'!H:H),'Fastmoss 500'!D:D,'Fastmoss 500'!D:D)),"Não","Sim")) -> Sim | O186: =IF(AND(M186="Sim",N186="Sim"),"Sim","Não") -> Não | P186: =IF(I186>K186,"Sim","Não") -> Não | Q186: =COUNTIFS(C:C,C186) -> 1
C187: 995022276 | D187: PANGU Store | E187: =_xlfn.XLOOKUP(C187,'Same Seller Hist'!E:E,'Same Seller Hist'!I:I) -> 7.4961622e+18 | F187: =_xlfn.XLOOKUP(C187,'Same Seller Hist'!E:E,'Same Seller Hist'!H:H) -> PanguTK | G187: CN | H187: 2114.3548 | I187: 17475.863 | J187: =_xlfn.IFNA(_xlfn.XLOOKUP(F187,'Fastmoss 500'!D:D,'Fastmoss 500'!O:O),0) -> 354.83871 | K187: =_xlfn.IFNA(_xlfn.XLOOKUP(F187,'Fastmoss 500'!D:D,'Fastmoss 500'!N:N),0) -> 20287.097 | L187: Shp 500 | M187: =IF(L187="Shp 500","Sim",IF(ISNA(_xlfn.XLOOKUP(C187,'Shp 500'!D:D,'Shp 500'!D:D)),"Não","Sim")) -> Sim | N187: =IF(L187="Fastmoss 500","Sim",IF(ISNA(_xlfn.XLOOKUP(_xlfn.XLOOKUP(C187,'Same Seller Hist'!E:E,'Same Seller Hist'!H:H),'Fastmoss 500'!D:D,'Fastmoss 500'!D:D)),"Não","Sim")) -> Sim | O187: =IF(AND(M187="Sim",N187="Sim"),"Sim","Não") -> Sim | P187: =IF(I187>K187,"Sim","Não") -> Não | Q187: =COUNTIFS(C:C,C187) -> 1
C188: =_xlfn.XLOOKUP(F188,'Same Seller Hist'!H:H,'Same Seller Hist'!E:E) -> 773016601 | D188: =_xlfn.XLOOKUP(F188,'Same Seller Hist'!H:H,'Same Seller Hist'!D:D) -> Mais.Amor | E188: =_xlfn.XLOOKUP(F188,'Same Seller Hist'!H:H,'Same Seller Hist'!I:I) -> 7.4961623e+18 | F188: Mais.Amor | G188: =_xlfn.XLOOKUP(C188,'Same Seller Hist'!E:E,'Same Seller Hist'!F:F) -> Lifestyle | H188: =_xlfn.IFNA(_xlfn.XLOOKUP(C188,'Shp 500'!D:D,'Shp 500'!I:I),0) -> 0 | I188: =_xlfn.IFNA(_xlfn.XLOOKUP(C188,'Shp 500'!D:D,'Shp 500'!J:J),0) -> 0 | J188: 622.58065 | K188: 21635.484 | L188: Fastmoss 500 | M188: =IF(L188="Shp 500","Sim",IF(ISNA(_xlfn.XLOOKUP(C188,'Shp 500'!D:D,'Shp 500'!D:D)),"Não","Sim")) -> Não | N188: =IF(L188="Fastmoss 500","Sim",IF(ISNA(_xlfn.XLOOKUP(_xlfn.XLOOKUP(C188,'Same Seller Hist'!E:E,'Same Seller Hist'!H:H),'Fastmoss 500'!D:D,'Fastmoss 500'!D:D)),"Não","Sim")) -> Sim | O188: =IF(AND(M188="Sim",N188="Sim"),"Sim","Não") -> Não | P188: =IF(I188>K188,"Sim","Não") -> Não | Q188: =COUNTIFS(C:C,C188) -> 1
C189: =_xlfn.XLOOKUP(F189,'Same Seller Hist'!H:H,'Same Seller Hist'!E:E) -> 815223259 | D189: =_xlfn.XLOOKUP(F189,'Same Seller Hist'!H:H,'Same Seller Hist'!D:D) -> RH OUTLET | E189: =_xlfn.XLOOKUP(F189,'Same Seller Hist'!H:H,'Same Seller Hist'!I:I) -> 7.4962777e+18 | F189: RH OUTLET | G189: =_xlfn.XLOOKUP(C189,'Same Seller Hist'!E:E,'Same Seller Hist'!F:F) -> Fashion | H189: =_xlfn.IFNA(_xlfn.XLOOKUP(C189,'Shp 500'!D:D,'Shp 500'!I:I),0) -> 0 | I189: =_xlfn.IFNA(_xlfn.XLOOKUP(C189,'Shp 500'!D:D,'Shp 500'!J:J),0) -> 0 | J189: 593.54839 | K189: 26835.484 | L189: Fastmoss 500 | M189: =IF(L189="Shp 500","Sim",IF(ISNA(_xlfn.XLOOKUP(C189,'Shp 500'!D:D,'Shp 500'!D:D)),"Não","Sim")) -> Não | N189: =IF(L189="Fastmoss 500","Sim",IF(ISNA(_xlfn.XLOOKUP(_xlfn.XLOOKUP(C189,'Same Seller Hist'!E:E,'Same Seller Hist'!H:H),'Fastmoss 500'!D:D,'Fastmoss 500'!D:D)),"Não","Sim")) -> Sim | O189: =IF(AND(M189="Sim",N189="Sim"),"Sim","Não") -> Não | P189: =IF(I189>K189,"Sim","Não") -> Não | Q189: =COUNTIFS(C:C,C189) -> 1
C190: 1025824477 | D190: YUMI CELL | E190: =_xlfn.XLOOKUP(C190,'Same Seller Hist'!E:E,'Same Seller Hist'!I:I) -> 7.4941815e+18 | F190: =_xlfn.XLOOKUP(C190,'Same Seller Hist'!E:E,'Same Seller Hist'!H:H) -> YUMI CELL BR | G190: CN | H190: 3297.7742 | I190: 25555.055 | J190: =_xlfn.IFNA(_xlfn.XLOOKUP(F190,'Fastmoss 500'!D:D,'Fastmoss 500'!O:O),0) -> 235.48387 | K190: =_xlfn.IFNA(_xlfn.XLOOKUP(F190,'Fastmoss 500'!D:D,'Fastmoss 500'!N:N),0) -> 17706.452 | L190: Shp 500 | M190: =IF(L190="Shp 500","Sim",IF(ISNA(_xlfn.XLOOKUP(C190,'Shp 500'!D:D,'Shp 500'!D:D)),"Não","Sim")) -> Sim | N190: =IF(L190="Fastmoss 500","Sim",IF(ISNA(_xlfn.XLOOKUP(_xlfn.XLOOKUP(C190,'Same Seller Hist'!E:E,'Same Seller Hist'!H:H),'Fastmoss 500'!D:D,'Fastmoss 500'!D:D)),"Não","Sim")) -> Sim | O190: =IF(AND(M190="Sim",N190="Sim"),"Sim","Não") -> Sim | P190: =IF(I190>K190,"Sim","Não") -> Sim | Q190: =COUNTIFS(C:C,C190) -> 1
C191: =_xlfn.XLOOKUP(F191,'Same Seller Hist'!H:H,'Same Seller Hist'!E:E) -> 1226196647 | D191: =_xlfn.XLOOKUP(F191,'Same Seller Hist'!H:H,'Same Seller Hist'!D:D) -> CECILIA PRESENTE | E191: =_xlfn.XLOOKUP(F191,'Same Seller Hist'!H:H,'Same Seller Hist'!I:I) -> 7.4941814e+18 | F191: CECILIA PRESENTE | G191: =_xlfn.XLOOKUP(C191,'Same Seller Hist'!E:E,'Same Seller Hist'!F:F) -> 0 | H191: =_xlfn.IFNA(_xlfn.XLOOKUP(C191,'Shp 500'!D:D,'Shp 500'!I:I),0) -> 0 | I191: =_xlfn.IFNA(_xlfn.XLOOKUP(C191,'Shp 500'!D:D,'Shp 500'!J:J),0) -> 0 | J191: 587.09677 | K191: 16874.194 | L191: Fastmoss 500 | M191: =IF(L191="Shp 500","Sim",IF(ISNA(_xlfn.XLOOKUP(C191,'Shp 500'!D:D,'Shp 500'!D:D)),"Não","Sim")) -> Não | N191: =IF(L191="Fastmoss 500","Sim",IF(ISNA(_xlfn.XLOOKUP(_xlfn.XLOOKUP(C191,'Same Seller Hist'!E:E,'Same Seller Hist'!H:H),'Fastmoss 500'!D:D,'Fastmoss 500'!D:D)),"Não","Sim")) -> Sim | O191: =IF(AND(M191="Sim",N191="Sim"),"Sim","Não") -> Não | P191: =IF(I191>K191,"Sim","Não") -> Não | Q191: =COUNTIFS(C:C,C191) -> 1
C192: =_xlfn.XLOOKUP(F192,'Same Seller Hist'!H:H,'Same Seller Hist'!E:E) -> 1600146163 | D192: =_xlfn.XLOOKUP(F192,'Same Seller Hist'!H:H,'Same Seller Hist'!D:D) -> JADE COSMÉTICOS | E192: =_xlfn.XLOOKUP(F192,'Same Seller Hist'!H:H,'Same Seller Hist'!I:I) -> 7.4963224e+18 | F192: JADE COSMÉTICOS | G192: =_xlfn.XLOOKUP(C192,'Same Seller Hist'!E:E,'Same Seller Hist'!F:F) -> FMCG | H192: =_xlfn.IFNA(_xlfn.XLOOKUP(C192,'Shp 500'!D:D,'Shp 500'!I:I),0) -> 0 | I192: =_xlfn.IFNA(_xlfn.XLOOKUP(C192,'Shp 500'!D:D,'Shp 500'!J:J),0) -> 0 | J192: 583.87097 | K192: 26667.742 | L192: Fastmoss 500 | M192: =IF(L192="Shp 500","Sim",IF(ISNA(_xlfn.XLOOKUP(C192,'Shp 500'!D:D,'Shp 500'!D:D)),"Não","Sim")) -> Não | N192: =IF(L192="Fastmoss 500","Sim",IF(ISNA(_xlfn.XLOOKUP(_xlfn.XLOOKUP(C192,'Same Seller Hist'!E:E,'Same Seller Hist'!H:H),'Fastmoss 500'!D:D,'Fastmoss 500'!D:D)),"Não","Sim")) -> Sim | O192: =IF(AND(M192="Sim",N192="Sim"),"Sim","Não") -> Não | P192: =IF(I192>K192,"Sim","Não") -> Não | Q192: =COUNTIFS(C:C,C192) -> 1
C193: =_xlfn.XLOOKUP(F193,'Same Seller Hist'!H:H,'Same Seller Hist'!E:E) -> 1017564998 | D193: =_xlfn.XLOOKUP(F193,'Same Seller Hist'!H:H,'Same Seller Hist'!D:D) -> YIYI MODA | E193: =_xlfn.XLOOKUP(F193,'Same Seller Hist'!H:H,'Same Seller Hist'!I:I) -> 7.4961519e+18 | F193: YIYI MODA | G193: =_xlfn.XLOOKUP(C193,'Same Seller Hist'!E:E,'Same Seller Hist'!F:F) -> Lifestyle | H193: =_xlfn.IFNA(_xlfn.XLOOKUP(C193,'Shp 500'!D:D,'Shp 500'!I:I),0) -> 0 | I193: =_xlfn.IFNA(_xlfn.XLOOKUP(C193,'Shp 500'!D:D,'Shp 500'!J:J),0) -> 0 | J193: 574.19355 | K193: 26151.613 | L193: Fastmoss 500 | M193: =IF(L193="Shp 500","Sim",IF(ISNA(_xlfn.XLOOKUP(C193,'Shp 500'!D:D,'Shp 500'!D:D)),"Não","Sim")) -> Não | N193: =IF(L193="Fastmoss 500","Sim",IF(ISNA(_xlfn.XLOOKUP(_xlfn.XLOOKUP(C193,'Same Seller Hist'!E:E,'Same Seller Hist'!H:H),'Fastmoss 500'!D:D,'Fastmoss 500'!D:D)),"Não","Sim")) -> Sim | O193: =IF(AND(M193="Sim",N193="Sim"),"Sim","Não") -> Não | P193: =IF(I193>K193,"Sim","Não") -> Não | Q193: =COUNTIFS(C:C,C193) -> 1
C194: =_xlfn.XLOOKUP(F194,'Same Seller Hist'!H:H,'Same Seller Hist'!E:E) -> 395166866 | D194: =_xlfn.XLOOKUP(F194,'Same Seller Hist'!H:H,'Same Seller Hist'!D:D) -> KOKESHI COSMETICOS | E194: =_xlfn.XLOOKUP(F194,'Same Seller Hist'!H:H,'Same Seller Hist'!I:I) -> 7.4962047e+18 | F194: KOKESHI COSMETICOS | G194: =_xlfn.XLOOKUP(C194,'Same Seller Hist'!E:E,'Same Seller Hist'!F:F) -> FMCG | H194: =_xlfn.IFNA(_xlfn.XLOOKUP(C194,'Shp 500'!D:D,'Shp 500'!I:I),0) -> 0 | I194: =_xlfn.IFNA(_xlfn.XLOOKUP(C194,'Shp 500'!D:D,'Shp 500'!J:J),0) -> 0 | J194: 570.96774 | K194: 25664.516 | L194: Fastmoss 500 | M194: =IF(L194="Shp 500","Sim",IF(ISNA(_xlfn.XLOOKUP(C194,'Shp 500'!D:D,'Shp 500'!D:D)),"Não","Sim")) -> Não | N194: =IF(L194="Fastmoss 500","Sim",IF(ISNA(_xlfn.XLOOKUP(_xlfn.XLOOKUP(C194,'Same Seller Hist'!E:E,'Same Seller Hist'!H:H),'Fastmoss 500'!D:D,'Fastmoss 500'!D:D)),"Não","Sim")) -> Sim | O194: =IF(AND(M194="Sim",N194="Sim"),"Sim","Não") -> Não | P194: =IF(I194>K194,"Sim","Não") -> Não | Q194: =COUNTIFS(C:C,C194) -> 1
C195: =_xlfn.XLOOKUP(F195,'Same Seller Hist'!H:H,'Same Seller Hist'!E:E) -> 331042174 | D195: =_xlfn.XLOOKUP(F195,'Same Seller Hist'!H:H,'Same Seller Hist'!D:D) -> Xavierabolsa | E195: =_xlfn.XLOOKUP(F195,'Same Seller Hist'!H:H,'Same Seller Hist'!I:I) -> 7.4961616e+18 | F195: Xavierabolsa | G195: =_xlfn.XLOOKUP(C195,'Same Seller Hist'!E:E,'Same Seller Hist'!F:F) -> Fashion | H195: =_xlfn.IFNA(_xlfn.XLOOKUP(C195,'Shp 500'!D:D,'Shp 500'!I:I),0) -> 0 | I195: =_xlfn.IFNA(_xlfn.XLOOKUP(C195,'Shp 500'!D:D,'Shp 500'!J:J),0) -> 0 | J195: 570.96774 | K195: 58064.516 | L195: Fastmoss 500 | M195: =IF(L195="Shp 500","Sim",IF(ISNA(_xlfn.XLOOKUP(C195,'Shp 500'!D:D,'Shp 500'!D:D)),"Não","Sim")) -> Não | N195: =IF(L195="Fastmoss 500","Sim",IF(ISNA(_xlfn.XLOOKUP(_xlfn.XLOOKUP(C195,'Same Seller Hist'!E:E,'Same Seller Hist'!H:H),'Fastmoss 500'!D:D,'Fastmoss 500'!D:D)),"Não","Sim")) -> Sim | O195: =IF(AND(M195="Sim",N195="Sim"),"Sim","Não") -> Não | P195: =IF(I195>K195,"Sim","Não") -> Não | Q195: =COUNTIFS(C:C,C195) -> 1
C196: =_xlfn.XLOOKUP(F196,'Same Seller Hist'!H:H,'Same Seller Hist'!E:E) -> 667607022 | D196: =_xlfn.XLOOKUP(F196,'Same Seller Hist'!H:H,'Same Seller Hist'!D:D) -> Llili Decorações | E196: =_xlfn.XLOOKUP(F196,'Same Seller Hist'!H:H,'Same Seller Hist'!I:I) -> 7.494183e+18 | F196: Llili Decorações | G196: =_xlfn.XLOOKUP(C196,'Same Seller Hist'!E:E,'Same Seller Hist'!F:F) -> 0 | H196: =_xlfn.IFNA(_xlfn.XLOOKUP(C196,'Shp 500'!D:D,'Shp 500'!I:I),0) -> 0 | I196: =_xlfn.IFNA(_xlfn.XLOOKUP(C196,'Shp 500'!D:D,'Shp 500'!J:J),0) -> 0 | J196: 558.06452 | K196: 19870.968 | L196: Fastmoss 500 | M196: =IF(L196="Shp 500","Sim",IF(ISNA(_xlfn.XLOOKUP(C196,'Shp 500'!D:D,'Shp 500'!D:D)),"Não","Sim")) -> Não | N196: =IF(L196="Fastmoss 500","Sim",IF(ISNA(_xlfn.XLOOKUP(_xlfn.XLOOKUP(C196,'Same Seller Hist'!E:E,'Same Seller Hist'!H:H),'Fastmoss 500'!D:D,'Fastmoss 500'!D:D)),"Não","Sim")) -> Sim | O196: =IF(AND(M196="Sim",N196="Sim"),"Sim","Não") -> Não | P196: =IF(I196>K196,"Sim","Não") -> Não | Q196: =COUNTIFS(C:C,C196) -> 1
C197: =_xlfn.XLOOKUP(F197,'Same Seller Hist'!H:H,'Same Seller Hist'!E:E) -> 1188165400 | D197: =_xlfn.XLOOKUP(F197,'Same Seller Hist'!H:H,'Same Seller Hist'!D:D) -> Maxfem | E197: =_xlfn.XLOOKUP(F197,'Same Seller Hist'!H:H,'Same Seller Hist'!I:I) -> 7.4961482e+18 | F197: Maxfem | G197: =_xlfn.XLOOKUP(C197,'Same Seller Hist'!E:E,'Same Seller Hist'!F:F) -> FMCG | H197: =_xlfn.IFNA(_xlfn.XLOOKUP(C197,'Shp 500'!D:D,'Shp 500'!I:I),0) -> 0 | I197: =_xlfn.IFNA(_xlfn.XLOOKUP(C197,'Shp 500'!D:D,'Shp 500'!J:J),0) -> 0 | J197: 545.16129 | K197: 61290.323 | L197: Fastmoss 500 | M197: =IF(L197="Shp 500","Sim",IF(ISNA(_xlfn.XLOOKUP(C197,'Shp 500'!D:D,'Shp 500'!D:D)),"Não","Sim")) -> Não | N197: =IF(L197="Fastmoss 500","Sim",IF(ISNA(_xlfn.XLOOKUP(_xlfn.XLOOKUP(C197,'Same Seller Hist'!E:E,'Same Seller Hist'!H:H),'Fastmoss 500'!D:D,'Fastmoss 500'!D:D)),"Não","Sim")) -> Sim | O197: =IF(AND(M197="Sim",N197="Sim"),"Sim","Não") -> Não | P197: =IF(I197>K197,"Sim","Não") -> Não | Q197: =COUNTIFS(C:C,C197) -> 1
C198: =_xlfn.XLOOKUP(F198,'Same Seller Hist'!H:H,'Same Seller Hist'!E:E) -> 411368149 | D198: =_xlfn.XLOOKUP(F198,'Same Seller Hist'!H:H,'Same Seller Hist'!D:D) -> Armazemdoschinelos | E198: =_xlfn.XLOOKUP(F198,'Same Seller Hist'!H:H,'Same Seller Hist'!I:I) -> 7.4961817e+18 | F198: Armazemdoschinelos | G198: =_xlfn.XLOOKUP(C198,'Same Seller Hist'!E:E,'Same Seller Hist'!F:F) -> Fashion | H198: =_xlfn.IFNA(_xlfn.XLOOKUP(C198,'Shp 500'!D:D,'Shp 500'!I:I),0) -> 0 | I198: =_xlfn.IFNA(_xlfn.XLOOKUP(C198,'Shp 500'!D:D,'Shp 500'!J:J),0) -> 0 | J198: 541.93548 | K198: 45161.29 | L198: Fastmoss 500 | M198: =IF(L198="Shp 500","Sim",IF(ISNA(_xlfn.XLOOKUP(C198,'Shp 500'!D:D,'Shp 500'!D:D)),"Não","Sim")) -> Não | N198: =IF(L198="Fastmoss 500","Sim",IF(ISNA(_xlfn.XLOOKUP(_xlfn.XLOOKUP(C198,'Same Seller Hist'!E:E,'Same Seller Hist'!H:H),'Fastmoss 500'!D:D,'Fastmoss 500'!D:D)),"Não","Sim")) -> Sim | O198: =IF(AND(M198="Sim",N198="Sim"),"Sim","Não") -> Não | P198: =IF(I198>K198,"Sim","Não") -> Não | Q198: =COUNTIFS(C:C,C198) -> 1
C199: 1041517511 | D199: tangshop_brasil | E199: =_xlfn.XLOOKUP(C199,'Same Seller Hist'!E:E,'Same Seller Hist'!I:I) -> 7.4961601e+18 | F199: =_xlfn.XLOOKUP(C199,'Same Seller Hist'!E:E,'Same Seller Hist'!H:H) -> Tang Lar & Estilo | G199: CN | H199: 1645.2903 | I199: 14495.395 | J199: =_xlfn.IFNA(_xlfn.XLOOKUP(F199,'Fastmoss 500'!D:D,'Fastmoss 500'!O:O),0) -> 706.45161 | K199: =_xlfn.IFNA(_xlfn.XLOOKUP(F199,'Fastmoss 500'!D:D,'Fastmoss 500'!N:N),0) -> 18312.903 | L199: Shp 500 | M199: =IF(L199="Shp 500","Sim",IF(ISNA(_xlfn.XLOOKUP(C199,'Shp 500'!D:D,'Shp 500'!D:D)),"Não","Sim")) -> Sim | N199: =IF(L199="Fastmoss 500","Sim",IF(ISNA(_xlfn.XLOOKUP(_xlfn.XLOOKUP(C199,'Same Seller Hist'!E:E,'Same Seller Hist'!H:H),'Fastmoss 500'!D:D,'Fastmoss 500'!D:D)),"Não","Sim")) -> Sim | O199: =IF(AND(M199="Sim",N199="Sim"),"Sim","Não") -> Sim | P199: =IF(I199>K199,"Sim","Não") -> Não | Q199: =COUNTIFS(C:C,C199) -> 1
C200: =_xlfn.XLOOKUP(F200,'Same Seller Hist'!H:H,'Same Seller Hist'!E:E) -> 427237722 | D200: =_xlfn.XLOOKUP(F200,'Same Seller Hist'!H:H,'Same Seller Hist'!D:D) -> Soul Bom | E200: =_xlfn.XLOOKUP(F200,'Same Seller Hist'!H:H,'Same Seller Hist'!I:I) -> 7.4961819e+18 | F200: Soul Bom | G200: =_xlfn.XLOOKUP(C200,'Same Seller Hist'!E:E,'Same Seller Hist'!F:F) -> FMCG | H200: =_xlfn.IFNA(_xlfn.XLOOKUP(C200,'Shp 500'!D:D,'Shp 500'!I:I),0) -> 0 | I200: =_xlfn.IFNA(_xlfn.XLOOKUP(C200,'Shp 500'!D:D,'Shp 500'!J:J),0) -> 0 | J200: 525.80645 | K200: 14809.677 | L200: Fastmoss 500 | M200: =IF(L200="Shp 500","Sim",IF(ISNA(_xlfn.XLOOKUP(C200,'Shp 500'!D:D,'Shp 500'!D:D)),"Não","Sim")) -> Não | N200: =IF(L200="Fastmoss 500","Sim",IF(ISNA(_xlfn.XLOOKUP(_xlfn.XLOOKUP(C200,'Same Seller Hist'!E:E,'Same Seller Hist'!H:H),'Fastmoss 500'!D:D,'Fastmoss 500'!D:D)),"Não","Sim")) -> Sim | O200: =IF(AND(M200="Sim",N200="Sim"),"Sim","Não") -> Não | P200: =IF(I200>K200,"Sim","Não") -> Não | Q200: =COUNTIFS(C:C,C200) -> 1
C201: =_xlfn.XLOOKUP(F201,'Same Seller Hist'!H:H,'Same Seller Hist'!E:E) -> 531238819 | D201: =_xlfn.XLOOKUP(F201,'Same Seller Hist'!H:H,'Same Seller Hist'!D:D) -> ColorfulDreams | E201: =_xlfn.XLOOKUP(F201,'Same Seller Hist'!H:H,'Same Seller Hist'!I:I) -> 7.4961834e+18 | F201: ColorfulDreams | G201: =_xlfn.XLOOKUP(C201,'Same Seller Hist'!E:E,'Same Seller Hist'!F:F) -> ELHA | H201: =_xlfn.IFNA(_xlfn.XLOOKUP(C201,'Shp 500'!D:D,'Shp 500'!I:I),0) -> 0 | I201: =_xlfn.IFNA(_xlfn.XLOOKUP(C201,'Shp 500'!D:D,'Shp 500'!J:J),0) -> 0 | J201: 509.67742 | K201: 16961.29 | L201: Fastmoss 500 | M201: =IF(L201="Shp 500","Sim",IF(ISNA(_xlfn.XLOOKUP(C201,'Shp 500'!D:D,'Shp 500'!D:D)),"Não","Sim")) -> Não | N201: =IF(L201="Fastmoss 500","Sim",IF(ISNA(_xlfn.XLOOKUP(_xlfn.XLOOKUP(C201,'Same Seller Hist'!E:E,'Same Seller Hist'!H:H),'Fastmoss 500'!D:D,'Fastmoss 500'!D:D)),"Não","Sim")) -> Sim | O201: =IF(AND(M201="Sim",N201="Sim"),"Sim","Não") -> Não | P201: =IF(I201>K201,"Sim","Não") -> Não | Q201: =COUNTIFS(C:C,C201) -> 1
C202: =_xlfn.XLOOKUP(F202,'Same Seller Hist'!H:H,'Same Seller Hist'!E:E) -> 1058502061 | D202: =_xlfn.XLOOKUP(F202,'Same Seller Hist'!H:H,'Same Seller Hist'!D:D) -> Nadin Modas | E202: =_xlfn.XLOOKUP(F202,'Same Seller Hist'!H:H,'Same Seller Hist'!I:I) -> 7.4961833e+18 | F202: Nadin Modas | G202: =_xlfn.XLOOKUP(C202,'Same Seller Hist'!E:E,'Same Seller Hist'!F:F) -> Fashion | H202: =_xlfn.IFNA(_xlfn.XLOOKUP(C202,'Shp 500'!D:D,'Shp 500'!I:I),0) -> 0 | I202: =_xlfn.IFNA(_xlfn.XLOOKUP(C202,'Shp 500'!D:D,'Shp 500'!J:J),0) -> 0 | J202: 509.67742 | K202: 23983.871 | L202: Fastmoss 500 | M202: =IF(L202="Shp 500","Sim",IF(ISNA(_xlfn.XLOOKUP(C202,'Shp 500'!D:D,'Shp 500'!D:D)),"Não","Sim")) -> Não | N202: =IF(L202="Fastmoss 500","Sim",IF(ISNA(_xlfn.XLOOKUP(_xlfn.XLOOKUP(C202,'Same Seller Hist'!E:E,'Same Seller Hist'!H:H),'Fastmoss 500'!D:D,'Fastmoss 500'!D:D)),"Não","Sim")) -> Sim | O202: =IF(AND(M202="Sim",N202="Sim"),"Sim","Não") -> Não | P202: =IF(I202>K202,"Sim","Não") -> Não | Q202: =COUNTIFS(C:C,C202) -> 1
C203: =_xlfn.XLOOKUP(F203,'Same Seller Hist'!H:H,'Same Seller Hist'!E:E) -> 1266325318 | D203: =_xlfn.XLOOKUP(F203,'Same Seller Hist'!H:H,'Same Seller Hist'!D:D) -> Attracione Men | E203: =_xlfn.XLOOKUP(F203,'Same Seller Hist'!H:H,'Same Seller Hist'!I:I) -> 7.4962053e+18 | F203: Attracione Men | G203: =_xlfn.XLOOKUP(C203,'Same Seller Hist'!E:E,'Same Seller Hist'!F:F) -> FMCG | H203: =_xlfn.IFNA(_xlfn.XLOOKUP(C203,'Shp 500'!D:D,'Shp 500'!I:I),0) -> 0 | I203: =_xlfn.IFNA(_xlfn.XLOOKUP(C203,'Shp 500'!D:D,'Shp 500'!J:J),0) -> 0 | J203: 509.67742 | K203: 54838.71 | L203: Fastmoss 500 | M203: =IF(L203="Shp 500","Sim",IF(ISNA(_xlfn.XLOOKUP(C203,'Shp 500'!D:D,'Shp 500'!D:D)),"Não","Sim")) -> Não | N203: =IF(L203="Fastmoss 500","Sim",IF(ISNA(_xlfn.XLOOKUP(_xlfn.XLOOKUP(C203,'Same Seller Hist'!E:E,'Same Seller Hist'!H:H),'Fastmoss 500'!D:D,'Fastmoss 500'!D:D)),"Não","Sim")) -> Sim | O203: =IF(AND(M203="Sim",N203="Sim"),"Sim","Não") -> Não | P203: =IF(I203>K203,"Sim","Não") -> Não | Q203: =COUNTIFS(C:C,C203) -> 1
C204: =_xlfn.XLOOKUP(F204,'Same Seller Hist'!H:H,'Same Seller Hist'!E:E) -> 717498842 | D204: =_xlfn.XLOOKUP(F204,'Same Seller Hist'!H:H,'Same Seller Hist'!D:D) -> SU MODA BR | E204: =_xlfn.XLOOKUP(F204,'Same Seller Hist'!H:H,'Same Seller Hist'!I:I) -> 7.4961818e+18 | F204: SU MODA BR | G204: =_xlfn.XLOOKUP(C204,'Same Seller Hist'!E:E,'Same Seller Hist'!F:F) -> 0 | H204: =_xlfn.IFNA(_xlfn.XLOOKUP(C204,'Shp 500'!D:D,'Shp 500'!I:I),0) -> 0 | I204: =_xlfn.IFNA(_xlfn.XLOOKUP(C204,'Shp 500'!D:D,'Shp 500'!J:J),0) -> 0 | J204: 503.22581 | K204: 16787.097 | L204: Fastmoss 500 | M204: =IF(L204="Shp 500","Sim",IF(ISNA(_xlfn.XLOOKUP(C204,'Shp 500'!D:D,'Shp 500'!D:D)),"Não","Sim")) -> Não | N204: =IF(L204="Fastmoss 500","Sim",IF(ISNA(_xlfn.XLOOKUP(_xlfn.XLOOKUP(C204,'Same Seller Hist'!E:E,'Same Seller Hist'!H:H),'Fastmoss 500'!D:D,'Fastmoss 500'!D:D)),"Não","Sim")) -> Sim | O204: =IF(AND(M204="Sim",N204="Sim"),"Sim","Não") -> Não | P204: =IF(I204>K204,"Sim","Não") -> Não | Q204: =COUNTIFS(C:C,C204) -> 1
C205: =_xlfn.XLOOKUP(F205,'Same Seller Hist'!H:H,'Same Seller Hist'!E:E) -> 1559124979 | D205: =_xlfn.XLOOKUP(F205,'Same Seller Hist'!H:H,'Same Seller Hist'!D:D) -> VII.TS shop | E205: =_xlfn.XLOOKUP(F205,'Same Seller Hist'!H:H,'Same Seller Hist'!I:I) -> 7.4961976e+18 | F205: VII.TS shop | G205: =_xlfn.XLOOKUP(C205,'Same Seller Hist'!E:E,'Same Seller Hist'!F:F) -> Fashion | H205: =_xlfn.IFNA(_xlfn.XLOOKUP(C205,'Shp 500'!D:D,'Shp 500'!I:I),0) -> 0 | I205: =_xlfn.IFNA(_xlfn.XLOOKUP(C205,'Shp 500'!D:D,'Shp 500'!J:J),0) -> 0 | J205: 503.22581 | K205: 35483.871 | L205: Fastmoss 500 | M205: =IF(L205="Shp 500","Sim",IF(ISNA(_xlfn.XLOOKUP(C205,'Shp 500'!D:D,'Shp 500'!D:D)),"Não","Sim")) -> Não | N205: =IF(L205="Fastmoss 500","Sim",IF(ISNA(_xlfn.XLOOKUP(_xlfn.XLOOKUP(C205,'Same Seller Hist'!E:E,'Same Seller Hist'!H:H),'Fastmoss 500'!D:D,'Fastmoss 500'!D:D)),"Não","Sim")) -> Sim | O205: =IF(AND(M205="Sim",N205="Sim"),"Sim","Não") -> Não | P205: =IF(I205>K205,"Sim","Não") -> Não | Q205: =COUNTIFS(C:C,C205) -> 1
C206: =_xlfn.XLOOKUP(F206,'Same Seller Hist'!H:H,'Same Seller Hist'!E:E) -> 315271502 | D206: =_xlfn.XLOOKUP(F206,'Same Seller Hist'!H:H,'Same Seller Hist'!D:D) -> PRIMO DECOR | E206: =_xlfn.XLOOKUP(F206,'Same Seller Hist'!H:H,'Same Seller Hist'!I:I) -> 7.4962513e+18 | F206: PRIMO DECOR | G206: =_xlfn.XLOOKUP(C206,'Same Seller Hist'!E:E,'Same Seller Hist'!F:F) -> Lifestyle | H206: =_xlfn.IFNA(_xlfn.XLOOKUP(C206,'Shp 500'!D:D,'Shp 500'!I:I),0) -> 0 | I206: =_xlfn.IFNA(_xlfn.XLOOKUP(C206,'Shp 500'!D:D,'Shp 500'!J:J),0) -> 0 | J206: 500 | K206: 11016.129 | L206: Fastmoss 500 | M206: =IF(L206="Shp 500","Sim",IF(ISNA(_xlfn.XLOOKUP(C206,'Shp 500'!D:D,'Shp 500'!D:D)),"Não","Sim")) -> Não | N206: =IF(L206="Fastmoss 500","Sim",IF(ISNA(_xlfn.XLOOKUP(_xlfn.XLOOKUP(C206,'Same Seller Hist'!E:E,'Same Seller Hist'!H:H),'Fastmoss 500'!D:D,'Fastmoss 500'!D:D)),"Não","Sim")) -> Sim | O206: =IF(AND(M206="Sim",N206="Sim"),"Sim","Não") -> Não | P206: =IF(I206>K206,"Sim","Não") -> Não | Q206: =COUNTIFS(C:C,C206) -> 1
C207: =_xlfn.XLOOKUP(F207,'Same Seller Hist'!H:H,'Same Seller Hist'!E:E) -> 1033200887 | D207: =_xlfn.XLOOKUP(F207,'Same Seller Hist'!H:H,'Same Seller Hist'!D:D) -> Fofo loja | E207: =_xlfn.XLOOKUP(F207,'Same Seller Hist'!H:H,'Same Seller Hist'!I:I) -> 7.4961892e+18 | F207: Fofo loja | G207: =_xlfn.XLOOKUP(C207,'Same Seller Hist'!E:E,'Same Seller Hist'!F:F) -> ELHA | H207: =_xlfn.IFNA(_xlfn.XLOOKUP(C207,'Shp 500'!D:D,'Shp 500'!I:I),0) -> 0 | I207: =_xlfn.IFNA(_xlfn.XLOOKUP(C207,'Shp 500'!D:D,'Shp 500'!J:J),0) -> 0 | J207: 493.54839 | K207: 28825.806 | L207: Fastmoss 500 | M207: =IF(L207="Shp 500","Sim",IF(ISNA(_xlfn.XLOOKUP(C207,'Shp 500'!D:D,'Shp 500'!D:D)),"Não","Sim")) -> Não | N207: =IF(L207="Fastmoss 500","Sim",IF(ISNA(_xlfn.XLOOKUP(_xlfn.XLOOKUP(C207,'Same Seller Hist'!E:E,'Same Seller Hist'!H:H),'Fastmoss 500'!D:D,'Fastmoss 500'!D:D)),"Não","Sim")) -> Sim | O207: =IF(AND(M207="Sim",N207="Sim"),"Sim","Não") -> Não | P207: =IF(I207>K207,"Sim","Não") -> Não | Q207: =COUNTIFS(C:C,C207) -> 1
C208: =_xlfn.XLOOKUP(F208,'Same Seller Hist'!H:H,'Same Seller Hist'!E:E) -> 562043869 | D208: =_xlfn.XLOOKUP(F208,'Same Seller Hist'!H:H,'Same Seller Hist'!D:D) -> LIFE FASHION BABY | E208: =_xlfn.XLOOKUP(F208,'Same Seller Hist'!H:H,'Same Seller Hist'!I:I) -> 7.4962794e+18 | F208: LIFE FASHION BABY | G208: =_xlfn.XLOOKUP(C208,'Same Seller Hist'!E:E,'Same Seller Hist'!F:F) -> Fashion | H208: =_xlfn.IFNA(_xlfn.XLOOKUP(C208,'Shp 500'!D:D,'Shp 500'!I:I),0) -> 0 | I208: =_xlfn.IFNA(_xlfn.XLOOKUP(C208,'Shp 500'!D:D,'Shp 500'!J:J),0) -> 0 | J208: 490.32258 | K208: 16016.129 | L208: Fastmoss 500 | M208: =IF(L208="Shp 500","Sim",IF(ISNA(_xlfn.XLOOKUP(C208,'Shp 500'!D:D,'Shp 500'!D:D)),"Não","Sim")) -> Não | N208: =IF(L208="Fastmoss 500","Sim",IF(ISNA(_xlfn.XLOOKUP(_xlfn.XLOOKUP(C208,'Same Seller Hist'!E:E,'Same Seller Hist'!H:H),'Fastmoss 500'!D:D,'Fastmoss 500'!D:D)),"Não","Sim")) -> Sim | O208: =IF(AND(M208="Sim",N208="Sim"),"Sim","Não") -> Não | P208: =IF(I208>K208,"Sim","Não") -> Não | Q208: =COUNTIFS(C:C,C208) -> 1
C209: =_xlfn.XLOOKUP(F209,'Same Seller Hist'!H:H,'Same Seller Hist'!E:E) -> 1187336421 | D209: =_xlfn.XLOOKUP(F209,'Same Seller Hist'!H:H,'Same Seller Hist'!D:D) -> EMILIMODA | E209: =_xlfn.XLOOKUP(F209,'Same Seller Hist'!H:H,'Same Seller Hist'!I:I) -> 7.4961476e+18 | F209: EMILIMODA | G209: =_xlfn.XLOOKUP(C209,'Same Seller Hist'!E:E,'Same Seller Hist'!F:F) -> Fashion | H209: =_xlfn.IFNA(_xlfn.XLOOKUP(C209,'Shp 500'!D:D,'Shp 500'!I:I),0) -> 0 | I209: =_xlfn.IFNA(_xlfn.XLOOKUP(C209,'Shp 500'!D:D,'Shp 500'!J:J),0) -> 0 | J209: 487.09677 | K209: 32258.065 | L209: Fastmoss 500 | M209: =IF(L209="Shp 500","Sim",IF(ISNA(_xlfn.XLOOKUP(C209,'Shp 500'!D:D,'Shp 500'!D:D)),"Não","Sim")) -> Não | N209: =IF(L209="Fastmoss 500","Sim",IF(ISNA(_xlfn.XLOOKUP(_xlfn.XLOOKUP(C209,'Same Seller Hist'!E:E,'Same Seller Hist'!H:H),'Fastmoss 500'!D:D,'Fastmoss 500'!D:D)),"Não","Sim")) -> Sim | O209: =IF(AND(M209="Sim",N209="Sim"),"Sim","Não") -> Não | P209: =IF(I209>K209,"Sim","Não") -> Não | Q209: =COUNTIFS(C:C,C209) -> 1
C210: 1046470373 | D210: Mundo Master Atacado | E210: =_xlfn.XLOOKUP(C210,'Same Seller Hist'!E:E,'Same Seller Hist'!I:I) -> 7.4961792e+18 | F210: =_xlfn.XLOOKUP(C210,'Same Seller Hist'!E:E,'Same Seller Hist'!H:H) -> Mundo Master | G210: CN | H210: 1006.3226 | I210: 5080.7054 | J210: =_xlfn.IFNA(_xlfn.XLOOKUP(F210,'Fastmoss 500'!D:D,'Fastmoss 500'!O:O),0) -> 280.64516 | K210: =_xlfn.IFNA(_xlfn.XLOOKUP(F210,'Fastmoss 500'!D:D,'Fastmoss 500'!N:N),0) -> 7641.9355 | L210: Shp 500 | M210: =IF(L210="Shp 500","Sim",IF(ISNA(_xlfn.XLOOKUP(C210,'Shp 500'!D:D,'Shp 500'!D:D)),"Não","Sim")) -> Sim | N210: =IF(L210="Fastmoss 500","Sim",IF(ISNA(_xlfn.XLOOKUP(_xlfn.XLOOKUP(C210,'Same Seller Hist'!E:E,'Same Seller Hist'!H:H),'Fastmoss 500'!D:D,'Fastmoss 500'!D:D)),"Não","Sim")) -> Sim | O210: =IF(AND(M210="Sim",N210="Sim"),"Sim","Não") -> Sim | P210: =IF(I210>K210,"Sim","Não") -> Não | Q210: =COUNTIFS(C:C,C210) -> 1
C211: =_xlfn.XLOOKUP(F211,'Same Seller Hist'!H:H,'Same Seller Hist'!E:E) -> 321115312 | D211: =_xlfn.XLOOKUP(F211,'Same Seller Hist'!H:H,'Same Seller Hist'!D:D) -> Dejule | E211: =_xlfn.XLOOKUP(F211,'Same Seller Hist'!H:H,'Same Seller Hist'!I:I) -> 7.4961549e+18 | F211: Dejule | G211: =_xlfn.XLOOKUP(C211,'Same Seller Hist'!E:E,'Same Seller Hist'!F:F) -> Fashion | H211: =_xlfn.IFNA(_xlfn.XLOOKUP(C211,'Shp 500'!D:D,'Shp 500'!I:I),0) -> 0 | I211: =_xlfn.IFNA(_xlfn.XLOOKUP(C211,'Shp 500'!D:D,'Shp 500'!J:J),0) -> 0 | J211: 480.64516 | K211: 15335.484 | L211: Fastmoss 500 | M211: =IF(L211="Shp 500","Sim",IF(ISNA(_xlfn.XLOOKUP(C211,'Shp 500'!D:D,'Shp 500'!D:D)),"Não","Sim")) -> Não | N211: =IF(L211="Fastmoss 500","Sim",IF(ISNA(_xlfn.XLOOKUP(_xlfn.XLOOKUP(C211,'Same Seller Hist'!E:E,'Same Seller Hist'!H:H),'Fastmoss 500'!D:D,'Fastmoss 500'!D:D)),"Não","Sim")) -> Sim | O211: =IF(AND(M211="Sim",N211="Sim"),"Sim","Não") -> Não | P211: =IF(I211>K211,"Sim","Não") -> Não | Q211: =COUNTIFS(C:C,C211) -> 1
C212: =_xlfn.XLOOKUP(F212,'Same Seller Hist'!H:H,'Same Seller Hist'!E:E) -> 1498117394 | D212: =_xlfn.XLOOKUP(F212,'Same Seller Hist'!H:H,'Same Seller Hist'!D:D) -> MISSORDBR | E212: =_xlfn.XLOOKUP(F212,'Same Seller Hist'!H:H,'Same Seller Hist'!I:I) -> 7.4961605e+18 | F212: MISSORDBR | G212: =_xlfn.XLOOKUP(C212,'Same Seller Hist'!E:E,'Same Seller Hist'!F:F) -> Fashion | H212: =_xlfn.IFNA(_xlfn.XLOOKUP(C212,'Shp 500'!D:D,'Shp 500'!I:I),0) -> 0 | I212: =_xlfn.IFNA(_xlfn.XLOOKUP(C212,'Shp 500'!D:D,'Shp 500'!J:J),0) -> 0 | J212: 477.41935 | K212: 41935.484 | L212: Fastmoss 500 | M212: =IF(L212="Shp 500","Sim",IF(ISNA(_xlfn.XLOOKUP(C212,'Shp 500'!D:D,'Shp 500'!D:D)),"Não","Sim")) -> Não | N212: =IF(L212="Fastmoss 500","Sim",IF(ISNA(_xlfn.XLOOKUP(_xlfn.XLOOKUP(C212,'Same Seller Hist'!E:E,'Same Seller Hist'!H:H),'Fastmoss 500'!D:D,'Fastmoss 500'!D:D)),"Não","Sim")) -> Sim | O212: =IF(AND(M212="Sim",N212="Sim"),"Sim","Não") -> Não | P212: =IF(I212>K212,"Sim","Não") -> Não | Q212: =COUNTIFS(C:C,C212) -> 1
C213: =_xlfn.XLOOKUP(F213,'Same Seller Hist'!H:H,'Same Seller Hist'!E:E) -> 1615249318 | D213: =_xlfn.XLOOKUP(F213,'Same Seller Hist'!H:H,'Same Seller Hist'!D:D) -> LARA VIVA | E213: =_xlfn.XLOOKUP(F213,'Same Seller Hist'!H:H,'Same Seller Hist'!I:I) -> 7.4941764e+18 | F213: LARA VIVA | G213: =_xlfn.XLOOKUP(C213,'Same Seller Hist'!E:E,'Same Seller Hist'!F:F) -> 0 | H213: =_xlfn.IFNA(_xlfn.XLOOKUP(C213,'Shp 500'!D:D,'Shp 500'!I:I),0) -> 0 | I213: =_xlfn.IFNA(_xlfn.XLOOKUP(C213,'Shp 500'!D:D,'Shp 500'!J:J),0) -> 0 | J213: 474.19355 | K213: 26706.452 | L213: Fastmoss 500 | M213: =IF(L213="Shp 500","Sim",IF(ISNA(_xlfn.XLOOKUP(C213,'Shp 500'!D:D,'Shp 500'!D:D)),"Não","Sim")) -> Não | N213: =IF(L213="Fastmoss 500","Sim",IF(ISNA(_xlfn.XLOOKUP(_xlfn.XLOOKUP(C213,'Same Seller Hist'!E:E,'Same Seller Hist'!H:H),'Fastmoss 500'!D:D,'Fastmoss 500'!D:D)),"Não","Sim")) -> Sim | O213: =IF(AND(M213="Sim",N213="Sim"),"Sim","Não") -> Não | P213: =IF(I213>K213,"Sim","Não") -> Não | Q213: =COUNTIFS(C:C,C213) -> 1
C214: =_xlfn.XLOOKUP(F214,'Same Seller Hist'!H:H,'Same Seller Hist'!E:E) -> 867115662 | D214: =_xlfn.XLOOKUP(F214,'Same Seller Hist'!H:H,'Same Seller Hist'!D:D) -> Loja Ragde | E214: =_xlfn.XLOOKUP(F214,'Same Seller Hist'!H:H,'Same Seller Hist'!I:I) -> 7.4961857e+18 | F214: Loja Ragde | G214: =_xlfn.XLOOKUP(C214,'Same Seller Hist'!E:E,'Same Seller Hist'!F:F) -> Fashion | H214: =_xlfn.IFNA(_xlfn.XLOOKUP(C214,'Shp 500'!D:D,'Shp 500'!I:I),0) -> 0 | I214: =_xlfn.IFNA(_xlfn.XLOOKUP(C214,'Shp 500'!D:D,'Shp 500'!J:J),0) -> 0 | J214: 464.51613 | K214: 24325.806 | L214: Fastmoss 500 | M214: =IF(L214="Shp 500","Sim",IF(ISNA(_xlfn.XLOOKUP(C214,'Shp 500'!D:D,'Shp 500'!D:D)),"Não","Sim")) -> Não | N214: =IF(L214="Fastmoss 500","Sim",IF(ISNA(_xlfn.XLOOKUP(_xlfn.XLOOKUP(C214,'Same Seller Hist'!E:E,'Same Seller Hist'!H:H),'Fastmoss 500'!D:D,'Fastmoss 500'!D:D)),"Não","Sim")) -> Sim | O214: =IF(AND(M214="Sim",N214="Sim"),"Sim","Não") -> Não | P214: =IF(I214>K214,"Sim","Não") -> Não | Q214: =COUNTIFS(C:C,C214) -> 1
C215: =_xlfn.XLOOKUP(F215,'Same Seller Hist'!H:H,'Same Seller Hist'!E:E) -> 288781879 | D215: =_xlfn.XLOOKUP(F215,'Same Seller Hist'!H:H,'Same Seller Hist'!D:D) -> MP CONFECÇÕES | E215: =_xlfn.XLOOKUP(F215,'Same Seller Hist'!H:H,'Same Seller Hist'!I:I) -> 7.4962669e+18 | F215: MP CONFECÇÕES | G215: =_xlfn.XLOOKUP(C215,'Same Seller Hist'!E:E,'Same Seller Hist'!F:F) -> Lifestyle | H215: =_xlfn.IFNA(_xlfn.XLOOKUP(C215,'Shp 500'!D:D,'Shp 500'!I:I),0) -> 0 | I215: =_xlfn.IFNA(_xlfn.XLOOKUP(C215,'Shp 500'!D:D,'Shp 500'!J:J),0) -> 0 | J215: 464.51613 | K215: 20958.065 | L215: Fastmoss 500 | M215: =IF(L215="Shp 500","Sim",IF(ISNA(_xlfn.XLOOKUP(C215,'Shp 500'!D:D,'Shp 500'!D:D)),"Não","Sim")) -> Não | N215: =IF(L215="Fastmoss 500","Sim",IF(ISNA(_xlfn.XLOOKUP(_xlfn.XLOOKUP(C215,'Same Seller Hist'!E:E,'Same Seller Hist'!H:H),'Fastmoss 500'!D:D,'Fastmoss 500'!D:D)),"Não","Sim")) -> Sim | O215: =IF(AND(M215="Sim",N215="Sim"),"Sim","Não") -> Não | P215: =IF(I215>K215,"Sim","Não") -> Não | Q215: =COUNTIFS(C:C,C215) -> 1
C216: =_xlfn.XLOOKUP(F216,'Same Seller Hist'!H:H,'Same Seller Hist'!E:E) -> 1067229535 | D216: =_xlfn.XLOOKUP(F216,'Same Seller Hist'!H:H,'Same Seller Hist'!D:D) -> ACME BRASIL | E216: =_xlfn.XLOOKUP(F216,'Same Seller Hist'!H:H,'Same Seller Hist'!I:I) -> 7.4961476e+18 | F216: ACME BRASIL | G216: =_xlfn.XLOOKUP(C216,'Same Seller Hist'!E:E,'Same Seller Hist'!F:F) -> Fashion | H216: =_xlfn.IFNA(_xlfn.XLOOKUP(C216,'Shp 500'!D:D,'Shp 500'!I:I),0) -> 0 | I216: =_xlfn.IFNA(_xlfn.XLOOKUP(C216,'Shp 500'!D:D,'Shp 500'!J:J),0) -> 0 | J216: 451.6129 | K216: 31470.968 | L216: Fastmoss 500 | M216: =IF(L216="Shp 500","Sim",IF(ISNA(_xlfn.XLOOKUP(C216,'Shp 500'!D:D,'Shp 500'!D:D)),"Não","Sim")) -> Não | N216: =IF(L216="Fastmoss 500","Sim",IF(ISNA(_xlfn.XLOOKUP(_xlfn.XLOOKUP(C216,'Same Seller Hist'!E:E,'Same Seller Hist'!H:H),'Fastmoss 500'!D:D,'Fastmoss 500'!D:D)),"Não","Sim")) -> Sim | O216: =IF(AND(M216="Sim",N216="Sim"),"Sim","Não") -> Não | P216: =IF(I216>K216,"Sim","Não") -> Não | Q216: =COUNTIFS(C:C,C216) -> 1
C217: =_xlfn.XLOOKUP(F217,'Same Seller Hist'!H:H,'Same Seller Hist'!E:E) -> 389800143 | D217: =_xlfn.XLOOKUP(F217,'Same Seller Hist'!H:H,'Same Seller Hist'!D:D) -> INVICTUS ESHOP | E217: =_xlfn.XLOOKUP(F217,'Same Seller Hist'!H:H,'Same Seller Hist'!I:I) -> 7.4961474e+18 | F217: INVICTUS ESHOP | G217: =_xlfn.XLOOKUP(C217,'Same Seller Hist'!E:E,'Same Seller Hist'!F:F) -> FMCG | H217: =_xlfn.IFNA(_xlfn.XLOOKUP(C217,'Shp 500'!D:D,'Shp 500'!I:I),0) -> 0 | I217: =_xlfn.IFNA(_xlfn.XLOOKUP(C217,'Shp 500'!D:D,'Shp 500'!J:J),0) -> 0 | J217: 448.3871 | K217: 23325.806 | L217: Fastmoss 500 | M217: =IF(L217="Shp 500","Sim",IF(ISNA(_xlfn.XLOOKUP(C217,'Shp 500'!D:D,'Shp 500'!D:D)),"Não","Sim")) -> Não | N217: =IF(L217="Fastmoss 500","Sim",IF(ISNA(_xlfn.XLOOKUP(_xlfn.XLOOKUP(C217,'Same Seller Hist'!E:E,'Same Seller Hist'!H:H),'Fastmoss 500'!D:D,'Fastmoss 500'!D:D)),"Não","Sim")) -> Sim | O217: =IF(AND(M217="Sim",N217="Sim"),"Sim","Não") -> Não | P217: =IF(I217>K217,"Sim","Não") -> Não | Q217: =COUNTIFS(C:C,C217) -> 1
C218: =_xlfn.XLOOKUP(F218,'Same Seller Hist'!H:H,'Same Seller Hist'!E:E) -> 1013290785 | D218: =_xlfn.XLOOKUP(F218,'Same Seller Hist'!H:H,'Same Seller Hist'!D:D) -> Stella vista moda | E218: =_xlfn.XLOOKUP(F218,'Same Seller Hist'!H:H,'Same Seller Hist'!I:I) -> 7.4961473e+18 | F218: Stella vista moda | G218: =_xlfn.XLOOKUP(C218,'Same Seller Hist'!E:E,'Same Seller Hist'!F:F) -> Fashion | H218: =_xlfn.IFNA(_xlfn.XLOOKUP(C218,'Shp 500'!D:D,'Shp 500'!I:I),0) -> 0 | I218: =_xlfn.IFNA(_xlfn.XLOOKUP(C218,'Shp 500'!D:D,'Shp 500'!J:J),0) -> 0 | J218: 445.16129 | K218: 32258.065 | L218: Fastmoss 500 | M218: =IF(L218="Shp 500","Sim",IF(ISNA(_xlfn.XLOOKUP(C218,'Shp 500'!D:D,'Shp 500'!D:D)),"Não","Sim")) -> Não | N218: =IF(L218="Fastmoss 500","Sim",IF(ISNA(_xlfn.XLOOKUP(_xlfn.XLOOKUP(C218,'Same Seller Hist'!E:E,'Same Seller Hist'!H:H),'Fastmoss 500'!D:D,'Fastmoss 500'!D:D)),"Não","Sim")) -> Sim | O218: =IF(AND(M218="Sim",N218="Sim"),"Sim","Não") -> Não | P218: =IF(I218>K218,"Sim","Não") -> Não | Q218: =COUNTIFS(C:C,C218) -> 1
C219: =_xlfn.XLOOKUP(F219,'Same Seller Hist'!H:H,'Same Seller Hist'!E:E) -> 1334088625 | D219: =_xlfn.XLOOKUP(F219,'Same Seller Hist'!H:H,'Same Seller Hist'!D:D) -> WYL Top Comércio | E219: =_xlfn.XLOOKUP(F219,'Same Seller Hist'!H:H,'Same Seller Hist'!I:I) -> 7.496182e+18 | F219: WYL Top Comércio | G219: =_xlfn.XLOOKUP(C219,'Same Seller Hist'!E:E,'Same Seller Hist'!F:F) -> FMCG | H219: =_xlfn.IFNA(_xlfn.XLOOKUP(C219,'Shp 500'!D:D,'Shp 500'!I:I),0) -> 0 | I219: =_xlfn.IFNA(_xlfn.XLOOKUP(C219,'Shp 500'!D:D,'Shp 500'!J:J),0) -> 0 | J219: 441.93548 | K219: 7809.6774 | L219: Fastmoss 500 | M219: =IF(L219="Shp 500","Sim",IF(ISNA(_xlfn.XLOOKUP(C219,'Shp 500'!D:D,'Shp 500'!D:D)),"Não","Sim")) -> Não | N219: =IF(L219="Fastmoss 500","Sim",IF(ISNA(_xlfn.XLOOKUP(_xlfn.XLOOKUP(C219,'Same Seller Hist'!E:E,'Same Seller Hist'!H:H),'Fastmoss 500'!D:D,'Fastmoss 500'!D:D)),"Não","Sim")) -> Sim | O219: =IF(AND(M219="Sim",N219="Sim"),"Sim","Não") -> Não | P219: =IF(I219>K219,"Sim","Não") -> Não | Q219: =COUNTIFS(C:C,C219) -> 1
C220: 1057319077 | D220: LEO BUY SHOP | E220: =_xlfn.XLOOKUP(C220,'Same Seller Hist'!E:E,'Same Seller Hist'!I:I) -> 7.4963048e+18 | F220: =_xlfn.XLOOKUP(C220,'Same Seller Hist'!E:E,'Same Seller Hist'!H:H) -> LEO BUY SHOP | G220: CN | H220: 3971.5484 | I220: 34373.153 | J220: =_xlfn.IFNA(_xlfn.XLOOKUP(F220,'Fastmoss 500'!D:D,'Fastmoss 500'!O:O),0) -> 1938.7097 | K220: =_xlfn.IFNA(_xlfn.XLOOKUP(F220,'Fastmoss 500'!D:D,'Fastmoss 500'!N:N),0) -> 138709.68 | L220: Shp 500 | M220: =IF(L220="Shp 500","Sim",IF(ISNA(_xlfn.XLOOKUP(C220,'Shp 500'!D:D,'Shp 500'!D:D)),"Não","Sim")) -> Sim | N220: =IF(L220="Fastmoss 500","Sim",IF(ISNA(_xlfn.XLOOKUP(_xlfn.XLOOKUP(C220,'Same Seller Hist'!E:E,'Same Seller Hist'!H:H),'Fastmoss 500'!D:D,'Fastmoss 500'!D:D)),"Não","Sim")) -> Sim | O220: =IF(AND(M220="Sim",N220="Sim"),"Sim","Não") -> Sim | P220: =IF(I220>K220,"Sim","Não") -> Não | Q220: =COUNTIFS(C:C,C220) -> 1
C221: =_xlfn.XLOOKUP(F221,'Same Seller Hist'!H:H,'Same Seller Hist'!E:E) -> 1252832710 | D221: =_xlfn.XLOOKUP(F221,'Same Seller Hist'!H:H,'Same Seller Hist'!D:D) -> Ninevariedades | E221: =_xlfn.XLOOKUP(F221,'Same Seller Hist'!H:H,'Same Seller Hist'!I:I) -> 7.4941462e+18 | F221: Ninevariedades | G221: =_xlfn.XLOOKUP(C221,'Same Seller Hist'!E:E,'Same Seller Hist'!F:F) -> 0 | H221: =_xlfn.IFNA(_xlfn.XLOOKUP(C221,'Shp 500'!D:D,'Shp 500'!I:I),0) -> 0 | I221: =_xlfn.IFNA(_xlfn.XLOOKUP(C221,'Shp 500'!D:D,'Shp 500'!J:J),0) -> 0 | J221: 432.25806 | K221: 22806.452 | L221: Fastmoss 500 | M221: =IF(L221="Shp 500","Sim",IF(ISNA(_xlfn.XLOOKUP(C221,'Shp 500'!D:D,'Shp 500'!D:D)),"Não","Sim")) -> Não | N221: =IF(L221="Fastmoss 500","Sim",IF(ISNA(_xlfn.XLOOKUP(_xlfn.XLOOKUP(C221,'Same Seller Hist'!E:E,'Same Seller Hist'!H:H),'Fastmoss 500'!D:D,'Fastmoss 500'!D:D)),"Não","Sim")) -> Sim | O221: =IF(AND(M221="Sim",N221="Sim"),"Sim","Não") -> Não | P221: =IF(I221>K221,"Sim","Não") -> Não | Q221: =COUNTIFS(C:C,C221) -> 1
C222: =_xlfn.XLOOKUP(F222,'Same Seller Hist'!H:H,'Same Seller Hist'!E:E) -> 325503017 | D222: =_xlfn.XLOOKUP(F222,'Same Seller Hist'!H:H,'Same Seller Hist'!D:D) -> Galuno Artesanato em Madeira | E222: =_xlfn.XLOOKUP(F222,'Same Seller Hist'!H:H,'Same Seller Hist'!I:I) -> 7.4962167e+18 | F222: Galuno Artesanato em Madeira | G222: =_xlfn.XLOOKUP(C222,'Same Seller Hist'!E:E,'Same Seller Hist'!F:F) -> Lifestyle | H222: =_xlfn.IFNA(_xlfn.XLOOKUP(C222,'Shp 500'!D:D,'Shp 500'!I:I),0) -> 0 | I222: =_xlfn.IFNA(_xlfn.XLOOKUP(C222,'Shp 500'!D:D,'Shp 500'!J:J),0) -> 0 | J222: 425.80645 | K222: 7925.8065 | L222: Fastmoss 500 | M222: =IF(L222="Shp 500","Sim",IF(ISNA(_xlfn.XLOOKUP(C222,'Shp 500'!D:D,'Shp 500'!D:D)),"Não","Sim")) -> Não | N222: =IF(L222="Fastmoss 500","Sim",IF(ISNA(_xlfn.XLOOKUP(_xlfn.XLOOKUP(C222,'Same Seller Hist'!E:E,'Same Seller Hist'!H:H),'Fastmoss 500'!D:D,'Fastmoss 500'!D:D)),"Não","Sim")) -> Sim | O222: =IF(AND(M222="Sim",N222="Sim"),"Sim","Não") -> Não | P222: =IF(I222>K222,"Sim","Não") -> Não | Q222: =COUNTIFS(C:C,C222) -> 1
C223: =_xlfn.XLOOKUP(F223,'Same Seller Hist'!H:H,'Same Seller Hist'!E:E) -> 1420699091 | D223: =_xlfn.XLOOKUP(F223,'Same Seller Hist'!H:H,'Same Seller Hist'!D:D) -> Bestbrasil | E223: =_xlfn.XLOOKUP(F223,'Same Seller Hist'!H:H,'Same Seller Hist'!I:I) -> 7.4963198e+18 | F223: Bestbrasil | G223: =_xlfn.XLOOKUP(C223,'Same Seller Hist'!E:E,'Same Seller Hist'!F:F) -> Lifestyle | H223: =_xlfn.IFNA(_xlfn.XLOOKUP(C223,'Shp 500'!D:D,'Shp 500'!I:I),0) -> 0 | I223: =_xlfn.IFNA(_xlfn.XLOOKUP(C223,'Shp 500'!D:D,'Shp 500'!J:J),0) -> 0 | J223: 425.80645 | K223: 18812.903 | L223: Fastmoss 500 | M223: =IF(L223="Shp 500","Sim",IF(ISNA(_xlfn.XLOOKUP(C223,'Shp 500'!D:D,'Shp 500'!D:D)),"Não","Sim")) -> Não | N223: =IF(L223="Fastmoss 500","Sim",IF(ISNA(_xlfn.XLOOKUP(_xlfn.XLOOKUP(C223,'Same Seller Hist'!E:E,'Same Seller Hist'!H:H),'Fastmoss 500'!D:D,'Fastmoss 500'!D:D)),"Não","Sim")) -> Sim | O223: =IF(AND(M223="Sim",N223="Sim"),"Sim","Não") -> Não | P223: =IF(I223>K223,"Sim","Não") -> Não | Q223: =COUNTIFS(C:C,C223) -> 1
C224: =_xlfn.XLOOKUP(F224,'Same Seller Hist'!H:H,'Same Seller Hist'!E:E) -> 1114645438 | D224: =_xlfn.XLOOKUP(F224,'Same Seller Hist'!H:H,'Same Seller Hist'!D:D) -> bettdow.br | E224: =_xlfn.XLOOKUP(F224,'Same Seller Hist'!H:H,'Same Seller Hist'!I:I) -> 7.4961474e+18 | F224: bettdow.br | G224: =_xlfn.XLOOKUP(C224,'Same Seller Hist'!E:E,'Same Seller Hist'!F:F) -> ELHA | H224: =_xlfn.IFNA(_xlfn.XLOOKUP(C224,'Shp 500'!D:D,'Shp 500'!I:I),0) -> 0 | I224: =_xlfn.IFNA(_xlfn.XLOOKUP(C224,'Shp 500'!D:D,'Shp 500'!J:J),0) -> 0 | J224: 1035.4839 | K224: 83870.968 | L224: Fastmoss 500 | M224: =IF(L224="Shp 500","Sim",IF(ISNA(_xlfn.XLOOKUP(C224,'Shp 500'!D:D,'Shp 500'!D:D)),"Não","Sim")) -> Não | N224: =IF(L224="Fastmoss 500","Sim",IF(ISNA(_xlfn.XLOOKUP(_xlfn.XLOOKUP(C224,'Same Seller Hist'!E:E,'Same Seller Hist'!H:H),'Fastmoss 500'!D:D,'Fastmoss 500'!D:D)),"Não","Sim")) -> Sim | O224: =IF(AND(M224="Sim",N224="Sim"),"Sim","Não") -> Não | P224: =IF(I224>K224,"Sim","Não") -> Não | Q224: =COUNTIFS(C:C,C224) -> 1
C225: =_xlfn.XLOOKUP(F225,'Same Seller Hist'!H:H,'Same Seller Hist'!E:E) -> 1615209975 | D225: =_xlfn.XLOOKUP(F225,'Same Seller Hist'!H:H,'Same Seller Hist'!D:D) -> Lafu | E225: =_xlfn.XLOOKUP(F225,'Same Seller Hist'!H:H,'Same Seller Hist'!I:I) -> 7.4941285e+18 | F225: Lafu | G225: =_xlfn.XLOOKUP(C225,'Same Seller Hist'!E:E,'Same Seller Hist'!F:F) -> FMCG | H225: =_xlfn.IFNA(_xlfn.XLOOKUP(C225,'Shp 500'!D:D,'Shp 500'!I:I),0) -> 0 | I225: =_xlfn.IFNA(_xlfn.XLOOKUP(C225,'Shp 500'!D:D,'Shp 500'!J:J),0) -> 0 | J225: 403.22581 | K225: 20958.065 | L225: Fastmoss 500 | M225: =IF(L225="Shp 500","Sim",IF(ISNA(_xlfn.XLOOKUP(C225,'Shp 500'!D:D,'Shp 500'!D:D)),"Não","Sim")) -> Não | N225: =IF(L225="Fastmoss 500","Sim",IF(ISNA(_xlfn.XLOOKUP(_xlfn.XLOOKUP(C225,'Same Seller Hist'!E:E,'Same Seller Hist'!H:H),'Fastmoss 500'!D:D,'Fastmoss 500'!D:D)),"Não","Sim")) -> Sim | O225: =IF(AND(M225="Sim",N225="Sim"),"Sim","Não") -> Não | P225: =IF(I225>K225,"Sim","Não") -> Não | Q225: =COUNTIFS(C:C,C225) -> 1
...

Sheet Analysis Table dup
B3: TABELA DE SUPORTE PARA ANÁLISE
C7: shop_id_shp | D7: shop_name_shp | E7: shop_id_tts | F7: shop_name_tts | G7: cluster | H7: net_ado_shp | I7: net_adnmv_usd_shp | J7: net_ado_tts | K7: net_adnmv_usd_tts | L7: source | M7: top_at_shp | N7: top_at_tts | O7: top_at_both | P7: bigger_at_shp | Q7: duplicates
C8: 291174073 | D8: ZSZ_Official Store | E8: =_xlfn.XLOOKUP(C8,'Same Seller Hist'!E:E,'Same Seller Hist'!I:I) -> 7.4961635e+18 | F8: =_xlfn.XLOOKUP(C8,'Same Seller Hist'!E:E,'Same Seller Hist'!H:H) -> ZSZ BR | G8: CN | H8: 1622 | I8: 9436.935 | J8: =_xlfn.IFNA(_xlfn.XLOOKUP(F8,'Fastmoss 500'!D:D,'Fastmoss 500'!O:O),0) -> 700 | K8: =_xlfn.IFNA(_xlfn.XLOOKUP(F8,'Fastmoss 500'!D:D,'Fastmoss 500'!N:N),0) -> 14158.065 | L8: Shp 500 | M8: =IF(L8="Shp 500","Sim",IF(ISNA(_xlfn.XLOOKUP(C8,'Shp 500'!D:D,'Shp 500'!D:D)),"Não","Sim")) -> Sim | N8: =IF(L8="Fastmoss 500","Sim",IF(ISNA(_xlfn.XLOOKUP(_xlfn.XLOOKUP(C8,'Same Seller Hist'!E:E,'Same Seller Hist'!H:H),'Fastmoss 500'!D:D,'Fastmoss 500'!D:D)),"Não","Sim")) -> Sim | O8: =IF(AND(M8="Sim",N8="Sim"),"Sim","Não") -> Sim | P8: =IF(I8>K8,"Sim","Não") -> Não | Q8: =COUNTIFS(C:C,C8) -> 2
C9: =_xlfn.XLOOKUP(F9,'Same Seller Hist'!H:H,'Same Seller Hist'!E:E) -> 291174073 | D9: =_xlfn.XLOOKUP(F9,'Same Seller Hist'!H:H,'Same Seller Hist'!D:D) -> ZSZ BR | E9: =_xlfn.XLOOKUP(F9,'Same Seller Hist'!H:H,'Same Seller Hist'!I:I) -> 7.4961635e+18 | F9: ZSZ BR | G9: =_xlfn.XLOOKUP(C9,'Same Seller Hist'!E:E,'Same Seller Hist'!F:F) -> Lifestyle | H9: =_xlfn.IFNA(_xlfn.XLOOKUP(C9,'Shp 500'!D:D,'Shp 500'!I:I),0) -> 1622 | I9: =_xlfn.IFNA(_xlfn.XLOOKUP(C9,'Shp 500'!D:D,'Shp 500'!J:J),0) -> 9436.935 | J9: 700 | K9: 14158.065 | L9: Fastmoss 500 | M9: =IF(L9="Shp 500","Sim",IF(ISNA(_xlfn.XLOOKUP(C9,'Shp 500'!D:D,'Shp 500'!D:D)),"Não","Sim")) -> Sim | N9: =IF(L9="Fastmoss 500","Sim",IF(ISNA(_xlfn.XLOOKUP(_xlfn.XLOOKUP(C9,'Same Seller Hist'!E:E,'Same Seller Hist'!H:H),'Fastmoss 500'!D:D,'Fastmoss 500'!D:D)),"Não","Sim")) -> Sim | O9: =IF(AND(M9="Sim",N9="Sim"),"Sim","Não") -> Sim | P9: =IF(I9>K9,"Sim","Não") -> Não | Q9: =COUNTIFS(C:C,C9) -> 2
C10: 552896405 | D10: Casa_Completa_Enxovais | E10: =_xlfn.XLOOKUP(C10,'Same Seller Hist'!E:E,'Same Seller Hist'!I:I) -> 7.49626e+18 | F10: =_xlfn.XLOOKUP(C10,'Same Seller Hist'!E:E,'Same Seller Hist'!H:H) -> Casa Completa Enxovais | G10: Lifestyle | H10: 5043.8387 | I10: 53289.304 | J10: =_xlfn.IFNA(_xlfn.XLOOKUP(F10,'Fastmoss 500'!D:D,'Fastmoss 500'!O:O),0) -> 0 | K10: =_xlfn.IFNA(_xlfn.XLOOKUP(F10,'Fastmoss 500'!D:D,'Fastmoss 500'!N:N),0) -> 0 | L10: Shp 500 | M10: =IF(L10="Shp 500","Sim",IF(ISNA(_xlfn.XLOOKUP(C10,'Shp 500'!D:D,'Shp 500'!D:D)),"Não","Sim")) -> Sim | N10: =IF(L10="Fastmoss 500","Sim",IF(ISNA(_xlfn.XLOOKUP(_xlfn.XLOOKUP(C10,'Same Seller Hist'!E:E,'Same Seller Hist'!H:H),'Fastmoss 500'!D:D,'Fastmoss 500'!D:D)),"Não","Sim")) -> Não | O10: =IF(AND(M10="Sim",N10="Sim"),"Sim","Não") -> Não | P10: =IF(I10>K10,"Sim","Não") -> Sim | Q10: =COUNTIFS(C:C,C10) -> 1
C11: 974102638 | D11: Loja 128 | E11: =_xlfn.XLOOKUP(C11,'Same Seller Hist'!E:E,'Same Seller Hist'!I:I) -> 7.4962283e+18 | F11: =_xlfn.XLOOKUP(C11,'Same Seller Hist'!E:E,'Same Seller Hist'!H:H) -> blueepulse | G11: CN | H11: 4870.1613 | I11: 49065.871 | J11: =_xlfn.IFNA(_xlfn.XLOOKUP(F11,'Fastmoss 500'!D:D,'Fastmoss 500'!O:O),0) -> 0 | K11: =_xlfn.IFNA(_xlfn.XLOOKUP(F11,'Fastmoss 500'!D:D,'Fastmoss 500'!N:N),0) -> 0 | L11: Shp 500 | M11: =IF(L11="Shp 500","Sim",IF(ISNA(_xlfn.XLOOKUP(C11,'Shp 500'!D:D,'Shp 500'!D:D)),"Não","Sim")) -> Sim | N11: =IF(L11="Fastmoss 500","Sim",IF(ISNA(_xlfn.XLOOKUP(_xlfn.XLOOKUP(C11,'Same Seller Hist'!E:E,'Same Seller Hist'!H:H),'Fastmoss 500'!D:D,'Fastmoss 500'!D:D)),"Não","Sim")) -> Não | O11: =IF(AND(M11="Sim",N11="Sim"),"Sim","Não") -> Não | P11: =IF(I11>K11,"Sim","Não") -> Sim | Q11: =COUNTIFS(C:C,C11) -> 1
C12: 362859393 | D12: ALFA MERCEARIA.BR | E12: =_xlfn.XLOOKUP(C12,'Same Seller Hist'!E:E,'Same Seller Hist'!I:I) -> 7.4961597e+18 | F12: =_xlfn.XLOOKUP(C12,'Same Seller Hist'!E:E,'Same Seller Hist'!H:H) -> ALFA SHOP.BR | G12: CN | H12: 4604.9355 | I12: 14928.731 | J12: =_xlfn.IFNA(_xlfn.XLOOKUP(F12,'Fastmoss 500'!D:D,'Fastmoss 500'!O:O),0) -> 0 | K12: =_xlfn.IFNA(_xlfn.XLOOKUP(F12,'Fastmoss 500'!D:D,'Fastmoss 500'!N:N),0) -> 0 | L12: Shp 500 | M12: =IF(L12="Shp 500","Sim",IF(ISNA(_xlfn.XLOOKUP(C12,'Shp 500'!D:D,'Shp 500'!D:D)),"Não","Sim")) -> Sim | N12: =IF(L12="Fastmoss 500","Sim",IF(ISNA(_xlfn.XLOOKUP(_xlfn.XLOOKUP(C12,'Same Seller Hist'!E:E,'Same Seller Hist'!H:H),'Fastmoss 500'!D:D,'Fastmoss 500'!D:D)),"Não","Sim")) -> Não | O12: =IF(AND(M12="Sim",N12="Sim"),"Sim","Não") -> Não | P12: =IF(I12>K12,"Sim","Não") -> Sim | Q12: =COUNTIFS(C:C,C12) -> 1
C13: 1045085918 | D13: Droga Clara | E13: =_xlfn.XLOOKUP(C13,'Same Seller Hist'!E:E,'Same Seller Hist'!I:I) -> 7.4941815e+18 | F13: =_xlfn.XLOOKUP(C13,'Same Seller Hist'!E:E,'Same Seller Hist'!H:H) -> YUMI CELL BR | G13: FMCG | H13: 4299.4839 | I13: 22995.675 | J13: =_xlfn.IFNA(_xlfn.XLOOKUP(F13,'Fastmoss 500'!D:D,'Fastmoss 500'!O:O),0) -> 235.48387 | K13: =_xlfn.IFNA(_xlfn.XLOOKUP(F13,'Fastmoss 500'!D:D,'Fastmoss 500'!N:N),0) -> 17706.452 | L13: Shp 500 | M13: =IF(L13="Shp 500","Sim",IF(ISNA(_xlfn.XLOOKUP(C13,'Shp 500'!D:D,'Shp 500'!D:D)),"Não","Sim")) -> Sim | N13: =IF(L13="Fastmoss 500","Sim",IF(ISNA(_xlfn.XLOOKUP(_xlfn.XLOOKUP(C13,'Same Seller Hist'!E:E,'Same Seller Hist'!H:H),'Fastmoss 500'!D:D,'Fastmoss 500'!D:D)),"Não","Sim")) -> Sim | O13: =IF(AND(M13="Sim",N13="Sim"),"Sim","Não") -> Sim | P13: =IF(I13>K13,"Sim","Não") -> Sim | Q13: =COUNTIFS(C:C,C13) -> 1
C14: 296363855 | D14: CasaLauraEnxovais | E14: =_xlfn.XLOOKUP(C14,'Same Seller Hist'!E:E,'Same Seller Hist'!I:I) -> 7.4955619e+18 | F14: =_xlfn.XLOOKUP(C14,'Same Seller Hist'!E:E,'Same Seller Hist'!H:H) -> Casa Laura Enxovais | G14: Lifestyle | H14: 1873.9355 | I14: 15155.613 | J14: =_xlfn.IFNA(_xlfn.XLOOKUP(F14,'Fastmoss 500'!D:D,'Fastmoss 500'!O:O),0) -> 280.64516 | K14: =_xlfn.IFNA(_xlfn.XLOOKUP(F14,'Fastmoss 500'!D:D,'Fastmoss 500'!N:N),0) -> 16445.161 | L14: Shp 500 | M14: =IF(L14="Shp 500","Sim",IF(ISNA(_xlfn.XLOOKUP(C14,'Shp 500'!D:D,'Shp 500'!D:D)),"Não","Sim")) -> Sim | N14: =IF(L14="Fastmoss 500","Sim",IF(ISNA(_xlfn.XLOOKUP(_xlfn.XLOOKUP(C14,'Same Seller Hist'!E:E,'Same Seller Hist'!H:H),'Fastmoss 500'!D:D,'Fastmoss 500'!D:D)),"Não","Sim")) -> Sim | O14: =IF(AND(M14="Sim",N14="Sim"),"Sim","Não") -> Sim | P14: =IF(I14>K14,"Sim","Não") -> Não | Q14: =COUNTIFS(C:C,C14) -> 2
C15: =_xlfn.XLOOKUP(F15,'Same Seller Hist'!H:H,'Same Seller Hist'!E:E) -> 296363855 | D15: =_xlfn.XLOOKUP(F15,'Same Seller Hist'!H:H,'Same Seller Hist'!D:D) -> Casa Laura Enxovais | E15: =_xlfn.XLOOKUP(F15,'Same Seller Hist'!H:H,'Same Seller Hist'!I:I) -> 7.4955619e+18 | F15: Casa Laura Enxovais | G15: =_xlfn.XLOOKUP(C15,'Same Seller Hist'!E:E,'Same Seller Hist'!F:F) -> Lifestyle | H15: =_xlfn.IFNA(_xlfn.XLOOKUP(C15,'Shp 500'!D:D,'Shp 500'!I:I),0) -> 1873.9355 | I15: =_xlfn.IFNA(_xlfn.XLOOKUP(C15,'Shp 500'!D:D,'Shp 500'!J:J),0) -> 15155.613 | J15: 280.64516 | K15: 16445.161 | L15: Fastmoss 500 | M15: =IF(L15="Shp 500","Sim",IF(ISNA(_xlfn.XLOOKUP(C15,'Shp 500'!D:D,'Shp 500'!D:D)),"Não","Sim")) -> Sim | N15: =IF(L15="Fastmoss 500","Sim",IF(ISNA(_xlfn.XLOOKUP(_xlfn.XLOOKUP(C15,'Same Seller Hist'!E:E,'Same Seller Hist'!H:H),'Fastmoss 500'!D:D,'Fastmoss 500'!D:D)),"Não","Sim")) -> Sim | O15: =IF(AND(M15="Sim",N15="Sim"),"Sim","Não") -> Sim | P15: =IF(I15>K15,"Sim","Não") -> Não | Q15: =COUNTIFS(C:C,C15) -> 2
C16: 872424585 | D16: Mega TechStore | E16: =_xlfn.XLOOKUP(C16,'Same Seller Hist'!E:E,'Same Seller Hist'!I:I) -> 7.4961817e+18 | F16: =_xlfn.XLOOKUP(C16,'Same Seller Hist'!E:E,'Same Seller Hist'!H:H) -> mega tech store | G16: CN | H16: 3866.0645 | I16: 31272.972 | J16: =_xlfn.IFNA(_xlfn.XLOOKUP(F16,'Fastmoss 500'!D:D,'Fastmoss 500'!O:O),0) -> 0 | K16: =_xlfn.IFNA(_xlfn.XLOOKUP(F16,'Fastmoss 500'!D:D,'Fastmoss 500'!N:N),0) -> 0 | L16: Shp 500 | M16: =IF(L16="Shp 500","Sim",IF(ISNA(_xlfn.XLOOKUP(C16,'Shp 500'!D:D,'Shp 500'!D:D)),"Não","Sim")) -> Sim | N16: =IF(L16="Fastmoss 500","Sim",IF(ISNA(_xlfn.XLOOKUP(_xlfn.XLOOKUP(C16,'Same Seller Hist'!E:E,'Same Seller Hist'!H:H),'Fastmoss 500'!D:D,'Fastmoss 500'!D:D)),"Não","Sim")) -> Não | O16: =IF(AND(M16="Sim",N16="Sim"),"Sim","Não") -> Não | P16: =IF(I16>K16,"Sim","Não") -> Sim | Q16: =COUNTIFS(C:C,C16) -> 1
C17: 643719371 | D17: NEWCOOL | E17: =_xlfn.XLOOKUP(C17,'Same Seller Hist'!E:E,'Same Seller Hist'!I:I) -> 7.496184e+18 | F17: =_xlfn.XLOOKUP(C17,'Same Seller Hist'!E:E,'Same Seller Hist'!H:H) -> NEWCOOL.BR | G17: CN | H17: 3826.9355 | I17: 19013.021 | J17: =_xlfn.IFNA(_xlfn.XLOOKUP(F17,'Fastmoss 500'!D:D,'Fastmoss 500'!O:O),0) -> 0 | K17: =_xlfn.IFNA(_xlfn.XLOOKUP(F17,'Fastmoss 500'!D:D,'Fastmoss 500'!N:N),0) -> 0 | L17: Shp 500 | M17: =IF(L17="Shp 500","Sim",IF(ISNA(_xlfn.XLOOKUP(C17,'Shp 500'!D:D,'Shp 500'!D:D)),"Não","Sim")) -> Sim | N17: =IF(L17="Fastmoss 500","Sim",IF(ISNA(_xlfn.XLOOKUP(_xlfn.XLOOKUP(C17,'Same Seller Hist'!E:E,'Same Seller Hist'!H:H),'Fastmoss 500'!D:D,'Fastmoss 500'!D:D)),"Não","Sim")) -> Não | O17: =IF(AND(M17="Sim",N17="Sim"),"Sim","Não") -> Não | P17: =IF(I17>K17,"Sim","Não") -> Sim | Q17: =COUNTIFS(C:C,C17) -> 1
C18: 299222557 | D18: RIven Bazar | E18: =_xlfn.XLOOKUP(C18,'Same Seller Hist'!E:E,'Same Seller Hist'!I:I) -> 7.4961792e+18 | F18: =_xlfn.XLOOKUP(C18,'Same Seller Hist'!E:E,'Same Seller Hist'!H:H) -> RIVEN BAZAR | G18: CN | H18: 2540.1613 | I18: 9178.8417 | J18: =_xlfn.IFNA(_xlfn.XLOOKUP(F18,'Fastmoss 500'!D:D,'Fastmoss 500'!O:O),0) -> 251.6129 | K18: =_xlfn.IFNA(_xlfn.XLOOKUP(F18,'Fastmoss 500'!D:D,'Fastmoss 500'!N:N),0) -> 10303.226 | L18: Shp 500 | M18: =IF(L18="Shp 500","Sim",IF(ISNA(_xlfn.XLOOKUP(C18,'Shp 500'!D:D,'Shp 500'!D:D)),"Não","Sim")) -> Sim | N18: =IF(L18="Fastmoss 500","Sim",IF(ISNA(_xlfn.XLOOKUP(_xlfn.XLOOKUP(C18,'Same Seller Hist'!E:E,'Same Seller Hist'!H:H),'Fastmoss 500'!D:D,'Fastmoss 500'!D:D)),"Não","Sim")) -> Sim | O18: =IF(AND(M18="Sim",N18="Sim"),"Sim","Não") -> Sim | P18: =IF(I18>K18,"Sim","Não") -> Não | Q18: =COUNTIFS(C:C,C18) -> 2
C19: 1064041485 | D19: LuxeElectra | E19: =_xlfn.XLOOKUP(C19,'Same Seller Hist'!E:E,'Same Seller Hist'!I:I) -> 7.4961859e+18 | F19: =_xlfn.XLOOKUP(C19,'Same Seller Hist'!E:E,'Same Seller Hist'!H:H) -> luxeelectra | G19: CN | H19: 3451.0968 | I19: 33941.769 | J19: =_xlfn.IFNA(_xlfn.XLOOKUP(F19,'Fastmoss 500'!D:D,'Fastmoss 500'!O:O),0) -> 0 | K19: =_xlfn.IFNA(_xlfn.XLOOKUP(F19,'Fastmoss 500'!D:D,'Fastmoss 500'!N:N),0) -> 0 | L19: Shp 500 | M19: =IF(L19="Shp 500","Sim",IF(ISNA(_xlfn.XLOOKUP(C19,'Shp 500'!D:D,'Shp 500'!D:D)),"Não","Sim")) -> Sim | N19: =IF(L19="Fastmoss 500","Sim",IF(ISNA(_xlfn.XLOOKUP(_xlfn.XLOOKUP(C19,'Same Seller Hist'!E:E,'Same Seller Hist'!H:H),'Fastmoss 500'!D:D,'Fastmoss 500'!D:D)),"Não","Sim")) -> Não | O19: =IF(AND(M19="Sim",N19="Sim"),"Sim","Não") -> Não | P19: =IF(I19>K19,"Sim","Não") -> Sim | Q19: =COUNTIFS(C:C,C19) -> 1
C20: 341167297 | D20: Poloinfantil.store | E20: =_xlfn.XLOOKUP(C20,'Same Seller Hist'!E:E,'Same Seller Hist'!I:I) -> 0 | F20: =_xlfn.XLOOKUP(C20,'Same Seller Hist'!E:E,'Same Seller Hist'!H:H) -> 0 | G20: Fashion | H20: 3346.871 | I20: 37236.535 | J20: =_xlfn.IFNA(_xlfn.XLOOKUP(F20,'Fastmoss 500'!D:D,'Fastmoss 500'!O:O),0) -> 0 | K20: =_xlfn.IFNA(_xlfn.XLOOKUP(F20,'Fastmoss 500'!D:D,'Fastmoss 500'!N:N),0) -> 0 | L20: Shp 500 | M20: =IF(L20="Shp 500","Sim",IF(ISNA(_xlfn.XLOOKUP(C20,'Shp 500'!D:D,'Shp 500'!D:D)),"Não","Sim")) -> Sim | N20: =IF(L20="Fastmoss 500","Sim",IF(ISNA(_xlfn.XLOOKUP(_xlfn.XLOOKUP(C20,'Same Seller Hist'!E:E,'Same Seller Hist'!H:H),'Fastmoss 500'!D:D,'Fastmoss 500'!D:D)),"Não","Sim")) -> Não | O20: =IF(AND(M20="Sim",N20="Sim"),"Sim","Não") -> Não | P20: =IF(I20>K20,"Sim","Não") -> Sim | Q20: =COUNTIFS(C:C,C20) -> 1
C21: 313660590 | D21: Nosso Lar Enxovais | E21: =_xlfn.XLOOKUP(C21,'Same Seller Hist'!E:E,'Same Seller Hist'!I:I) -> 7.4940983e+18 | F21: =_xlfn.XLOOKUP(C21,'Same Seller Hist'!E:E,'Same Seller Hist'!H:H) -> Nosso Lar Enxovais | G21: Lifestyle | H21: 3313.3226 | I21: 29155.732 | J21: =_xlfn.IFNA(_xlfn.XLOOKUP(F21,'Fastmoss 500'!D:D,'Fastmoss 500'!O:O),0) -> 0 | K21: =_xlfn.IFNA(_xlfn.XLOOKUP(F21,'Fastmoss 500'!D:D,'Fastmoss 500'!N:N),0) -> 0 | L21: Shp 500 | M21: =IF(L21="Shp 500","Sim",IF(ISNA(_xlfn.XLOOKUP(C21,'Shp 500'!D:D,'Shp 500'!D:D)),"Não","Sim")) -> Sim | N21: =IF(L21="Fastmoss 500","Sim",IF(ISNA(_xlfn.XLOOKUP(_xlfn.XLOOKUP(C21,'Same Seller Hist'!E:E,'Same Seller Hist'!H:H),'Fastmoss 500'!D:D,'Fastmoss 500'!D:D)),"Não","Sim")) -> Não | O21: =IF(AND(M21="Sim",N21="Sim"),"Sim","Não") -> Não | P21: =IF(I21>K21,"Sim","Não") -> Sim | Q21: =COUNTIFS(C:C,C21) -> 1
C22: =_xlfn.XLOOKUP(F22,'Same Seller Hist'!H:H,'Same Seller Hist'!E:E) -> 299222557 | D22: =_xlfn.XLOOKUP(F22,'Same Seller Hist'!H:H,'Same Seller Hist'!D:D) -> RIVEN BAZAR | E22: =_xlfn.XLOOKUP(F22,'Same Seller Hist'!H:H,'Same Seller Hist'!I:I) -> 7.4961792e+18 | F22: RIVEN BAZAR | G22: =_xlfn.XLOOKUP(C22,'Same Seller Hist'!E:E,'Same Seller Hist'!F:F) -> FMCG | H22: =_xlfn.IFNA(_xlfn.XLOOKUP(C22,'Shp 500'!D:D,'Shp 500'!I:I),0) -> 2540.1613 | I22: =_xlfn.IFNA(_xlfn.XLOOKUP(C22,'Shp 500'!D:D,'Shp 500'!J:J),0) -> 9178.8417 | J22: 251.6129 | K22: 10303.226 | L22: Fastmoss 500 | M22: =IF(L22="Shp 500","Sim",IF(ISNA(_xlfn.XLOOKUP(C22,'Shp 500'!D:D,'Shp 500'!D:D)),"Não","Sim")) -> Sim | N22: =IF(L22="Fastmoss 500","Sim",IF(ISNA(_xlfn.XLOOKUP(_xlfn.XLOOKUP(C22,'Same Seller Hist'!E:E,'Same Seller Hist'!H:H),'Fastmoss 500'!D:D,'Fastmoss 500'!D:D)),"Não","Sim")) -> Sim | O22: =IF(AND(M22="Sim",N22="Sim"),"Sim","Não") -> Sim | P22: =IF(I22>K22,"Sim","Não") -> Não | Q22: =COUNTIFS(C:C,C22) -> 2
C23: 313984108 | D23: CASA NOVA ENXOVAIS E DECORAÇÃO | E23: =_xlfn.XLOOKUP(C23,'Same Seller Hist'!E:E,'Same Seller Hist'!I:I) -> 7.4940883e+18 | F23: =_xlfn.XLOOKUP(C23,'Same Seller Hist'!E:E,'Same Seller Hist'!H:H) -> Casa Nova Enxovais e Decoração | G23: Lifestyle | H23: 2282.8387 | I23: 18438.426 | J23: =_xlfn.IFNA(_xlfn.XLOOKUP(F23,'Fastmoss 500'!D:D,'Fastmoss 500'!O:O),0) -> 383.87097 | K23: =_xlfn.IFNA(_xlfn.XLOOKUP(F23,'Fastmoss 500'!D:D,'Fastmoss 500'!N:N),0) -> 9980.6452 | L23: Shp 500 | M23: =IF(L23="Shp 500","Sim",IF(ISNA(_xlfn.XLOOKUP(C23,'Shp 500'!D:D,'Shp 500'!D:D)),"Não","Sim")) -> Sim | N23: =IF(L23="Fastmoss 500","Sim",IF(ISNA(_xlfn.XLOOKUP(_xlfn.XLOOKUP(C23,'Same Seller Hist'!E:E,'Same Seller Hist'!H:H),'Fastmoss 500'!D:D,'Fastmoss 500'!D:D)),"Não","Sim")) -> Sim | O23: =IF(AND(M23="Sim",N23="Sim"),"Sim","Não") -> Sim | P23: =IF(I23>K23,"Sim","Não") -> Sim | Q23: =COUNTIFS(C:C,C23) -> 2
C24: =_xlfn.XLOOKUP(F24,'Same Seller Hist'!H:H,'Same Seller Hist'!E:E) -> 313984108 | D24: =_xlfn.XLOOKUP(F24,'Same Seller Hist'!H:H,'Same Seller Hist'!D:D) -> Casa Nova Enxovais e Decoração | E24: =_xlfn.XLOOKUP(F24,'Same Seller Hist'!H:H,'Same Seller Hist'!I:I) -> 7.4940883e+18 | F24: Casa Nova Enxovais e Decoração | G24: =_xlfn.XLOOKUP(C24,'Same Seller Hist'!E:E,'Same Seller Hist'!F:F) -> Lifestyle | H24: =_xlfn.IFNA(_xlfn.XLOOKUP(C24,'Shp 500'!D:D,'Shp 500'!I:I),0) -> 2282.8387 | I24: =_xlfn.IFNA(_xlfn.XLOOKUP(C24,'Shp 500'!D:D,'Shp 500'!J:J),0) -> 18438.426 | J24: 383.87097 | K24: 9980.6452 | L24: Fastmoss 500 | M24: =IF(L24="Shp 500","Sim",IF(ISNA(_xlfn.XLOOKUP(C24,'Shp 500'!D:D,'Shp 500'!D:D)),"Não","Sim")) -> Sim | N24: =IF(L24="Fastmoss 500","Sim",IF(ISNA(_xlfn.XLOOKUP(_xlfn.XLOOKUP(C24,'Same Seller Hist'!E:E,'Same Seller Hist'!H:H),'Fastmoss 500'!D:D,'Fastmoss 500'!D:D)),"Não","Sim")) -> Sim | O24: =IF(AND(M24="Sim",N24="Sim"),"Sim","Não") -> Sim | P24: =IF(I24>K24,"Sim","Não") -> Sim | Q24: =COUNTIFS(C:C,C24) -> 2
C25: 343246764 | D25: Zyoou Market | E25: =_xlfn.XLOOKUP(C25,'Same Seller Hist'!E:E,'Same Seller Hist'!I:I) -> 7.4961625e+18 | F25: =_xlfn.XLOOKUP(C25,'Same Seller Hist'!E:E,'Same Seller Hist'!H:H) -> Zyoou Market | G25: CN | H25: 3018.7419 | I25: 12152.887 | J25: =_xlfn.IFNA(_xlfn.XLOOKUP(F25,'Fastmoss 500'!D:D,'Fastmoss 500'!O:O),0) -> 0 | K25: =_xlfn.IFNA(_xlfn.XLOOKUP(F25,'Fastmoss 500'!D:D,'Fastmoss 500'!N:N),0) -> 0 | L25: Shp 500 | M25: =IF(L25="Shp 500","Sim",IF(ISNA(_xlfn.XLOOKUP(C25,'Shp 500'!D:D,'Shp 500'!D:D)),"Não","Sim")) -> Sim | N25: =IF(L25="Fastmoss 500","Sim",IF(ISNA(_xlfn.XLOOKUP(_xlfn.XLOOKUP(C25,'Same Seller Hist'!E:E,'Same Seller Hist'!H:H),'Fastmoss 500'!D:D,'Fastmoss 500'!D:D)),"Não","Sim")) -> Não | O25: =IF(AND(M25="Sim",N25="Sim"),"Sim","Não") -> Não | P25: =IF(I25>K25,"Sim","Não") -> Sim | Q25: =COUNTIFS(C:C,C25) -> 1
C26: 418205294 | D26: ANA 1108 | E26: =_xlfn.XLOOKUP(C26,'Same Seller Hist'!E:E,'Same Seller Hist'!I:I) -> 7.4961473e+18 | F26: =_xlfn.XLOOKUP(C26,'Same Seller Hist'!E:E,'Same Seller Hist'!H:H) -> ANA1108 SHOP | G26: CN | H26: 3015.129 | I26: 11080.647 | J26: =_xlfn.IFNA(_xlfn.XLOOKUP(F26,'Fastmoss 500'!D:D,'Fastmoss 500'!O:O),0) -> 0 | K26: =_xlfn.IFNA(_xlfn.XLOOKUP(F26,'Fastmoss 500'!D:D,'Fastmoss 500'!N:N),0) -> 0 | L26: Shp 500 | M26: =IF(L26="Shp 500","Sim",IF(ISNA(_xlfn.XLOOKUP(C26,'Shp 500'!D:D,'Shp 500'!D:D)),"Não","Sim")) -> Sim | N26: =IF(L26="Fastmoss 500","Sim",IF(ISNA(_xlfn.XLOOKUP(_xlfn.XLOOKUP(C26,'Same Seller Hist'!E:E,'Same Seller Hist'!H:H),'Fastmoss 500'!D:D,'Fastmoss 500'!D:D)),"Não","Sim")) -> Não | O26: =IF(AND(M26="Sim",N26="Sim"),"Sim","Não") -> Não | P26: =IF(I26>K26,"Sim","Não") -> Sim | Q26: =COUNTIFS(C:C,C26) -> 1
C27: 300779622 | D27: Icasa Ibitinga | E27: =_xlfn.XLOOKUP(C27,'Same Seller Hist'!E:E,'Same Seller Hist'!I:I) -> 7.4962023e+18 | F27: =_xlfn.XLOOKUP(C27,'Same Seller Hist'!E:E,'Same Seller Hist'!H:H) -> Icasa Ibitinga | G27: Lifestyle | H27: 2956.2903 | I27: 25985.607 | J27: =_xlfn.IFNA(_xlfn.XLOOKUP(F27,'Fastmoss 500'!D:D,'Fastmoss 500'!O:O),0) -> 0 | K27: =_xlfn.IFNA(_xlfn.XLOOKUP(F27,'Fastmoss 500'!D:D,'Fastmoss 500'!N:N),0) -> 0 | L27: Shp 500 | M27: =IF(L27="Shp 500","Sim",IF(ISNA(_xlfn.XLOOKUP(C27,'Shp 500'!D:D,'Shp 500'!D:D)),"Não","Sim")) -> Sim | N27: =IF(L27="Fastmoss 500","Sim",IF(ISNA(_xlfn.XLOOKUP(_xlfn.XLOOKUP(C27,'Same Seller Hist'!E:E,'Same Seller Hist'!H:H),'Fastmoss 500'!D:D,'Fastmoss 500'!D:D)),"Não","Sim")) -> Não | O27: =IF(AND(M27="Sim",N27="Sim"),"Sim","Não") -> Não | P27: =IF(I27>K27,"Sim","Não") -> Sim | Q27: =COUNTIFS(C:C,C27) -> 1
C28: 394731864 | D28: EvaMia | E28: =_xlfn.XLOOKUP(C28,'Same Seller Hist'!E:E,'Same Seller Hist'!I:I) -> 7.4961625e+18 | F28: =_xlfn.XLOOKUP(C28,'Same Seller Hist'!E:E,'Same Seller Hist'!H:H) -> Evamia 21 | G28: CN | H28: 2890.5484 | I28: 11832.645 | J28: =_xlfn.IFNA(_xlfn.XLOOKUP(F28,'Fastmoss 500'!D:D,'Fastmoss 500'!O:O),0) -> 0 | K28: =_xlfn.IFNA(_xlfn.XLOOKUP(F28,'Fastmoss 500'!D:D,'Fastmoss 500'!N:N),0) -> 0 | L28: Shp 500 | M28: =IF(L28="Shp 500","Sim",IF(ISNA(_xlfn.XLOOKUP(C28,'Shp 500'!D:D,'Shp 500'!D:D)),"Não","Sim")) -> Sim | N28: =IF(L28="Fastmoss 500","Sim",IF(ISNA(_xlfn.XLOOKUP(_xlfn.XLOOKUP(C28,'Same Seller Hist'!E:E,'Same Seller Hist'!H:H),'Fastmoss 500'!D:D,'Fastmoss 500'!D:D)),"Não","Sim")) -> Não | O28: =IF(AND(M28="Sim",N28="Sim"),"Sim","Não") -> Não | P28: =IF(I28>K28,"Sim","Não") -> Sim | Q28: =COUNTIFS(C:C,C28) -> 1
C29: 325008325 | D29: Na Web Group De Marcas | E29: =_xlfn.XLOOKUP(C29,'Same Seller Hist'!E:E,'Same Seller Hist'!I:I) -> 0 | F29: =_xlfn.XLOOKUP(C29,'Same Seller Hist'!E:E,'Same Seller Hist'!H:H) -> 0 | G29: Lifestyle | H29: 1795.6129 | I29: 32107.84 | J29: =_xlfn.IFNA(_xlfn.XLOOKUP(F29,'Fastmoss 500'!D:D,'Fastmoss 500'!O:O),0) -> 0 | K29: =_xlfn.IFNA(_xlfn.XLOOKUP(F29,'Fastmoss 500'!D:D,'Fastmoss 500'!N:N),0) -> 0 | L29: Shp 500 | M29: =IF(L29="Shp 500","Sim",IF(ISNA(_xlfn.XLOOKUP(C29,'Shp 500'!D:D,'Shp 500'!D:D)),"Não","Sim")) -> Sim | N29: =IF(L29="Fastmoss 500","Sim",IF(ISNA(_xlfn.XLOOKUP(_xlfn.XLOOKUP(C29,'Same Seller Hist'!E:E,'Same Seller Hist'!H:H),'Fastmoss 500'!D:D,'Fastmoss 500'!D:D)),"Não","Sim")) -> Não | O29: =IF(AND(M29="Sim",N29="Sim"),"Sim","Não") -> Não | P29: =IF(I29>K29,"Sim","Não") -> Sim | Q29: =COUNTIFS(C:C,C29) -> 2
C30: 378105312 | D30: EssencialBaby | E30: =_xlfn.XLOOKUP(C30,'Same Seller Hist'!E:E,'Same Seller Hist'!I:I) -> 7.496183e+18 | F30: =_xlfn.XLOOKUP(C30,'Same Seller Hist'!E:E,'Same Seller Hist'!H:H) -> Essencial Baby | G30: FMCG | H30: 2847.1935 | I30: 14097.538 | J30: =_xlfn.IFNA(_xlfn.XLOOKUP(F30,'Fastmoss 500'!D:D,'Fastmoss 500'!O:O),0) -> 0 | K30: =_xlfn.IFNA(_xlfn.XLOOKUP(F30,'Fastmoss 500'!D:D,'Fastmoss 500'!N:N),0) -> 0 | L30: Shp 500 | M30: =IF(L30="Shp 500","Sim",IF(ISNA(_xlfn.XLOOKUP(C30,'Shp 500'!D:D,'Shp 500'!D:D)),"Não","Sim")) -> Sim | N30: =IF(L30="Fastmoss 500","Sim",IF(ISNA(_xlfn.XLOOKUP(_xlfn.XLOOKUP(C30,'Same Seller Hist'!E:E,'Same Seller Hist'!H:H),'Fastmoss 500'!D:D,'Fastmoss 500'!D:D)),"Não","Sim")) -> Não | O30: =IF(AND(M30="Sim",N30="Sim"),"Sim","Não") -> Não | P30: =IF(I30>K30,"Sim","Não") -> Sim | Q30: =COUNTIFS(C:C,C30) -> 1
C31: =_xlfn.XLOOKUP(F31,'Same Seller Hist'!H:H,'Same Seller Hist'!E:E) -> 325008325 | D31: =_xlfn.XLOOKUP(F31,'Same Seller Hist'!H:H,'Same Seller Hist'!D:D) -> Na Web | E31: =_xlfn.XLOOKUP(F31,'Same Seller Hist'!H:H,'Same Seller Hist'!I:I) -> 7.4961601e+18 | F31: Na Web | G31: =_xlfn.XLOOKUP(C31,'Same Seller Hist'!E:E,'Same Seller Hist'!F:F) -> Lifestyle | H31: =_xlfn.IFNA(_xlfn.XLOOKUP(C31,'Shp 500'!D:D,'Shp 500'!I:I),0) -> 1795.6129 | I31: =_xlfn.IFNA(_xlfn.XLOOKUP(C31,'Shp 500'!D:D,'Shp 500'!J:J),0) -> 32107.84 | J31: 587.09677 | K31: 54838.71 | L31: Fastmoss 500 | M31: =IF(L31="Shp 500","Sim",IF(ISNA(_xlfn.XLOOKUP(C31,'Shp 500'!D:D,'Shp 500'!D:D)),"Não","Sim")) -> Sim | N31: =IF(L31="Fastmoss 500","Sim",IF(ISNA(_xlfn.XLOOKUP(_xlfn.XLOOKUP(C31,'Same Seller Hist'!E:E,'Same Seller Hist'!H:H),'Fastmoss 500'!D:D,'Fastmoss 500'!D:D)),"Não","Sim")) -> Sim | O31: =IF(AND(M31="Sim",N31="Sim"),"Sim","Não") -> Sim | P31: =IF(I31>K31,"Sim","Não") -> Não | Q31: =COUNTIFS(C:C,C31) -> 2
C32: 328666563 | D32: DAFUSHOP_brasil | E32: =_xlfn.XLOOKUP(C32,'Same Seller Hist'!E:E,'Same Seller Hist'!I:I) -> 7.4961464e+18 | F32: =_xlfn.XLOOKUP(C32,'Same Seller Hist'!E:E,'Same Seller Hist'!H:H) -> DAFUSHOP BRASIL | G32: CN | H32: 2853.6774 | I32: 20794.012 | J32: =_xlfn.IFNA(_xlfn.XLOOKUP(F32,'Fastmoss 500'!D:D,'Fastmoss 500'!O:O),0) -> 2251.6129 | K32: =_xlfn.IFNA(_xlfn.XLOOKUP(F32,'Fastmoss 500'!D:D,'Fastmoss 500'!N:N),0) -> 138709.68 | L32: Shp 500 | M32: =IF(L32="Shp 500","Sim",IF(ISNA(_xlfn.XLOOKUP(C32,'Shp 500'!D:D,'Shp 500'!D:D)),"Não","Sim")) -> Sim | N32: =IF(L32="Fastmoss 500","Sim",IF(ISNA(_xlfn.XLOOKUP(_xlfn.XLOOKUP(C32,'Same Seller Hist'!E:E,'Same Seller Hist'!H:H),'Fastmoss 500'!D:D,'Fastmoss 500'!D:D)),"Não","Sim")) -> Sim | O32: =IF(AND(M32="Sim",N32="Sim"),"Sim","Não") -> Sim | P32: =IF(I32>K32,"Sim","Não") -> Não | Q32: =COUNTIFS(C:C,C32) -> 2
C33: 375201738 | D33: LUCKY BAZAR | E33: =_xlfn.XLOOKUP(C33,'Same Seller Hist'!E:E,'Same Seller Hist'!I:I) -> 7.4961623e+18 | F33: =_xlfn.XLOOKUP(C33,'Same Seller Hist'!E:E,'Same Seller Hist'!H:H) -> Lucky Bazar | G33: CN | H33: 2655.1613 | I33: 11185.769 | J33: =_xlfn.IFNA(_xlfn.XLOOKUP(F33,'Fastmoss 500'!D:D,'Fastmoss 500'!O:O),0) -> 0 | K33: =_xlfn.IFNA(_xlfn.XLOOKUP(F33,'Fastmoss 500'!D:D,'Fastmoss 500'!N:N),0) -> 0 | L33: Shp 500 | M33: =IF(L33="Shp 500","Sim",IF(ISNA(_xlfn.XLOOKUP(C33,'Shp 500'!D:D,'Shp 500'!D:D)),"Não","Sim")) -> Sim | N33: =IF(L33="Fastmoss 500","Sim",IF(ISNA(_xlfn.XLOOKUP(_xlfn.XLOOKUP(C33,'Same Seller Hist'!E:E,'Same Seller Hist'!H:H),'Fastmoss 500'!D:D,'Fastmoss 500'!D:D)),"Não","Sim")) -> Não | O33: =IF(AND(M33="Sim",N33="Sim"),"Sim","Não") -> Não | P33: =IF(I33>K33,"Sim","Não") -> Sim | Q33: =COUNTIFS(C:C,C33) -> 1
C34: =_xlfn.XLOOKUP(F34,'Same Seller Hist'!H:H,'Same Seller Hist'!E:E) -> 328666563 | D34: =_xlfn.XLOOKUP(F34,'Same Seller Hist'!H:H,'Same Seller Hist'!D:D) -> DAFUSHOP BRASIL | E34: =_xlfn.XLOOKUP(F34,'Same Seller Hist'!H:H,'Same Seller Hist'!I:I) -> 7.4961464e+18 | F34: DAFUSHOP BRASIL | G34: =_xlfn.XLOOKUP(C34,'Same Seller Hist'!E:E,'Same Seller Hist'!F:F) -> ELHA | H34: =_xlfn.IFNA(_xlfn.XLOOKUP(C34,'Shp 500'!D:D,'Shp 500'!I:I),0) -> 2853.6774 | I34: =_xlfn.IFNA(_xlfn.XLOOKUP(C34,'Shp 500'!D:D,'Shp 500'!J:J),0) -> 20794.012 | J34: 2251.6129 | K34: 138709.68 | L34: Fastmoss 500 | M34: =IF(L34="Shp 500","Sim",IF(ISNA(_xlfn.XLOOKUP(C34,'Shp 500'!D:D,'Shp 500'!D:D)),"Não","Sim")) -> Sim | N34: =IF(L34="Fastmoss 500","Sim",IF(ISNA(_xlfn.XLOOKUP(_xlfn.XLOOKUP(C34,'Same Seller Hist'!E:E,'Same Seller Hist'!H:H),'Fastmoss 500'!D:D,'Fastmoss 500'!D:D)),"Não","Sim")) -> Sim | O34: =IF(AND(M34="Sim",N34="Sim"),"Sim","Não") -> Sim | P34: =IF(I34>K34,"Sim","Não") -> Não | Q34: =COUNTIFS(C:C,C34) -> 2
C35: 290073877 | D35: mypetone | E35: =_xlfn.XLOOKUP(C35,'Same Seller Hist'!E:E,'Same Seller Hist'!I:I) -> 7.4963023e+18 | F35: =_xlfn.XLOOKUP(C35,'Same Seller Hist'!E:E,'Same Seller Hist'!H:H) -> mypetonebr | G35: FMCG | H35: 2629.9677 | I35: 19695.027 | J35: =_xlfn.IFNA(_xlfn.XLOOKUP(F35,'Fastmoss 500'!D:D,'Fastmoss 500'!O:O),0) -> 0 | K35: =_xlfn.IFNA(_xlfn.XLOOKUP(F35,'Fastmoss 500'!D:D,'Fastmoss 500'!N:N),0) -> 0 | L35: Shp 500 | M35: =IF(L35="Shp 500","Sim",IF(ISNA(_xlfn.XLOOKUP(C35,'Shp 500'!D:D,'Shp 500'!D:D)),"Não","Sim")) -> Sim | N35: =IF(L35="Fastmoss 500","Sim",IF(ISNA(_xlfn.XLOOKUP(_xlfn.XLOOKUP(C35,'Same Seller Hist'!E:E,'Same Seller Hist'!H:H),'Fastmoss 500'!D:D,'Fastmoss 500'!D:D)),"Não","Sim")) -> Não | O35: =IF(AND(M35="Sim",N35="Sim"),"Sim","Não") -> Não | P35: =IF(I35>K35,"Sim","Não") -> Sim | Q35: =COUNTIFS(C:C,C35) -> 1
C36: 347988064 | D36: Soldiers Nutrition | E36: =_xlfn.XLOOKUP(C36,'Same Seller Hist'!E:E,'Same Seller Hist'!I:I) -> 7.4961622e+18 | F36: =_xlfn.XLOOKUP(C36,'Same Seller Hist'!E:E,'Same Seller Hist'!H:H) -> Soldiers Nutrition | G36: Fashion | H36: 931.35484 | I36: 10885.508 | J36: =_xlfn.IFNA(_xlfn.XLOOKUP(F36,'Fastmoss 500'!D:D,'Fastmoss 500'!O:O),0) -> 732.25806 | K36: =_xlfn.IFNA(_xlfn.XLOOKUP(F36,'Fastmoss 500'!D:D,'Fastmoss 500'!N:N),0) -> 48387.097 | L36: Shp 500 | M36: =IF(L36="Shp 500","Sim",IF(ISNA(_xlfn.XLOOKUP(C36,'Shp 500'!D:D,'Shp 500'!D:D)),"Não","Sim")) -> Sim | N36: =IF(L36="Fastmoss 500","Sim",IF(ISNA(_xlfn.XLOOKUP(_xlfn.XLOOKUP(C36,'Same Seller Hist'!E:E,'Same Seller Hist'!H:H),'Fastmoss 500'!D:D,'Fastmoss 500'!D:D)),"Não","Sim")) -> Sim | O36: =IF(AND(M36="Sim",N36="Sim"),"Sim","Não") -> Sim | P36: =IF(I36>K36,"Sim","Não") -> Não | Q36: =COUNTIFS(C:C,C36) -> 2
C37: =_xlfn.XLOOKUP(F37,'Same Seller Hist'!H:H,'Same Seller Hist'!E:E) -> 347988064 | D37: =_xlfn.XLOOKUP(F37,'Same Seller Hist'!H:H,'Same Seller Hist'!D:D) -> Soldiers Nutrition | E37: =_xlfn.XLOOKUP(F37,'Same Seller Hist'!H:H,'Same Seller Hist'!I:I) -> 7.4961622e+18 | F37: Soldiers Nutrition | G37: =_xlfn.XLOOKUP(C37,'Same Seller Hist'!E:E,'Same Seller Hist'!F:F) -> Fashion | H37: =_xlfn.IFNA(_xlfn.XLOOKUP(C37,'Shp 500'!D:D,'Shp 500'!I:I),0) -> 931.35484 | I37: =_xlfn.IFNA(_xlfn.XLOOKUP(C37,'Shp 500'!D:D,'Shp 500'!J:J),0) -> 10885.508 | J37: 732.25806 | K37: 48387.097 | L37: Fastmoss 500 | M37: =IF(L37="Shp 500","Sim",IF(ISNA(_xlfn.XLOOKUP(C37,'Shp 500'!D:D,'Shp 500'!D:D)),"Não","Sim")) -> Sim | N37: =IF(L37="Fastmoss 500","Sim",IF(ISNA(_xlfn.XLOOKUP(_xlfn.XLOOKUP(C37,'Same Seller Hist'!E:E,'Same Seller Hist'!H:H),'Fastmoss 500'!D:D,'Fastmoss 500'!D:D)),"Não","Sim")) -> Sim | O37: =IF(AND(M37="Sim",N37="Sim"),"Sim","Não") -> Sim | P37: =IF(I37>K37,"Sim","Não") -> Não | Q37: =COUNTIFS(C:C,C37) -> 2
C38: 1388709282 | D38: Belmicro Oficial | E38: =_xlfn.XLOOKUP(C38,'Same Seller Hist'!E:E,'Same Seller Hist'!I:I) -> 7.4962907e+18 | F38: =_xlfn.XLOOKUP(C38,'Same Seller Hist'!E:E,'Same Seller Hist'!H:H) -> Belmicro | G38: ELHA | H38: 2420.1935 | I38: 265042.32 | J38: =_xlfn.IFNA(_xlfn.XLOOKUP(F38,'Fastmoss 500'!D:D,'Fastmoss 500'!O:O),0) -> 0 | K38: =_xlfn.IFNA(_xlfn.XLOOKUP(F38,'Fastmoss 500'!D:D,'Fastmoss 500'!N:N),0) -> 0 | L38: Shp 500 | M38: =IF(L38="Shp 500","Sim",IF(ISNA(_xlfn.XLOOKUP(C38,'Shp 500'!D:D,'Shp 500'!D:D)),"Não","Sim")) -> Sim | N38: =IF(L38="Fastmoss 500","Sim",IF(ISNA(_xlfn.XLOOKUP(_xlfn.XLOOKUP(C38,'Same Seller Hist'!E:E,'Same Seller Hist'!H:H),'Fastmoss 500'!D:D,'Fastmoss 500'!D:D)),"Não","Sim")) -> Não | O38: =IF(AND(M38="Sim",N38="Sim"),"Sim","Não") -> Não | P38: =IF(I38>K38,"Sim","Não") -> Sim | Q38: =COUNTIFS(C:C,C38) -> 1
C39: 359168917 | D39: LOI BRASIL | E39: =_xlfn.XLOOKUP(C39,'Same Seller Hist'!E:E,'Same Seller Hist'!I:I) -> 7.4961604e+18 | F39: =_xlfn.XLOOKUP(C39,'Same Seller Hist'!E:E,'Same Seller Hist'!H:H) -> LOi Brasil | G39: ELHA | H39: 1513.9355 | I39: 44619.585 | J39: =_xlfn.IFNA(_xlfn.XLOOKUP(F39,'Fastmoss 500'!D:D,'Fastmoss 500'!O:O),0) -> 316.12903 | K39: =_xlfn.IFNA(_xlfn.XLOOKUP(F39,'Fastmoss 500'!D:D,'Fastmoss 500'!N:N),0) -> 45161.29 | L39: Shp 500 | M39: =IF(L39="Shp 500","Sim",IF(ISNA(_xlfn.XLOOKUP(C39,'Shp 500'!D:D,'Shp 500'!D:D)),"Não","Sim")) -> Sim | N39: =IF(L39="Fastmoss 500","Sim",IF(ISNA(_xlfn.XLOOKUP(_xlfn.XLOOKUP(C39,'Same Seller Hist'!E:E,'Same Seller Hist'!H:H),'Fastmoss 500'!D:D,'Fastmoss 500'!D:D)),"Não","Sim")) -> Sim | O39: =IF(AND(M39="Sim",N39="Sim"),"Sim","Não") -> Sim | P39: =IF(I39>K39,"Sim","Não") -> Não | Q39: =COUNTIFS(C:C,C39) -> 2
C40: 1360752092 | D40: XING TU BOLSA | E40: =_xlfn.XLOOKUP(C40,'Same Seller Hist'!E:E,'Same Seller Hist'!I:I) -> 0 | F40: =_xlfn.XLOOKUP(C40,'Same Seller Hist'!E:E,'Same Seller Hist'!H:H) -> 0 | G40: Lifestyle | H40: 2352.7742 | I40: 12036.157 | J40: =_xlfn.IFNA(_xlfn.XLOOKUP(F40,'Fastmoss 500'!D:D,'Fastmoss 500'!O:O),0) -> 0 | K40: =_xlfn.IFNA(_xlfn.XLOOKUP(F40,'Fastmoss 500'!D:D,'Fastmoss 500'!N:N),0) -> 0 | L40: Shp 500 | M40: =IF(L40="Shp 500","Sim",IF(ISNA(_xlfn.XLOOKUP(C40,'Shp 500'!D:D,'Shp 500'!D:D)),"Não","Sim")) -> Sim | N40: =IF(L40="Fastmoss 500","Sim",IF(ISNA(_xlfn.XLOOKUP(_xlfn.XLOOKUP(C40,'Same Seller Hist'!E:E,'Same Seller Hist'!H:H),'Fastmoss 500'!D:D,'Fastmoss 500'!D:D)),"Não","Sim")) -> Não | O40: =IF(AND(M40="Sim",N40="Sim"),"Sim","Não") -> Não | P40: =IF(I40>K40,"Sim","Não") -> Sim | Q40: =COUNTIFS(C:C,C40) -> 1
C41: =_xlfn.XLOOKUP(F41,'Same Seller Hist'!H:H,'Same Seller Hist'!E:E) -> 359168917 | D41: =_xlfn.XLOOKUP(F41,'Same Seller Hist'!H:H,'Same Seller Hist'!D:D) -> LOi Brasil | E41: =_xlfn.XLOOKUP(F41,'Same Seller Hist'!H:H,'Same Seller Hist'!I:I) -> 7.4961604e+18 | F41: LOi Brasil | G41: =_xlfn.XLOOKUP(C41,'Same Seller Hist'!E:E,'Same Seller Hist'!F:F) -> ELHA | H41: =_xlfn.IFNA(_xlfn.XLOOKUP(C41,'Shp 500'!D:D,'Shp 500'!I:I),0) -> 1513.9355 | I41: =_xlfn.IFNA(_xlfn.XLOOKUP(C41,'Shp 500'!D:D,'Shp 500'!J:J),0) -> 44619.585 | J41: 316.12903 | K41: 45161.29 | L41: Fastmoss 500 | M41: =IF(L41="Shp 500","Sim",IF(ISNA(_xlfn.XLOOKUP(C41,'Shp 500'!D:D,'Shp 500'!D:D)),"Não","Sim")) -> Sim | N41: =IF(L41="Fastmoss 500","Sim",IF(ISNA(_xlfn.XLOOKUP(_xlfn.XLOOKUP(C41,'Same Seller Hist'!E:E,'Same Seller Hist'!H:H),'Fastmoss 500'!D:D,'Fastmoss 500'!D:D)),"Não","Sim")) -> Sim | O41: =IF(AND(M41="Sim",N41="Sim"),"Sim","Não") -> Sim | P41: =IF(I41>K41,"Sim","Não") -> Não | Q41: =COUNTIFS(C:C,C41) -> 2
C42: 526615488 | D42: Sus.store | E42: =_xlfn.XLOOKUP(C42,'Same Seller Hist'!E:E,'Same Seller Hist'!I:I) -> 7.4962212e+18 | F42: =_xlfn.XLOOKUP(C42,'Same Seller Hist'!E:E,'Same Seller Hist'!H:H) -> Sus.store | G42: CN | H42: 2276.129 | I42: 16653.107 | J42: =_xlfn.IFNA(_xlfn.XLOOKUP(F42,'Fastmoss 500'!D:D,'Fastmoss 500'!O:O),0) -> 0 | K42: =_xlfn.IFNA(_xlfn.XLOOKUP(F42,'Fastmoss 500'!D:D,'Fastmoss 500'!N:N),0) -> 0 | L42: Shp 500 | M42: =IF(L42="Shp 500","Sim",IF(ISNA(_xlfn.XLOOKUP(C42,'Shp 500'!D:D,'Shp 500'!D:D)),"Não","Sim")) -> Sim | N42: =IF(L42="Fastmoss 500","Sim",IF(ISNA(_xlfn.XLOOKUP(_xlfn.XLOOKUP(C42,'Same Seller Hist'!E:E,'Same Seller Hist'!H:H),'Fastmoss 500'!D:D,'Fastmoss 500'!D:D)),"Não","Sim")) -> Não | O42: =IF(AND(M42="Sim",N42="Sim"),"Sim","Não") -> Não | P42: =IF(I42>K42,"Sim","Não") -> Sim | Q42: =COUNTIFS(C:C,C42) -> 1
C43: 367507085 | D43: Lóris Shoes | E43: =_xlfn.XLOOKUP(C43,'Same Seller Hist'!E:E,'Same Seller Hist'!I:I) -> 7.4961541e+18 | F43: =_xlfn.XLOOKUP(C43,'Same Seller Hist'!E:E,'Same Seller Hist'!H:H) -> Lóris Shoes | G43: Fashion | H43: 1376.871 | I43: 13286.643 | J43: =_xlfn.IFNA(_xlfn.XLOOKUP(F43,'Fastmoss 500'!D:D,'Fastmoss 500'!O:O),0) -> 622.58065 | K43: =_xlfn.IFNA(_xlfn.XLOOKUP(F43,'Fastmoss 500'!D:D,'Fastmoss 500'!N:N),0) -> 54838.71 | L43: Shp 500 | M43: =IF(L43="Shp 500","Sim",IF(ISNA(_xlfn.XLOOKUP(C43,'Shp 500'!D:D,'Shp 500'!D:D)),"Não","Sim")) -> Sim | N43: =IF(L43="Fastmoss 500","Sim",IF(ISNA(_xlfn.XLOOKUP(_xlfn.XLOOKUP(C43,'Same Seller Hist'!E:E,'Same Seller Hist'!H:H),'Fastmoss 500'!D:D,'Fastmoss 500'!D:D)),"Não","Sim")) -> Sim | O43: =IF(AND(M43="Sim",N43="Sim"),"Sim","Não") -> Sim | P43: =IF(I43>K43,"Sim","Não") -> Não | Q43: =COUNTIFS(C:C,C43) -> 2
C44: =_xlfn.XLOOKUP(F44,'Same Seller Hist'!H:H,'Same Seller Hist'!E:E) -> 367507085 | D44: =_xlfn.XLOOKUP(F44,'Same Seller Hist'!H:H,'Same Seller Hist'!D:D) -> Lóris Shoes | E44: =_xlfn.XLOOKUP(F44,'Same Seller Hist'!H:H,'Same Seller Hist'!I:I) -> 7.4961541e+18 | F44: Lóris Shoes | G44: =_xlfn.XLOOKUP(C44,'Same Seller Hist'!E:E,'Same Seller Hist'!F:F) -> Fashion | H44: =_xlfn.IFNA(_xlfn.XLOOKUP(C44,'Shp 500'!D:D,'Shp 500'!I:I),0) -> 1376.871 | I44: =_xlfn.IFNA(_xlfn.XLOOKUP(C44,'Shp 500'!D:D,'Shp 500'!J:J),0) -> 13286.643 | J44: 622.58065 | K44: 54838.71 | L44: Fastmoss 500 | M44: =IF(L44="Shp 500","Sim",IF(ISNA(_xlfn.XLOOKUP(C44,'Shp 500'!D:D,'Shp 500'!D:D)),"Não","Sim")) -> Sim | N44: =IF(L44="Fastmoss 500","Sim",IF(ISNA(_xlfn.XLOOKUP(_xlfn.XLOOKUP(C44,'Same Seller Hist'!E:E,'Same Seller Hist'!H:H),'Fastmoss 500'!D:D,'Fastmoss 500'!D:D)),"Não","Sim")) -> Sim | O44: =IF(AND(M44="Sim",N44="Sim"),"Sim","Não") -> Sim | P44: =IF(I44>K44,"Sim","Não") -> Não | Q44: =COUNTIFS(C:C,C44) -> 2
C45: 373261329 | D45: Principia Skincare | E45: =_xlfn.XLOOKUP(C45,'Same Seller Hist'!E:E,'Same Seller Hist'!I:I) -> 7.4961539e+18 | F45: =_xlfn.XLOOKUP(C45,'Same Seller Hist'!E:E,'Same Seller Hist'!H:H) -> PRINCIPIA | G45: FMCG | H45: 2353.2903 | I45: 30442.55 | J45: =_xlfn.IFNA(_xlfn.XLOOKUP(F45,'Fastmoss 500'!D:D,'Fastmoss 500'!O:O),0) -> 593.54839 | K45: =_xlfn.IFNA(_xlfn.XLOOKUP(F45,'Fastmoss 500'!D:D,'Fastmoss 500'!N:N),0) -> 48387.097 | L45: Shp 500 | M45: =IF(L45="Shp 500","Sim",IF(ISNA(_xlfn.XLOOKUP(C45,'Shp 500'!D:D,'Shp 500'!D:D)),"Não","Sim")) -> Sim | N45: =IF(L45="Fastmoss 500","Sim",IF(ISNA(_xlfn.XLOOKUP(_xlfn.XLOOKUP(C45,'Same Seller Hist'!E:E,'Same Seller Hist'!H:H),'Fastmoss 500'!D:D,'Fastmoss 500'!D:D)),"Não","Sim")) -> Sim | O45: =IF(AND(M45="Sim",N45="Sim"),"Sim","Não") -> Sim | P45: =IF(I45>K45,"Sim","Não") -> Não | Q45: =COUNTIFS(C:C,C45) -> 2
C46: =_xlfn.XLOOKUP(F46,'Same Seller Hist'!H:H,'Same Seller Hist'!E:E) -> 373261329 | D46: =_xlfn.XLOOKUP(F46,'Same Seller Hist'!H:H,'Same Seller Hist'!D:D) -> PRINCIPIA | E46: =_xlfn.XLOOKUP(F46,'Same Seller Hist'!H:H,'Same Seller Hist'!I:I) -> 7.4961539e+18 | F46: PRINCIPIA | G46: =_xlfn.XLOOKUP(C46,'Same Seller Hist'!E:E,'Same Seller Hist'!F:F) -> FMCG | H46: =_xlfn.IFNA(_xlfn.XLOOKUP(C46,'Shp 500'!D:D,'Shp 500'!I:I),0) -> 2353.2903 | I46: =_xlfn.IFNA(_xlfn.XLOOKUP(C46,'Shp 500'!D:D,'Shp 500'!J:J),0) -> 30442.55 | J46: 593.54839 | K46: 48387.097 | L46: Fastmoss 500 | M46: =IF(L46="Shp 500","Sim",IF(ISNA(_xlfn.XLOOKUP(C46,'Shp 500'!D:D,'Shp 500'!D:D)),"Não","Sim")) -> Sim | N46: =IF(L46="Fastmoss 500","Sim",IF(ISNA(_xlfn.XLOOKUP(_xlfn.XLOOKUP(C46,'Same Seller Hist'!E:E,'Same Seller Hist'!H:H),'Fastmoss 500'!D:D,'Fastmoss 500'!D:D)),"Não","Sim")) -> Sim | O46: =IF(AND(M46="Sim",N46="Sim"),"Sim","Não") -> Sim | P46: =IF(I46>K46,"Sim","Não") -> Não | Q46: =COUNTIFS(C:C,C46) -> 2
C47: 407760070 | D47: Karseell Oficial | E47: =_xlfn.XLOOKUP(C47,'Same Seller Hist'!E:E,'Same Seller Hist'!I:I) -> 7.4962131e+18 | F47: =_xlfn.XLOOKUP(C47,'Same Seller Hist'!E:E,'Same Seller Hist'!H:H) -> Karseellshop-BR | G47: FMCG | H47: 2112 | I47: 14126.845 | J47: =_xlfn.IFNA(_xlfn.XLOOKUP(F47,'Fastmoss 500'!D:D,'Fastmoss 500'!O:O),0) -> 0 | K47: =_xlfn.IFNA(_xlfn.XLOOKUP(F47,'Fastmoss 500'!D:D,'Fastmoss 500'!N:N),0) -> 0 | L47: Shp 500 | M47: =IF(L47="Shp 500","Sim",IF(ISNA(_xlfn.XLOOKUP(C47,'Shp 500'!D:D,'Shp 500'!D:D)),"Não","Sim")) -> Sim | N47: =IF(L47="Fastmoss 500","Sim",IF(ISNA(_xlfn.XLOOKUP(_xlfn.XLOOKUP(C47,'Same Seller Hist'!E:E,'Same Seller Hist'!H:H),'Fastmoss 500'!D:D,'Fastmoss 500'!D:D)),"Não","Sim")) -> Não | O47: =IF(AND(M47="Sim",N47="Sim"),"Sim","Não") -> Não | P47: =IF(I47>K47,"Sim","Não") -> Sim | Q47: =COUNTIFS(C:C,C47) -> 1
C48: 373745451 | D48: Keedi Eletrônicos | E48: =_xlfn.XLOOKUP(C48,'Same Seller Hist'!E:E,'Same Seller Hist'!I:I) -> 7.4961741e+18 | F48: =_xlfn.XLOOKUP(C48,'Same Seller Hist'!E:E,'Same Seller Hist'!H:H) -> Keedistore | G48: CN | H48: 892.83871 | I48: 7380.4533 | J48: =_xlfn.IFNA(_xlfn.XLOOKUP(F48,'Fastmoss 500'!D:D,'Fastmoss 500'!O:O),0) -> 261.29032 | K48: =_xlfn.IFNA(_xlfn.XLOOKUP(F48,'Fastmoss 500'!D:D,'Fastmoss 500'!N:N),0) -> 9780.6452 | L48: Shp 500 | M48: =IF(L48="Shp 500","Sim",IF(ISNA(_xlfn.XLOOKUP(C48,'Shp 500'!D:D,'Shp 500'!D:D)),"Não","Sim")) -> Sim | N48: =IF(L48="Fastmoss 500","Sim",IF(ISNA(_xlfn.XLOOKUP(_xlfn.XLOOKUP(C48,'Same Seller Hist'!E:E,'Same Seller Hist'!H:H),'Fastmoss 500'!D:D,'Fastmoss 500'!D:D)),"Não","Sim")) -> Sim | O48: =IF(AND(M48="Sim",N48="Sim"),"Sim","Não") -> Sim | P48: =IF(I48>K48,"Sim","Não") -> Não | Q48: =COUNTIFS(C:C,C48) -> 2
C49: =_xlfn.XLOOKUP(F49,'Same Seller Hist'!H:H,'Same Seller Hist'!E:E) -> 373745451 | D49: =_xlfn.XLOOKUP(F49,'Same Seller Hist'!H:H,'Same Seller Hist'!D:D) -> Keedistore | E49: =_xlfn.XLOOKUP(F49,'Same Seller Hist'!H:H,'Same Seller Hist'!I:I) -> 7.4961741e+18 | F49: Keedistore | G49: =_xlfn.XLOOKUP(C49,'Same Seller Hist'!E:E,'Same Seller Hist'!F:F) -> ELHA | H49: =_xlfn.IFNA(_xlfn.XLOOKUP(C49,'Shp 500'!D:D,'Shp 500'!I:I),0) -> 892.83871 | I49: =_xlfn.IFNA(_xlfn.XLOOKUP(C49,'Shp 500'!D:D,'Shp 500'!J:J),0) -> 7380.4533 | J49: 261.29032 | K49: 9780.6452 | L49: Fastmoss 500 | M49: =IF(L49="Shp 500","Sim",IF(ISNA(_xlfn.XLOOKUP(C49,'Shp 500'!D:D,'Shp 500'!D:D)),"Não","Sim")) -> Sim | N49: =IF(L49="Fastmoss 500","Sim",IF(ISNA(_xlfn.XLOOKUP(_xlfn.XLOOKUP(C49,'Same Seller Hist'!E:E,'Same Seller Hist'!H:H),'Fastmoss 500'!D:D,'Fastmoss 500'!D:D)),"Não","Sim")) -> Sim | O49: =IF(AND(M49="Sim",N49="Sim"),"Sim","Não") -> Sim | P49: =IF(I49>K49,"Sim","Não") -> Não | Q49: =COUNTIFS(C:C,C49) -> 2
C50: 1515741369 | D50: HEXUN SHOP | E50: =_xlfn.XLOOKUP(C50,'Same Seller Hist'!E:E,'Same Seller Hist'!I:I) -> 7.4961822e+18 | F50: =_xlfn.XLOOKUP(C50,'Same Seller Hist'!E:E,'Same Seller Hist'!H:H) -> HEXUNSHOP | G50: CN | H50: 1902.6774 | I50: 11655.041 | J50: =_xlfn.IFNA(_xlfn.XLOOKUP(F50,'Fastmoss 500'!D:D,'Fastmoss 500'!O:O),0) -> 0 | K50: =_xlfn.IFNA(_xlfn.XLOOKUP(F50,'Fastmoss 500'!D:D,'Fastmoss 500'!N:N),0) -> 0 | L50: Shp 500 | M50: =IF(L50="Shp 500","Sim",IF(ISNA(_xlfn.XLOOKUP(C50,'Shp 500'!D:D,'Shp 500'!D:D)),"Não","Sim")) -> Sim | N50: =IF(L50="Fastmoss 500","Sim",IF(ISNA(_xlfn.XLOOKUP(_xlfn.XLOOKUP(C50,'Same Seller Hist'!E:E,'Same Seller Hist'!H:H),'Fastmoss 500'!D:D,'Fastmoss 500'!D:D)),"Não","Sim")) -> Não | O50: =IF(AND(M50="Sim",N50="Sim"),"Sim","Não") -> Não | P50: =IF(I50>K50,"Sim","Não") -> Sim | Q50: =COUNTIFS(C:C,C50) -> 1
C51: 322432427 | D51: Amor de Make Oficial | E51: =_xlfn.XLOOKUP(C51,'Same Seller Hist'!E:E,'Same Seller Hist'!I:I) -> 7.4941559e+18 | F51: =_xlfn.XLOOKUP(C51,'Same Seller Hist'!E:E,'Same Seller Hist'!H:H) -> Amor de Make | G51: FMCG | H51: 1889.0645 | I51: 13057.062 | J51: =_xlfn.IFNA(_xlfn.XLOOKUP(F51,'Fastmoss 500'!D:D,'Fastmoss 500'!O:O),0) -> 0 | K51: =_xlfn.IFNA(_xlfn.XLOOKUP(F51,'Fastmoss 500'!D:D,'Fastmoss 500'!N:N),0) -> 0 | L51: Shp 500 | M51: =IF(L51="Shp 500","Sim",IF(ISNA(_xlfn.XLOOKUP(C51,'Shp 500'!D:D,'Shp 500'!D:D)),"Não","Sim")) -> Sim | N51: =IF(L51="Fastmoss 500","Sim",IF(ISNA(_xlfn.XLOOKUP(_xlfn.XLOOKUP(C51,'Same Seller Hist'!E:E,'Same Seller Hist'!H:H),'Fastmoss 500'!D:D,'Fastmoss 500'!D:D)),"Não","Sim")) -> Não | O51: =IF(AND(M51="Sim",N51="Sim"),"Sim","Não") -> Não | P51: =IF(I51>K51,"Sim","Não") -> Sim | Q51: =COUNTIFS(C:C,C51) -> 1
C52: 375175329 | D52: Shekinah Calçados | E52: =_xlfn.XLOOKUP(C52,'Same Seller Hist'!E:E,'Same Seller Hist'!I:I) -> 7.496155e+18 | F52: =_xlfn.XLOOKUP(C52,'Same Seller Hist'!E:E,'Same Seller Hist'!H:H) -> Shekinah Calçados | G52: Fashion | H52: 1047.6129 | I52: 10358.655 | J52: =_xlfn.IFNA(_xlfn.XLOOKUP(F52,'Fastmoss 500'!D:D,'Fastmoss 500'!O:O),0) -> 296.77419 | K52: =_xlfn.IFNA(_xlfn.XLOOKUP(F52,'Fastmoss 500'!D:D,'Fastmoss 500'!N:N),0) -> 22419.355 | L52: Shp 500 | M52: =IF(L52="Shp 500","Sim",IF(ISNA(_xlfn.XLOOKUP(C52,'Shp 500'!D:D,'Shp 500'!D:D)),"Não","Sim")) -> Sim | N52: =IF(L52="Fastmoss 500","Sim",IF(ISNA(_xlfn.XLOOKUP(_xlfn.XLOOKUP(C52,'Same Seller Hist'!E:E,'Same Seller Hist'!H:H),'Fastmoss 500'!D:D,'Fastmoss 500'!D:D)),"Não","Sim")) -> Sim | O52: =IF(AND(M52="Sim",N52="Sim"),"Sim","Não") -> Sim | P52: =IF(I52>K52,"Sim","Não") -> Não | Q52: =COUNTIFS(C:C,C52) -> 2
C53: 489001115 | D53: Dutra Máquinas | E53: =_xlfn.XLOOKUP(C53,'Same Seller Hist'!E:E,'Same Seller Hist'!I:I) -> 7.4961625e+18 | F53: =_xlfn.XLOOKUP(C53,'Same Seller Hist'!E:E,'Same Seller Hist'!H:H) -> Dutra Máquinas | G53: ELHA | H53: 1873.2258 | I53: 62143.234 | J53: =_xlfn.IFNA(_xlfn.XLOOKUP(F53,'Fastmoss 500'!D:D,'Fastmoss 500'!O:O),0) -> 0 | K53: =_xlfn.IFNA(_xlfn.XLOOKUP(F53,'Fastmoss 500'!D:D,'Fastmoss 500'!N:N),0) -> 0 | L53: Shp 500 | M53: =IF(L53="Shp 500","Sim",IF(ISNA(_xlfn.XLOOKUP(C53,'Shp 500'!D:D,'Shp 500'!D:D)),"Não","Sim")) -> Sim | N53: =IF(L53="Fastmoss 500","Sim",IF(ISNA(_xlfn.XLOOKUP(_xlfn.XLOOKUP(C53,'Same Seller Hist'!E:E,'Same Seller Hist'!H:H),'Fastmoss 500'!D:D,'Fastmoss 500'!D:D)),"Não","Sim")) -> Não | O53: =IF(AND(M53="Sim",N53="Sim"),"Sim","Não") -> Não | P53: =IF(I53>K53,"Sim","Não") -> Sim | Q53: =COUNTIFS(C:C,C53) -> 1
C54: =_xlfn.XLOOKUP(F54,'Same Seller Hist'!H:H,'Same Seller Hist'!E:E) -> 375175329 | D54: =_xlfn.XLOOKUP(F54,'Same Seller Hist'!H:H,'Same Seller Hist'!D:D) -> Shekinah Calçados | E54: =_xlfn.XLOOKUP(F54,'Same Seller Hist'!H:H,'Same Seller Hist'!I:I) -> 7.496155e+18 | F54: Shekinah Calçados | G54: =_xlfn.XLOOKUP(C54,'Same Seller Hist'!E:E,'Same Seller Hist'!F:F) -> Fashion | H54: =_xlfn.IFNA(_xlfn.XLOOKUP(C54,'Shp 500'!D:D,'Shp 500'!I:I),0) -> 1047.6129 | I54: =_xlfn.IFNA(_xlfn.XLOOKUP(C54,'Shp 500'!D:D,'Shp 500'!J:J),0) -> 10358.655 | J54: 296.77419 | K54: 22419.355 | L54: Fastmoss 500 | M54: =IF(L54="Shp 500","Sim",IF(ISNA(_xlfn.XLOOKUP(C54,'Shp 500'!D:D,'Shp 500'!D:D)),"Não","Sim")) -> Sim | N54: =IF(L54="Fastmoss 500","Sim",IF(ISNA(_xlfn.XLOOKUP(_xlfn.XLOOKUP(C54,'Same Seller Hist'!E:E,'Same Seller Hist'!H:H),'Fastmoss 500'!D:D,'Fastmoss 500'!D:D)),"Não","Sim")) -> Sim | O54: =IF(AND(M54="Sim",N54="Sim"),"Sim","Não") -> Sim | P54: =IF(I54>K54,"Sim","Não") -> Não | Q54: =COUNTIFS(C:C,C54) -> 2
C55: 377126536 | D55: Multineos Comercio | E55: =_xlfn.XLOOKUP(C55,'Same Seller Hist'!E:E,'Same Seller Hist'!I:I) -> 7.4961537e+18 | F55: =_xlfn.XLOOKUP(C55,'Same Seller Hist'!E:E,'Same Seller Hist'!H:H) -> Multineos - Mochila e Bolsa | G55: CN | H55: 1853.5484 | I55: 15479.431 | J55: =_xlfn.IFNA(_xlfn.XLOOKUP(F55,'Fastmoss 500'!D:D,'Fastmoss 500'!O:O),0) -> 506.45161 | K55: =_xlfn.IFNA(_xlfn.XLOOKUP(F55,'Fastmoss 500'!D:D,'Fastmoss 500'!N:N),0) -> 32258.065 | L55: Shp 500 | M55: =IF(L55="Shp 500","Sim",IF(ISNA(_xlfn.XLOOKUP(C55,'Shp 500'!D:D,'Shp 500'!D:D)),"Não","Sim")) -> Sim | N55: =IF(L55="Fastmoss 500","Sim",IF(ISNA(_xlfn.XLOOKUP(_xlfn.XLOOKUP(C55,'Same Seller Hist'!E:E,'Same Seller Hist'!H:H),'Fastmoss 500'!D:D,'Fastmoss 500'!D:D)),"Não","Sim")) -> Sim | O55: =IF(AND(M55="Sim",N55="Sim"),"Sim","Não") -> Sim | P55: =IF(I55>K55,"Sim","Não") -> Não | Q55: =COUNTIFS(C:C,C55) -> 2
C56: =_xlfn.XLOOKUP(F56,'Same Seller Hist'!H:H,'Same Seller Hist'!E:E) -> 377126536 | D56: =_xlfn.XLOOKUP(F56,'Same Seller Hist'!H:H,'Same Seller Hist'!D:D) -> Multineos - Mochila e Bolsa | E56: =_xlfn.XLOOKUP(F56,'Same Seller Hist'!H:H,'Same Seller Hist'!I:I) -> 7.4961537e+18 | F56: Multineos - Mochila e Bolsa | G56: =_xlfn.XLOOKUP(C56,'Same Seller Hist'!E:E,'Same Seller Hist'!F:F) -> Fashion | H56: =_xlfn.IFNA(_xlfn.XLOOKUP(C56,'Shp 500'!D:D,'Shp 500'!I:I),0) -> 1853.5484 | I56: =_xlfn.IFNA(_xlfn.XLOOKUP(C56,'Shp 500'!D:D,'Shp 500'!J:J),0) -> 15479.431 | J56: 506.45161 | K56: 32258.065 | L56: Fastmoss 500 | M56: =IF(L56="Shp 500","Sim",IF(ISNA(_xlfn.XLOOKUP(C56,'Shp 500'!D:D,'Shp 500'!D:D)),"Não","Sim")) -> Sim | N56: =IF(L56="Fastmoss 500","Sim",IF(ISNA(_xlfn.XLOOKUP(_xlfn.XLOOKUP(C56,'Same Seller Hist'!E:E,'Same Seller Hist'!H:H),'Fastmoss 500'!D:D,'Fastmoss 500'!D:D)),"Não","Sim")) -> Sim | O56: =IF(AND(M56="Sim",N56="Sim"),"Sim","Não") -> Sim | P56: =IF(I56>K56,"Sim","Não") -> Não | Q56: =COUNTIFS(C:C,C56) -> 2
C57: 594157579 | D57: Eggers Móveis Modulados | E57: =_xlfn.XLOOKUP(C57,'Same Seller Hist'!E:E,'Same Seller Hist'!I:I) -> 7.496182e+18 | F57: =_xlfn.XLOOKUP(C57,'Same Seller Hist'!E:E,'Same Seller Hist'!H:H) -> Eggers Móveis Modulados | G57: Lifestyle | H57: 1773.129 | I57: 15343.422 | J57: =_xlfn.IFNA(_xlfn.XLOOKUP(F57,'Fastmoss 500'!D:D,'Fastmoss 500'!O:O),0) -> 0 | K57: =_xlfn.IFNA(_xlfn.XLOOKUP(F57,'Fastmoss 500'!D:D,'Fastmoss 500'!N:N),0) -> 0 | L57: Shp 500 | M57: =IF(L57="Shp 500","Sim",IF(ISNA(_xlfn.XLOOKUP(C57,'Shp 500'!D:D,'Shp 500'!D:D)),"Não","Sim")) -> Sim | N57: =IF(L57="Fastmoss 500","Sim",IF(ISNA(_xlfn.XLOOKUP(_xlfn.XLOOKUP(C57,'Same Seller Hist'!E:E,'Same Seller Hist'!H:H),'Fastmoss 500'!D:D,'Fastmoss 500'!D:D)),"Não","Sim")) -> Não | O57: =IF(AND(M57="Sim",N57="Sim"),"Sim","Não") -> Não | P57: =IF(I57>K57,"Sim","Não") -> Sim | Q57: =COUNTIFS(C:C,C57) -> 1
C58: 387348115 | D58: GiGiL | E58: =_xlfn.XLOOKUP(C58,'Same Seller Hist'!E:E,'Same Seller Hist'!I:I) -> 7.4961604e+18 | F58: =_xlfn.XLOOKUP(C58,'Same Seller Hist'!E:E,'Same Seller Hist'!H:H) -> GiGiL. | G58: Fashion | H58: 1522.5806 | I58: 16855.794 | J58: =_xlfn.IFNA(_xlfn.XLOOKUP(F58,'Fastmoss 500'!D:D,'Fastmoss 500'!O:O),0) -> 470.96774 | K58: =_xlfn.IFNA(_xlfn.XLOOKUP(F58,'Fastmoss 500'!D:D,'Fastmoss 500'!N:N),0) -> 35483.871 | L58: Shp 500 | M58: =IF(L58="Shp 500","Sim",IF(ISNA(_xlfn.XLOOKUP(C58,'Shp 500'!D:D,'Shp 500'!D:D)),"Não","Sim")) -> Sim | N58: =IF(L58="Fastmoss 500","Sim",IF(ISNA(_xlfn.XLOOKUP(_xlfn.XLOOKUP(C58,'Same Seller Hist'!E:E,'Same Seller Hist'!H:H),'Fastmoss 500'!D:D,'Fastmoss 500'!D:D)),"Não","Sim")) -> Sim | O58: =IF(AND(M58="Sim",N58="Sim"),"Sim","Não") -> Sim | P58: =IF(I58>K58,"Sim","Não") -> Não | Q58: =COUNTIFS(C:C,C58) -> 2
C59: 346235717 | D59: Heybox­­ | E59: =_xlfn.XLOOKUP(C59,'Same Seller Hist'!E:E,'Same Seller Hist'!I:I) -> 7.4962836e+18 | F59: =_xlfn.XLOOKUP(C59,'Same Seller Hist'!E:E,'Same Seller Hist'!H:H) -> heybox ?? | G59: Lifestyle | H59: 1755.2581 | I59: 16349.484 | J59: =_xlfn.IFNA(_xlfn.XLOOKUP(F59,'Fastmoss 500'!D:D,'Fastmoss 500'!O:O),0) -> 0 | K59: =_xlfn.IFNA(_xlfn.XLOOKUP(F59,'Fastmoss 500'!D:D,'Fastmoss 500'!N:N),0) -> 0 | L59: Shp 500 | M59: =IF(L59="Shp 500","Sim",IF(ISNA(_xlfn.XLOOKUP(C59,'Shp 500'!D:D,'Shp 500'!D:D)),"Não","Sim")) -> Sim | N59: =IF(L59="Fastmoss 500","Sim",IF(ISNA(_xlfn.XLOOKUP(_xlfn.XLOOKUP(C59,'Same Seller Hist'!E:E,'Same Seller Hist'!H:H),'Fastmoss 500'!D:D,'Fastmoss 500'!D:D)),"Não","Sim")) -> Não | O59: =IF(AND(M59="Sim",N59="Sim"),"Sim","Não") -> Não | P59: =IF(I59>K59,"Sim","Não") -> Sim | Q59: =COUNTIFS(C:C,C59) -> 1
C60: =_xlfn.XLOOKUP(F60,'Same Seller Hist'!H:H,'Same Seller Hist'!E:E) -> 387348115 | D60: =_xlfn.XLOOKUP(F60,'Same Seller Hist'!H:H,'Same Seller Hist'!D:D) -> GiGiL. | E60: =_xlfn.XLOOKUP(F60,'Same Seller Hist'!H:H,'Same Seller Hist'!I:I) -> 7.4961604e+18 | F60: GiGiL. | G60: =_xlfn.XLOOKUP(C60,'Same Seller Hist'!E:E,'Same Seller Hist'!F:F) -> Fashion | H60: =_xlfn.IFNA(_xlfn.XLOOKUP(C60,'Shp 500'!D:D,'Shp 500'!I:I),0) -> 1522.5806 | I60: =_xlfn.IFNA(_xlfn.XLOOKUP(C60,'Shp 500'!D:D,'Shp 500'!J:J),0) -> 16855.794 | J60: 470.96774 | K60: 35483.871 | L60: Fastmoss 500 | M60: =IF(L60="Shp 500","Sim",IF(ISNA(_xlfn.XLOOKUP(C60,'Shp 500'!D:D,'Shp 500'!D:D)),"Não","Sim")) -> Sim | N60: =IF(L60="Fastmoss 500","Sim",IF(ISNA(_xlfn.XLOOKUP(_xlfn.XLOOKUP(C60,'Same Seller Hist'!E:E,'Same Seller Hist'!H:H),'Fastmoss 500'!D:D,'Fastmoss 500'!D:D)),"Não","Sim")) -> Sim | O60: =IF(AND(M60="Sim",N60="Sim"),"Sim","Não") -> Sim | P60: =IF(I60>K60,"Sim","Não") -> Não | Q60: =COUNTIFS(C:C,C60) -> 2
C61: 225117529 | D61: Trissé Acessórios | E61: =_xlfn.XLOOKUP(C61,'Same Seller Hist'!E:E,'Same Seller Hist'!I:I) -> 7.496306e+18 | F61: =_xlfn.XLOOKUP(C61,'Same Seller Hist'!E:E,'Same Seller Hist'!H:H) -> Trissé Acessórios | G61: FMCG | H61: 1688.0645 | I61: 4998.4763 | J61: =_xlfn.IFNA(_xlfn.XLOOKUP(F61,'Fastmoss 500'!D:D,'Fastmoss 500'!O:O),0) -> 0 | K61: =_xlfn.IFNA(_xlfn.XLOOKUP(F61,'Fastmoss 500'!D:D,'Fastmoss 500'!N:N),0) -> 0 | L61: Shp 500 | M61: =IF(L61="Shp 500","Sim",IF(ISNA(_xlfn.XLOOKUP(C61,'Shp 500'!D:D,'Shp 500'!D:D)),"Não","Sim")) -> Sim | N61: =IF(L61="Fastmoss 500","Sim",IF(ISNA(_xlfn.XLOOKUP(_xlfn.XLOOKUP(C61,'Same Seller Hist'!E:E,'Same Seller Hist'!H:H),'Fastmoss 500'!D:D,'Fastmoss 500'!D:D)),"Não","Sim")) -> Não | O61: =IF(AND(M61="Sim",N61="Sim"),"Sim","Não") -> Não | P61: =IF(I61>K61,"Sim","Não") -> Sim | Q61: =COUNTIFS(C:C,C61) -> 1
C62: 816161995 | D62: MULTI BAZAR E-COMMERCE | E62: =_xlfn.XLOOKUP(C62,'Same Seller Hist'!E:E,'Same Seller Hist'!I:I) -> 7.4961865e+18 | F62: =_xlfn.XLOOKUP(C62,'Same Seller Hist'!E:E,'Same Seller Hist'!H:H) -> MULTI BAZAR | G62: CN | H62: 1684.871 | I62: 6098.1941 | J62: =_xlfn.IFNA(_xlfn.XLOOKUP(F62,'Fastmoss 500'!D:D,'Fastmoss 500'!O:O),0) -> 0 | K62: =_xlfn.IFNA(_xlfn.XLOOKUP(F62,'Fastmoss 500'!D:D,'Fastmoss 500'!N:N),0) -> 0 | L62: Shp 500 | M62: =IF(L62="Shp 500","Sim",IF(ISNA(_xlfn.XLOOKUP(C62,'Shp 500'!D:D,'Shp 500'!D:D)),"Não","Sim")) -> Sim | N62: =IF(L62="Fastmoss 500","Sim",IF(ISNA(_xlfn.XLOOKUP(_xlfn.XLOOKUP(C62,'Same Seller Hist'!E:E,'Same Seller Hist'!H:H),'Fastmoss 500'!D:D,'Fastmoss 500'!D:D)),"Não","Sim")) -> Não | O62: =IF(AND(M62="Sim",N62="Sim"),"Sim","Não") -> Não | P62: =IF(I62>K62,"Sim","Não") -> Sim | Q62: =COUNTIFS(C:C,C62) -> 1
C63: 390307022 | D63: ZSZ_brasil | E63: =_xlfn.XLOOKUP(C63,'Same Seller Hist'!E:E,'Same Seller Hist'!I:I) -> 7.4961635e+18 | F63: =_xlfn.XLOOKUP(C63,'Same Seller Hist'!E:E,'Same Seller Hist'!H:H) -> ZSZ BRASIL | G63: CN | H63: 1902.9355 | I63: 9217.4875 | J63: =_xlfn.IFNA(_xlfn.XLOOKUP(F63,'Fastmoss 500'!D:D,'Fastmoss 500'!O:O),0) -> 1687.0968 | K63: =_xlfn.IFNA(_xlfn.XLOOKUP(F63,'Fastmoss 500'!D:D,'Fastmoss 500'!N:N),0) -> 27238.71 | L63: Shp 500 | M63: =IF(L63="Shp 500","Sim",IF(ISNA(_xlfn.XLOOKUP(C63,'Shp 500'!D:D,'Shp 500'!D:D)),"Não","Sim")) -> Sim | N63: =IF(L63="Fastmoss 500","Sim",IF(ISNA(_xlfn.XLOOKUP(_xlfn.XLOOKUP(C63,'Same Seller Hist'!E:E,'Same Seller Hist'!H:H),'Fastmoss 500'!D:D,'Fastmoss 500'!D:D)),"Não","Sim")) -> Sim | O63: =IF(AND(M63="Sim",N63="Sim"),"Sim","Não") -> Sim | P63: =IF(I63>K63,"Sim","Não") -> Não | Q63: =COUNTIFS(C:C,C63) -> 2
C64: =_xlfn.XLOOKUP(F64,'Same Seller Hist'!H:H,'Same Seller Hist'!E:E) -> 390307022 | D64: =_xlfn.XLOOKUP(F64,'Same Seller Hist'!H:H,'Same Seller Hist'!D:D) -> ZSZ BRASIL | E64: =_xlfn.XLOOKUP(F64,'Same Seller Hist'!H:H,'Same Seller Hist'!I:I) -> 7.4961635e+18 | F64: ZSZ BRASIL | G64: =_xlfn.XLOOKUP(C64,'Same Seller Hist'!E:E,'Same Seller Hist'!F:F) -> Lifestyle | H64: =_xlfn.IFNA(_xlfn.XLOOKUP(C64,'Shp 500'!D:D,'Shp 500'!I:I),0) -> 1902.9355 | I64: =_xlfn.IFNA(_xlfn.XLOOKUP(C64,'Shp 500'!D:D,'Shp 500'!J:J),0) -> 9217.4875 | J64: 1687.0968 | K64: 27238.71 | L64: Fastmoss 500 | M64: =IF(L64="Shp 500","Sim",IF(ISNA(_xlfn.XLOOKUP(C64,'Shp 500'!D:D,'Shp 500'!D:D)),"Não","Sim")) -> Sim | N64: =IF(L64="Fastmoss 500","Sim",IF(ISNA(_xlfn.XLOOKUP(_xlfn.XLOOKUP(C64,'Same Seller Hist'!E:E,'Same Seller Hist'!H:H),'Fastmoss 500'!D:D,'Fastmoss 500'!D:D)),"Não","Sim")) -> Sim | O64: =IF(AND(M64="Sim",N64="Sim"),"Sim","Não") -> Sim | P64: =IF(I64>K64,"Sim","Não") -> Não | Q64: =COUNTIFS(C:C,C64) -> 2
C65: 644980753 | D65: Encanto de Beleza | E65: =_xlfn.XLOOKUP(C65,'Same Seller Hist'!E:E,'Same Seller Hist'!I:I) -> 7.4962725e+18 | F65: =_xlfn.XLOOKUP(C65,'Same Seller Hist'!E:E,'Same Seller Hist'!H:H) -> Encando da Beleza | G65: FMCG | H65: 1623.7097 | I65: 6583.0182 | J65: =_xlfn.IFNA(_xlfn.XLOOKUP(F65,'Fastmoss 500'!D:D,'Fastmoss 500'!O:O),0) -> 0 | K65: =_xlfn.IFNA(_xlfn.XLOOKUP(F65,'Fastmoss 500'!D:D,'Fastmoss 500'!N:N),0) -> 0 | L65: Shp 500 | M65: =IF(L65="Shp 500","Sim",IF(ISNA(_xlfn.XLOOKUP(C65,'Shp 500'!D:D,'Shp 500'!D:D)),"Não","Sim")) -> Sim | N65: =IF(L65="Fastmoss 500","Sim",IF(ISNA(_xlfn.XLOOKUP(_xlfn.XLOOKUP(C65,'Same Seller Hist'!E:E,'Same Seller Hist'!H:H),'Fastmoss 500'!D:D,'Fastmoss 500'!D:D)),"Não","Sim")) -> Não | O65: =IF(AND(M65="Sim",N65="Sim"),"Sim","Não") -> Não | P65: =IF(I65>K65,"Sim","Não") -> Sim | Q65: =COUNTIFS(C:C,C65) -> 1
C66: 391739739 | D66: ANJ.GG store | E66: =_xlfn.XLOOKUP(C66,'Same Seller Hist'!E:E,'Same Seller Hist'!I:I) -> 7.4961475e+18 | F66: =_xlfn.XLOOKUP(C66,'Same Seller Hist'!E:E,'Same Seller Hist'!H:H) -> ANJGG.STORE | G66: CN | H66: 6695.3226 | I66: 52809.985 | J66: =_xlfn.IFNA(_xlfn.XLOOKUP(F66,'Fastmoss 500'!D:D,'Fastmoss 500'!O:O),0) -> 912.90323 | K66: =_xlfn.IFNA(_xlfn.XLOOKUP(F66,'Fastmoss 500'!D:D,'Fastmoss 500'!N:N),0) -> 41935.484 | L66: Shp 500 | M66: =IF(L66="Shp 500","Sim",IF(ISNA(_xlfn.XLOOKUP(C66,'Shp 500'!D:D,'Shp 500'!D:D)),"Não","Sim")) -> Sim | N66: =IF(L66="Fastmoss 500","Sim",IF(ISNA(_xlfn.XLOOKUP(_xlfn.XLOOKUP(C66,'Same Seller Hist'!E:E,'Same Seller Hist'!H:H),'Fastmoss 500'!D:D,'Fastmoss 500'!D:D)),"Não","Sim")) -> Sim | O66: =IF(AND(M66="Sim",N66="Sim"),"Sim","Não") -> Sim | P66: =IF(I66>K66,"Sim","Não") -> Sim | Q66: =COUNTIFS(C:C,C66) -> 2
C67: 1005980154 | D67: Arara.store | E67: =_xlfn.XLOOKUP(C67,'Same Seller Hist'!E:E,'Same Seller Hist'!I:I) -> 7.4941693e+18 | F67: =_xlfn.XLOOKUP(C67,'Same Seller Hist'!E:E,'Same Seller Hist'!H:H) -> Arara Store. | G67: CN | H67: 1618.1613 | I67: 10420.293 | J67: =_xlfn.IFNA(_xlfn.XLOOKUP(F67,'Fastmoss 500'!D:D,'Fastmoss 500'!O:O),0) -> 0 | K67: =_xlfn.IFNA(_xlfn.XLOOKUP(F67,'Fastmoss 500'!D:D,'Fastmoss 500'!N:N),0) -> 0 | L67: Shp 500 | M67: =IF(L67="Shp 500","Sim",IF(ISNA(_xlfn.XLOOKUP(C67,'Shp 500'!D:D,'Shp 500'!D:D)),"Não","Sim")) -> Sim | N67: =IF(L67="Fastmoss 500","Sim",IF(ISNA(_xlfn.XLOOKUP(_xlfn.XLOOKUP(C67,'Same Seller Hist'!E:E,'Same Seller Hist'!H:H),'Fastmoss 500'!D:D,'Fastmoss 500'!D:D)),"Não","Sim")) -> Não | O67: =IF(AND(M67="Sim",N67="Sim"),"Sim","Não") -> Não | P67: =IF(I67>K67,"Sim","Não") -> Sim | Q67: =COUNTIFS(C:C,C67) -> 1
C68: 659435897 | D68: Gud Buy | E68: =_xlfn.XLOOKUP(C68,'Same Seller Hist'!E:E,'Same Seller Hist'!I:I) -> 7.4961823e+18 | F68: =_xlfn.XLOOKUP(C68,'Same Seller Hist'!E:E,'Same Seller Hist'!H:H) -> GudBuy | G68: CN | H68: 1613.8387 | I68: 14152.908 | J68: =_xlfn.IFNA(_xlfn.XLOOKUP(F68,'Fastmoss 500'!D:D,'Fastmoss 500'!O:O),0) -> 0 | K68: =_xlfn.IFNA(_xlfn.XLOOKUP(F68,'Fastmoss 500'!D:D,'Fastmoss 500'!N:N),0) -> 0 | L68: Shp 500 | M68: =IF(L68="Shp 500","Sim",IF(ISNA(_xlfn.XLOOKUP(C68,'Shp 500'!D:D,'Shp 500'!D:D)),"Não","Sim")) -> Sim | N68: =IF(L68="Fastmoss 500","Sim",IF(ISNA(_xlfn.XLOOKUP(_xlfn.XLOOKUP(C68,'Same Seller Hist'!E:E,'Same Seller Hist'!H:H),'Fastmoss 500'!D:D,'Fastmoss 500'!D:D)),"Não","Sim")) -> Não | O68: =IF(AND(M68="Sim",N68="Sim"),"Sim","Não") -> Não | P68: =IF(I68>K68,"Sim","Não") -> Sim | Q68: =COUNTIFS(C:C,C68) -> 1
C69: 984950642 | D69: Gira Casa | E69: =_xlfn.XLOOKUP(C69,'Same Seller Hist'!E:E,'Same Seller Hist'!I:I) -> 7.4941259e+18 | F69: =_xlfn.XLOOKUP(C69,'Same Seller Hist'!E:E,'Same Seller Hist'!H:H) -> Gira Casa | G69: Lifestyle | H69: 1595.8387 | I69: 16729.223 | J69: =_xlfn.IFNA(_xlfn.XLOOKUP(F69,'Fastmoss 500'!D:D,'Fastmoss 500'!O:O),0) -> 0 | K69: =_xlfn.IFNA(_xlfn.XLOOKUP(F69,'Fastmoss 500'!D:D,'Fastmoss 500'!N:N),0) -> 0 | L69: Shp 500 | M69: =IF(L69="Shp 500","Sim",IF(ISNA(_xlfn.XLOOKUP(C69,'Shp 500'!D:D,'Shp 500'!D:D)),"Não","Sim")) -> Sim | N69: =IF(L69="Fastmoss 500","Sim",IF(ISNA(_xlfn.XLOOKUP(_xlfn.XLOOKUP(C69,'Same Seller Hist'!E:E,'Same Seller Hist'!H:H),'Fastmoss 500'!D:D,'Fastmoss 500'!D:D)),"Não","Sim")) -> Não | O69: =IF(AND(M69="Sim",N69="Sim"),"Sim","Não") -> Não | P69: =IF(I69>K69,"Sim","Não") -> Sim | Q69: =COUNTIFS(C:C,C69) -> 1
C70: 371656735 | D70: MY COMERCIO | E70: =_xlfn.XLOOKUP(C70,'Same Seller Hist'!E:E,'Same Seller Hist'!I:I) -> 7.4961622e+18 | F70: =_xlfn.XLOOKUP(C70,'Same Seller Hist'!E:E,'Same Seller Hist'!H:H) -> my comercio | G70: CN | H70: 1588.1935 | I70: 7553.4754 | J70: =_xlfn.IFNA(_xlfn.XLOOKUP(F70,'Fastmoss 500'!D:D,'Fastmoss 500'!O:O),0) -> 0 | K70: =_xlfn.IFNA(_xlfn.XLOOKUP(F70,'Fastmoss 500'!D:D,'Fastmoss 500'!N:N),0) -> 0 | L70: Shp 500 | M70: =IF(L70="Shp 500","Sim",IF(ISNA(_xlfn.XLOOKUP(C70,'Shp 500'!D:D,'Shp 500'!D:D)),"Não","Sim")) -> Sim | N70: =IF(L70="Fastmoss 500","Sim",IF(ISNA(_xlfn.XLOOKUP(_xlfn.XLOOKUP(C70,'Same Seller Hist'!E:E,'Same Seller Hist'!H:H),'Fastmoss 500'!D:D,'Fastmoss 500'!D:D)),"Não","Sim")) -> Não | O70: =IF(AND(M70="Sim",N70="Sim"),"Sim","Não") -> Não | P70: =IF(I70>K70,"Sim","Não") -> Sim | Q70: =COUNTIFS(C:C,C70) -> 1
C71: =_xlfn.XLOOKUP(F71,'Same Seller Hist'!H:H,'Same Seller Hist'!E:E) -> 391739739 | D71: =_xlfn.XLOOKUP(F71,'Same Seller Hist'!H:H,'Same Seller Hist'!D:D) -> ANJGG.STORE | E71: =_xlfn.XLOOKUP(F71,'Same Seller Hist'!H:H,'Same Seller Hist'!I:I) -> 7.4961475e+18 | F71: ANJGG.STORE | G71: =_xlfn.XLOOKUP(C71,'Same Seller Hist'!E:E,'Same Seller Hist'!F:F) -> ELHA | H71: =_xlfn.IFNA(_xlfn.XLOOKUP(C71,'Shp 500'!D:D,'Shp 500'!I:I),0) -> 6695.3226 | I71: =_xlfn.IFNA(_xlfn.XLOOKUP(C71,'Shp 500'!D:D,'Shp 500'!J:J),0) -> 52809.985 | J71: 912.90323 | K71: 41935.484 | L71: Fastmoss 500 | M71: =IF(L71="Shp 500","Sim",IF(ISNA(_xlfn.XLOOKUP(C71,'Shp 500'!D:D,'Shp 500'!D:D)),"Não","Sim")) -> Sim | N71: =IF(L71="Fastmoss 500","Sim",IF(ISNA(_xlfn.XLOOKUP(_xlfn.XLOOKUP(C71,'Same Seller Hist'!E:E,'Same Seller Hist'!H:H),'Fastmoss 500'!D:D,'Fastmoss 500'!D:D)),"Não","Sim")) -> Sim | O71: =IF(AND(M71="Sim",N71="Sim"),"Sim","Não") -> Sim | P71: =IF(I71>K71,"Sim","Não") -> Sim | Q71: =COUNTIFS(C:C,C71) -> 2
C72: 397374716 | D72: NEZHA SHOP | E72: =_xlfn.XLOOKUP(C72,'Same Seller Hist'!E:E,'Same Seller Hist'!I:I) -> 0 | F72: =_xlfn.XLOOKUP(C72,'Same Seller Hist'!E:E,'Same Seller Hist'!H:H) -> 0 | G72: CN | H72: 995.48387 | I72: 7664.8529 | J72: =_xlfn.IFNA(_xlfn.XLOOKUP(F72,'Fastmoss 500'!D:D,'Fastmoss 500'!O:O),0) -> 0 | K72: =_xlfn.IFNA(_xlfn.XLOOKUP(F72,'Fastmoss 500'!D:D,'Fastmoss 500'!N:N),0) -> 0 | L72: Shp 500 | M72: =IF(L72="Shp 500","Sim",IF(ISNA(_xlfn.XLOOKUP(C72,'Shp 500'!D:D,'Shp 500'!D:D)),"Não","Sim")) -> Sim | N72: =IF(L72="Fastmoss 500","Sim",IF(ISNA(_xlfn.XLOOKUP(_xlfn.XLOOKUP(C72,'Same Seller Hist'!E:E,'Same Seller Hist'!H:H),'Fastmoss 500'!D:D,'Fastmoss 500'!D:D)),"Não","Sim")) -> Não | O72: =IF(AND(M72="Sim",N72="Sim"),"Sim","Não") -> Não | P72: =IF(I72>K72,"Sim","Não") -> Sim | Q72: =COUNTIFS(C:C,C72) -> 2
C73: =_xlfn.XLOOKUP(F73,'Same Seller Hist'!H:H,'Same Seller Hist'!E:E) -> 397374716 | D73: =_xlfn.XLOOKUP(F73,'Same Seller Hist'!H:H,'Same Seller Hist'!D:D) -> NezhaFeira | E73: =_xlfn.XLOOKUP(F73,'Same Seller Hist'!H:H,'Same Seller Hist'!I:I) -> 7.4941348e+18 | F73: NezhaFeira | G73: =_xlfn.XLOOKUP(C73,'Same Seller Hist'!E:E,'Same Seller Hist'!F:F) -> ELHA | H73: =_xlfn.IFNA(_xlfn.XLOOKUP(C73,'Shp 500'!D:D,'Shp 500'!I:I),0) -> 995.48387 | I73: =_xlfn.IFNA(_xlfn.XLOOKUP(C73,'Shp 500'!D:D,'Shp 500'!J:J),0) -> 7664.8529 | J73: 348.3871 | K73: 16558.065 | L73: Fastmoss 500 | M73: =IF(L73="Shp 500","Sim",IF(ISNA(_xlfn.XLOOKUP(C73,'Shp 500'!D:D,'Shp 500'!D:D)),"Não","Sim")) -> Sim | N73: =IF(L73="Fastmoss 500","Sim",IF(ISNA(_xlfn.XLOOKUP(_xlfn.XLOOKUP(C73,'Same Seller Hist'!E:E,'Same Seller Hist'!H:H),'Fastmoss 500'!D:D,'Fastmoss 500'!D:D)),"Não","Sim")) -> Sim | O73: =IF(AND(M73="Sim",N73="Sim"),"Sim","Não") -> Sim | P73: =IF(I73>K73,"Sim","Não") -> Não | Q73: =COUNTIFS(C:C,C73) -> 2
C74: 400905650 | D74: Plenitude Distribuidora | E74: =_xlfn.XLOOKUP(C74,'Same Seller Hist'!E:E,'Same Seller Hist'!I:I) -> 7.4961866e+18 | F74: =_xlfn.XLOOKUP(C74,'Same Seller Hist'!E:E,'Same Seller Hist'!H:H) -> Plenitude Distribuidora | G74: FMCG | H74: 1494.1613 | I74: 11406.27 | J74: =_xlfn.IFNA(_xlfn.XLOOKUP(F74,'Fastmoss 500'!D:D,'Fastmoss 500'!O:O),0) -> 241.93548 | K74: =_xlfn.IFNA(_xlfn.XLOOKUP(F74,'Fastmoss 500'!D:D,'Fastmoss 500'!N:N),0) -> 12609.677 | L74: Shp 500 | M74: =IF(L74="Shp 500","Sim",IF(ISNA(_xlfn.XLOOKUP(C74,'Shp 500'!D:D,'Shp 500'!D:D)),"Não","Sim")) -> Sim | N74: =IF(L74="Fastmoss 500","Sim",IF(ISNA(_xlfn.XLOOKUP(_xlfn.XLOOKUP(C74,'Same Seller Hist'!E:E,'Same Seller Hist'!H:H),'Fastmoss 500'!D:D,'Fastmoss 500'!D:D)),"Não","Sim")) -> Sim | O74: =IF(AND(M74="Sim",N74="Sim"),"Sim","Não") -> Sim | P74: =IF(I74>K74,"Sim","Não") -> Não | Q74: =COUNTIFS(C:C,C74) -> 2
C75: 371728614 | D75: Osure | E75: =_xlfn.XLOOKUP(C75,'Same Seller Hist'!E:E,'Same Seller Hist'!I:I) -> 7.4961675e+18 | F75: =_xlfn.XLOOKUP(C75,'Same Seller Hist'!E:E,'Same Seller Hist'!H:H) -> OSURE | G75: CN | H75: 1486.6774 | I75: 21942.517 | J75: =_xlfn.IFNA(_xlfn.XLOOKUP(F75,'Fastmoss 500'!D:D,'Fastmoss 500'!O:O),0) -> 0 | K75: =_xlfn.IFNA(_xlfn.XLOOKUP(F75,'Fastmoss 500'!D:D,'Fastmoss 500'!N:N),0) -> 0 | L75: Shp 500 | M75: =IF(L75="Shp 500","Sim",IF(ISNA(_xlfn.XLOOKUP(C75,'Shp 500'!D:D,'Shp 500'!D:D)),"Não","Sim")) -> Sim | N75: =IF(L75="Fastmoss 500","Sim",IF(ISNA(_xlfn.XLOOKUP(_xlfn.XLOOKUP(C75,'Same Seller Hist'!E:E,'Same Seller Hist'!H:H),'Fastmoss 500'!D:D,'Fastmoss 500'!D:D)),"Não","Sim")) -> Não | O75: =IF(AND(M75="Sim",N75="Sim"),"Sim","Não") -> Não | P75: =IF(I75>K75,"Sim","Não") -> Sim | Q75: =COUNTIFS(C:C,C75) -> 1
C76: 305201598 | D76: ONE LIGHT SHOP | E76: =_xlfn.XLOOKUP(C76,'Same Seller Hist'!E:E,'Same Seller Hist'!I:I) -> 7.4961809e+18 | F76: =_xlfn.XLOOKUP(C76,'Same Seller Hist'!E:E,'Same Seller Hist'!H:H) -> ONE LIGHT SHOP BR | G76: CN | H76: 1486.4839 | I76: 8039.4133 | J76: =_xlfn.IFNA(_xlfn.XLOOKUP(F76,'Fastmoss 500'!D:D,'Fastmoss 500'!O:O),0) -> 0 | K76: =_xlfn.IFNA(_xlfn.XLOOKUP(F76,'Fastmoss 500'!D:D,'Fastmoss 500'!N:N),0) -> 0 | L76: Shp 500 | M76: =IF(L76="Shp 500","Sim",IF(ISNA(_xlfn.XLOOKUP(C76,'Shp 500'!D:D,'Shp 500'!D:D)),"Não","Sim")) -> Sim | N76: =IF(L76="Fastmoss 500","Sim",IF(ISNA(_xlfn.XLOOKUP(_xlfn.XLOOKUP(C76,'Same Seller Hist'!E:E,'Same Seller Hist'!H:H),'Fastmoss 500'!D:D,'Fastmoss 500'!D:D)),"Não","Sim")) -> Não | O76: =IF(AND(M76="Sim",N76="Sim"),"Sim","Não") -> Não | P76: =IF(I76>K76,"Sim","Não") -> Sim | Q76: =COUNTIFS(C:C,C76) -> 1
C77: 487505431 | D77: FU MOON | E77: =_xlfn.XLOOKUP(C77,'Same Seller Hist'!E:E,'Same Seller Hist'!I:I) -> 7.4961855e+18 | F77: =_xlfn.XLOOKUP(C77,'Same Seller Hist'!E:E,'Same Seller Hist'!H:H) -> FU Moon | G77: CN | H77: 1444.4516 | I77: 6648.9026 | J77: =_xlfn.IFNA(_xlfn.XLOOKUP(F77,'Fastmoss 500'!D:D,'Fastmoss 500'!O:O),0) -> 0 | K77: =_xlfn.IFNA(_xlfn.XLOOKUP(F77,'Fastmoss 500'!D:D,'Fastmoss 500'!N:N),0) -> 0 | L77: Shp 500 | M77: =IF(L77="Shp 500","Sim",IF(ISNA(_xlfn.XLOOKUP(C77,'Shp 500'!D:D,'Shp 500'!D:D)),"Não","Sim")) -> Sim | N77: =IF(L77="Fastmoss 500","Sim",IF(ISNA(_xlfn.XLOOKUP(_xlfn.XLOOKUP(C77,'Same Seller Hist'!E:E,'Same Seller Hist'!H:H),'Fastmoss 500'!D:D,'Fastmoss 500'!D:D)),"Não","Sim")) -> Não | O77: =IF(AND(M77="Sim",N77="Sim"),"Sim","Não") -> Não | P77: =IF(I77>K77,"Sim","Não") -> Sim | Q77: =COUNTIFS(C:C,C77) -> 1
C78: 294602625 | D78: Colina Shop | E78: =_xlfn.XLOOKUP(C78,'Same Seller Hist'!E:E,'Same Seller Hist'!I:I) -> 7.4941681e+18 | F78: =_xlfn.XLOOKUP(C78,'Same Seller Hist'!E:E,'Same Seller Hist'!H:H) -> Colina.shop | G78: Lifestyle | H78: 1437.5161 | I78: 5645.7252 | J78: =_xlfn.IFNA(_xlfn.XLOOKUP(F78,'Fastmoss 500'!D:D,'Fastmoss 500'!O:O),0) -> 0 | K78: =_xlfn.IFNA(_xlfn.XLOOKUP(F78,'Fastmoss 500'!D:D,'Fastmoss 500'!N:N),0) -> 0 | L78: Shp 500 | M78: =IF(L78="Shp 500","Sim",IF(ISNA(_xlfn.XLOOKUP(C78,'Shp 500'!D:D,'Shp 500'!D:D)),"Não","Sim")) -> Sim | N78: =IF(L78="Fastmoss 500","Sim",IF(ISNA(_xlfn.XLOOKUP(_xlfn.XLOOKUP(C78,'Same Seller Hist'!E:E,'Same Seller Hist'!H:H),'Fastmoss 500'!D:D,'Fastmoss 500'!D:D)),"Não","Sim")) -> Não | O78: =IF(AND(M78="Sim",N78="Sim"),"Sim","Não") -> Não | P78: =IF(I78>K78,"Sim","Não") -> Sim | Q78: =COUNTIFS(C:C,C78) -> 1
C79: 384529520 | D79: Ninipink Store | E79: =_xlfn.XLOOKUP(C79,'Same Seller Hist'!E:E,'Same Seller Hist'!I:I) -> 7.4961819e+18 | F79: =_xlfn.XLOOKUP(C79,'Same Seller Hist'!E:E,'Same Seller Hist'!H:H) -> Ninipink Store | G79: CN | H79: 1436.3226 | I79: 7309.1527 | J79: =_xlfn.IFNA(_xlfn.XLOOKUP(F79,'Fastmoss 500'!D:D,'Fastmoss 500'!O:O),0) -> 0 | K79: =_xlfn.IFNA(_xlfn.XLOOKUP(F79,'Fastmoss 500'!D:D,'Fastmoss 500'!N:N),0) -> 0 | L79: Shp 500 | M79: =IF(L79="Shp 500","Sim",IF(ISNA(_xlfn.XLOOKUP(C79,'Shp 500'!D:D,'Shp 500'!D:D)),"Não","Sim")) -> Sim | N79: =IF(L79="Fastmoss 500","Sim",IF(ISNA(_xlfn.XLOOKUP(_xlfn.XLOOKUP(C79,'Same Seller Hist'!E:E,'Same Seller Hist'!H:H),'Fastmoss 500'!D:D,'Fastmoss 500'!D:D)),"Não","Sim")) -> Não | O79: =IF(AND(M79="Sim",N79="Sim"),"Sim","Não") -> Não | P79: =IF(I79>K79,"Sim","Não") -> Sim | Q79: =COUNTIFS(C:C,C79) -> 1
C80: 1101178064 | D80: Jatobraz | E80: =_xlfn.XLOOKUP(C80,'Same Seller Hist'!E:E,'Same Seller Hist'!I:I) -> 7.496182e+18 | F80: =_xlfn.XLOOKUP(C80,'Same Seller Hist'!E:E,'Same Seller Hist'!H:H) -> JATOBRAZ BRASIL | G80: Lifestyle | H80: 1420.3871 | I80: 9179.3451 | J80: =_xlfn.IFNA(_xlfn.XLOOKUP(F80,'Fastmoss 500'!D:D,'Fastmoss 500'!O:O),0) -> 0 | K80: =_xlfn.IFNA(_xlfn.XLOOKUP(F80,'Fastmoss 500'!D:D,'Fastmoss 500'!N:N),0) -> 0 | L80: Shp 500 | M80: =IF(L80="Shp 500","Sim",IF(ISNA(_xlfn.XLOOKUP(C80,'Shp 500'!D:D,'Shp 500'!D:D)),"Não","Sim")) -> Sim | N80: =IF(L80="Fastmoss 500","Sim",IF(ISNA(_xlfn.XLOOKUP(_xlfn.XLOOKUP(C80,'Same Seller Hist'!E:E,'Same Seller Hist'!H:H),'Fastmoss 500'!D:D,'Fastmoss 500'!D:D)),"Não","Sim")) -> Não | O80: =IF(AND(M80="Sim",N80="Sim"),"Sim","Não") -> Não | P80: =IF(I80>K80,"Sim","Não") -> Sim | Q80: =COUNTIFS(C:C,C80) -> 1
C81: 301956567 | D81: KASPRIME.STORE | E81: =_xlfn.XLOOKUP(C81,'Same Seller Hist'!E:E,'Same Seller Hist'!I:I) -> 7.4961902e+18 | F81: =_xlfn.XLOOKUP(C81,'Same Seller Hist'!E:E,'Same Seller Hist'!H:H) -> KASPRIME | G81: CN | H81: 1412.0968 | I81: 3936.1361 | J81: =_xlfn.IFNA(_xlfn.XLOOKUP(F81,'Fastmoss 500'!D:D,'Fastmoss 500'!O:O),0) -> 0 | K81: =_xlfn.IFNA(_xlfn.XLOOKUP(F81,'Fastmoss 500'!D:D,'Fastmoss 500'!N:N),0) -> 0 | L81: Shp 500 | M81: =IF(L81="Shp 500","Sim",IF(ISNA(_xlfn.XLOOKUP(C81,'Shp 500'!D:D,'Shp 500'!D:D)),"Não","Sim")) -> Sim | N81: =IF(L81="Fastmoss 500","Sim",IF(ISNA(_xlfn.XLOOKUP(_xlfn.XLOOKUP(C81,'Same Seller Hist'!E:E,'Same Seller Hist'!H:H),'Fastmoss 500'!D:D,'Fastmoss 500'!D:D)),"Não","Sim")) -> Não | O81: =IF(AND(M81="Sim",N81="Sim"),"Sim","Não") -> Não | P81: =IF(I81>K81,"Sim","Não") -> Sim | Q81: =COUNTIFS(C:C,C81) -> 1
C82: 442506479 | D82: BRESTER MÁQUINAS E FERRAMENTAS | E82: =_xlfn.XLOOKUP(C82,'Same Seller Hist'!E:E,'Same Seller Hist'!I:I) -> 7.4961868e+18 | F82: =_xlfn.XLOOKUP(C82,'Same Seller Hist'!E:E,'Same Seller Hist'!H:H) -> Brester Brasil | G82: Lifestyle | H82: 1409.2581 | I82: 17888.047 | J82: =_xlfn.IFNA(_xlfn.XLOOKUP(F82,'Fastmoss 500'!D:D,'Fastmoss 500'!O:O),0) -> 0 | K82: =_xlfn.IFNA(_xlfn.XLOOKUP(F82,'Fastmoss 500'!D:D,'Fastmoss 500'!N:N),0) -> 0 | L82: Shp 500 | M82: =IF(L82="Shp 500","Sim",IF(ISNA(_xlfn.XLOOKUP(C82,'Shp 500'!D:D,'Shp 500'!D:D)),"Não","Sim")) -> Sim | N82: =IF(L82="Fastmoss 500","Sim",IF(ISNA(_xlfn.XLOOKUP(_xlfn.XLOOKUP(C82,'Same Seller Hist'!E:E,'Same Seller Hist'!H:H),'Fastmoss 500'!D:D,'Fastmoss 500'!D:D)),"Não","Sim")) -> Não | O82: =IF(AND(M82="Sim",N82="Sim"),"Sim","Não") -> Não | P82: =IF(I82>K82,"Sim","Não") -> Sim | Q82: =COUNTIFS(C:C,C82) -> 1
C83: 394786209 | D83: big-joia | E83: =_xlfn.XLOOKUP(C83,'Same Seller Hist'!E:E,'Same Seller Hist'!I:I) -> 7.4961791e+18 | F83: =_xlfn.XLOOKUP(C83,'Same Seller Hist'!E:E,'Same Seller Hist'!H:H) -> big-joia | G83: CN | H83: 1387.9355 | I83: 4418.7463 | J83: =_xlfn.IFNA(_xlfn.XLOOKUP(F83,'Fastmoss 500'!D:D,'Fastmoss 500'!O:O),0) -> 0 | K83: =_xlfn.IFNA(_xlfn.XLOOKUP(F83,'Fastmoss 500'!D:D,'Fastmoss 500'!N:N),0) -> 0 | L83: Shp 500 | M83: =IF(L83="Shp 500","Sim",IF(ISNA(_xlfn.XLOOKUP(C83,'Shp 500'!D:D,'Shp 500'!D:D)),"Não","Sim")) -> Sim | N83: =IF(L83="Fastmoss 500","Sim",IF(ISNA(_xlfn.XLOOKUP(_xlfn.XLOOKUP(C83,'Same Seller Hist'!E:E,'Same Seller Hist'!H:H),'Fastmoss 500'!D:D,'Fastmoss 500'!D:D)),"Não","Sim")) -> Não | O83: =IF(AND(M83="Sim",N83="Sim"),"Sim","Não") -> Não | P83: =IF(I83>K83,"Sim","Não") -> Sim | Q83: =COUNTIFS(C:C,C83) -> 1
C84: 389806204 | D84: Vancron | E84: =_xlfn.XLOOKUP(C84,'Same Seller Hist'!E:E,'Same Seller Hist'!I:I) -> 7.4942531e+18 | F84: =_xlfn.XLOOKUP(C84,'Same Seller Hist'!E:E,'Same Seller Hist'!H:H) -> Vancron | G84: CN | H84: 1380.6774 | I84: 13734.013 | J84: =_xlfn.IFNA(_xlfn.XLOOKUP(F84,'Fastmoss 500'!D:D,'Fastmoss 500'!O:O),0) -> 0 | K84: =_xlfn.IFNA(_xlfn.XLOOKUP(F84,'Fastmoss 500'!D:D,'Fastmoss 500'!N:N),0) -> 0 | L84: Shp 500 | M84: =IF(L84="Shp 500","Sim",IF(ISNA(_xlfn.XLOOKUP(C84,'Shp 500'!D:D,'Shp 500'!D:D)),"Não","Sim")) -> Sim | N84: =IF(L84="Fastmoss 500","Sim",IF(ISNA(_xlfn.XLOOKUP(_xlfn.XLOOKUP(C84,'Same Seller Hist'!E:E,'Same Seller Hist'!H:H),'Fastmoss 500'!D:D,'Fastmoss 500'!D:D)),"Não","Sim")) -> Não | O84: =IF(AND(M84="Sim",N84="Sim"),"Sim","Não") -> Não | P84: =IF(I84>K84,"Sim","Não") -> Sim | Q84: =COUNTIFS(C:C,C84) -> 1
C85: =_xlfn.XLOOKUP(F85,'Same Seller Hist'!H:H,'Same Seller Hist'!E:E) -> 400905650 | D85: =_xlfn.XLOOKUP(F85,'Same Seller Hist'!H:H,'Same Seller Hist'!D:D) -> Plenitude Distribuidora | E85: =_xlfn.XLOOKUP(F85,'Same Seller Hist'!H:H,'Same Seller Hist'!I:I) -> 7.4961866e+18 | F85: Plenitude Distribuidora | G85: =_xlfn.XLOOKUP(C85,'Same Seller Hist'!E:E,'Same Seller Hist'!F:F) -> FMCG | H85: =_xlfn.IFNA(_xlfn.XLOOKUP(C85,'Shp 500'!D:D,'Shp 500'!I:I),0) -> 1494.1613 | I85: =_xlfn.IFNA(_xlfn.XLOOKUP(C85,'Shp 500'!D:D,'Shp 500'!J:J),0) -> 11406.27 | J85: 241.93548 | K85: 12609.677 | L85: Fastmoss 500 | M85: =IF(L85="Shp 500","Sim",IF(ISNA(_xlfn.XLOOKUP(C85,'Shp 500'!D:D,'Shp 500'!D:D)),"Não","Sim")) -> Sim | N85: =IF(L85="Fastmoss 500","Sim",IF(ISNA(_xlfn.XLOOKUP(_xlfn.XLOOKUP(C85,'Same Seller Hist'!E:E,'Same Seller Hist'!H:H),'Fastmoss 500'!D:D,'Fastmoss 500'!D:D)),"Não","Sim")) -> Sim | O85: =IF(AND(M85="Sim",N85="Sim"),"Sim","Não") -> Sim | P85: =IF(I85>K85,"Sim","Não") -> Não | Q85: =COUNTIFS(C:C,C85) -> 2
C86: 1099068336 | D86: Estou_Crescendo | E86: =_xlfn.XLOOKUP(C86,'Same Seller Hist'!E:E,'Same Seller Hist'!I:I) -> 7.4961819e+18 | F86: =_xlfn.XLOOKUP(C86,'Same Seller Hist'!E:E,'Same Seller Hist'!H:H) -> Estou Crescendo | G86: ELHA | H86: 1371.7097 | I86: 7936.3227 | J86: =_xlfn.IFNA(_xlfn.XLOOKUP(F86,'Fastmoss 500'!D:D,'Fastmoss 500'!O:O),0) -> 0 | K86: =_xlfn.IFNA(_xlfn.XLOOKUP(F86,'Fastmoss 500'!D:D,'Fastmoss 500'!N:N),0) -> 0 | L86: Shp 500 | M86: =IF(L86="Shp 500","Sim",IF(ISNA(_xlfn.XLOOKUP(C86,'Shp 500'!D:D,'Shp 500'!D:D)),"Não","Sim")) -> Sim | N86: =IF(L86="Fastmoss 500","Sim",IF(ISNA(_xlfn.XLOOKUP(_xlfn.XLOOKUP(C86,'Same Seller Hist'!E:E,'Same Seller Hist'!H:H),'Fastmoss 500'!D:D,'Fastmoss 500'!D:D)),"Não","Sim")) -> Não | O86: =IF(AND(M86="Sim",N86="Sim"),"Sim","Não") -> Não | P86: =IF(I86>K86,"Sim","Não") -> Sim | Q86: =COUNTIFS(C:C,C86) -> 1
C87: 401609924 | D87: ALICE BEAUTY | E87: =_xlfn.XLOOKUP(C87,'Same Seller Hist'!E:E,'Same Seller Hist'!I:I) -> 7.4961822e+18 | F87: =_xlfn.XLOOKUP(C87,'Same Seller Hist'!E:E,'Same Seller Hist'!H:H) -> ALICE BEAUTY BR | G87: CN | H87: 960.03226 | I87: 4019.7777 | J87: =_xlfn.IFNA(_xlfn.XLOOKUP(F87,'Fastmoss 500'!D:D,'Fastmoss 500'!O:O),0) -> 319.35484 | K87: =_xlfn.IFNA(_xlfn.XLOOKUP(F87,'Fastmoss 500'!D:D,'Fastmoss 500'!N:N),0) -> 8648.3871 | L87: Shp 500 | M87: =IF(L87="Shp 500","Sim",IF(ISNA(_xlfn.XLOOKUP(C87,'Shp 500'!D:D,'Shp 500'!D:D)),"Não","Sim")) -> Sim | N87: =IF(L87="Fastmoss 500","Sim",IF(ISNA(_xlfn.XLOOKUP(_xlfn.XLOOKUP(C87,'Same Seller Hist'!E:E,'Same Seller Hist'!H:H),'Fastmoss 500'!D:D,'Fastmoss 500'!D:D)),"Não","Sim")) -> Sim | O87: =IF(AND(M87="Sim",N87="Sim"),"Sim","Não") -> Sim | P87: =IF(I87>K87,"Sim","Não") -> Não | Q87: =COUNTIFS(C:C,C87) -> 2
C88: =_xlfn.XLOOKUP(F88,'Same Seller Hist'!H:H,'Same Seller Hist'!E:E) -> 401609924 | D88: =_xlfn.XLOOKUP(F88,'Same Seller Hist'!H:H,'Same Seller Hist'!D:D) -> ALICE BEAUTY BR | E88: =_xlfn.XLOOKUP(F88,'Same Seller Hist'!H:H,'Same Seller Hist'!I:I) -> 7.4961822e+18 | F88: ALICE BEAUTY BR | G88: =_xlfn.XLOOKUP(C88,'Same Seller Hist'!E:E,'Same Seller Hist'!F:F) -> FMCG | H88: =_xlfn.IFNA(_xlfn.XLOOKUP(C88,'Shp 500'!D:D,'Shp 500'!I:I),0) -> 960.03226 | I88: =_xlfn.IFNA(_xlfn.XLOOKUP(C88,'Shp 500'!D:D,'Shp 500'!J:J),0) -> 4019.7777 | J88: 319.35484 | K88: 8648.3871 | L88: Fastmoss 500 | M88: =IF(L88="Shp 500","Sim",IF(ISNA(_xlfn.XLOOKUP(C88,'Shp 500'!D:D,'Shp 500'!D:D)),"Não","Sim")) -> Sim | N88: =IF(L88="Fastmoss 500","Sim",IF(ISNA(_xlfn.XLOOKUP(_xlfn.XLOOKUP(C88,'Same Seller Hist'!E:E,'Same Seller Hist'!H:H),'Fastmoss 500'!D:D,'Fastmoss 500'!D:D)),"Não","Sim")) -> Sim | O88: =IF(AND(M88="Sim",N88="Sim"),"Sim","Não") -> Sim | P88: =IF(I88>K88,"Sim","Não") -> Não | Q88: =COUNTIFS(C:C,C88) -> 2
C89: 1033215079 | D89: HerberT Eletrônico | E89: =_xlfn.XLOOKUP(C89,'Same Seller Hist'!E:E,'Same Seller Hist'!I:I) -> 7.4961622e+18 | F89: =_xlfn.XLOOKUP(C89,'Same Seller Hist'!E:E,'Same Seller Hist'!H:H) -> HerberT TK | G89: CN | H89: 1339.8065 | I89: 11320.565 | J89: =_xlfn.IFNA(_xlfn.XLOOKUP(F89,'Fastmoss 500'!D:D,'Fastmoss 500'!O:O),0) -> 0 | K89: =_xlfn.IFNA(_xlfn.XLOOKUP(F89,'Fastmoss 500'!D:D,'Fastmoss 500'!N:N),0) -> 0 | L89: Shp 500 | M89: =IF(L89="Shp 500","Sim",IF(ISNA(_xlfn.XLOOKUP(C89,'Shp 500'!D:D,'Shp 500'!D:D)),"Não","Sim")) -> Sim | N89: =IF(L89="Fastmoss 500","Sim",IF(ISNA(_xlfn.XLOOKUP(_xlfn.XLOOKUP(C89,'Same Seller Hist'!E:E,'Same Seller Hist'!H:H),'Fastmoss 500'!D:D,'Fastmoss 500'!D:D)),"Não","Sim")) -> Não | O89: =IF(AND(M89="Sim",N89="Sim"),"Sim","Não") -> Não | P89: =IF(I89>K89,"Sim","Não") -> Sim | Q89: =COUNTIFS(C:C,C89) -> 1
C90: 359240167 | D90: RIO ATACADÃO | E90: =_xlfn.XLOOKUP(C90,'Same Seller Hist'!E:E,'Same Seller Hist'!I:I) -> 7.4961821e+18 | F90: =_xlfn.XLOOKUP(C90,'Same Seller Hist'!E:E,'Same Seller Hist'!H:H) -> RIO BAZAR ATACADO | G90: CN | H90: 1335.2258 | I90: 5283.6509 | J90: =_xlfn.IFNA(_xlfn.XLOOKUP(F90,'Fastmoss 500'!D:D,'Fastmoss 500'!O:O),0) -> 0 | K90: =_xlfn.IFNA(_xlfn.XLOOKUP(F90,'Fastmoss 500'!D:D,'Fastmoss 500'!N:N),0) -> 0 | L90: Shp 500 | M90: =IF(L90="Shp 500","Sim",IF(ISNA(_xlfn.XLOOKUP(C90,'Shp 500'!D:D,'Shp 500'!D:D)),"Não","Sim")) -> Sim | N90: =IF(L90="Fastmoss 500","Sim",IF(ISNA(_xlfn.XLOOKUP(_xlfn.XLOOKUP(C90,'Same Seller Hist'!E:E,'Same Seller Hist'!H:H),'Fastmoss 500'!D:D,'Fastmoss 500'!D:D)),"Não","Sim")) -> Não | O90: =IF(AND(M90="Sim",N90="Sim"),"Sim","Não") -> Não | P90: =IF(I90>K90,"Sim","Não") -> Sim | Q90: =COUNTIFS(C:C,C90) -> 1
C91: 406098813 | D91: bo.store | E91: =_xlfn.XLOOKUP(C91,'Same Seller Hist'!E:E,'Same Seller Hist'!I:I) -> 7.4962608e+18 | F91: =_xlfn.XLOOKUP(C91,'Same Seller Hist'!E:E,'Same Seller Hist'!H:H) -> Fbo.store | G91: CN | H91: 877.67742 | I91: 8582.4832 | J91: =_xlfn.IFNA(_xlfn.XLOOKUP(F91,'Fastmoss 500'!D:D,'Fastmoss 500'!O:O),0) -> 361.29032 | K91: =_xlfn.IFNA(_xlfn.XLOOKUP(F91,'Fastmoss 500'!D:D,'Fastmoss 500'!N:N),0) -> 12112.903 | L91: Shp 500 | M91: =IF(L91="Shp 500","Sim",IF(ISNA(_xlfn.XLOOKUP(C91,'Shp 500'!D:D,'Shp 500'!D:D)),"Não","Sim")) -> Sim | N91: =IF(L91="Fastmoss 500","Sim",IF(ISNA(_xlfn.XLOOKUP(_xlfn.XLOOKUP(C91,'Same Seller Hist'!E:E,'Same Seller Hist'!H:H),'Fastmoss 500'!D:D,'Fastmoss 500'!D:D)),"Não","Sim")) -> Sim | O91: =IF(AND(M91="Sim",N91="Sim"),"Sim","Não") -> Sim | P91: =IF(I91>K91,"Sim","Não") -> Não | Q91: =COUNTIFS(C:C,C91) -> 2
C92: 445163047 | D92: Domus | E92: =_xlfn.XLOOKUP(C92,'Same Seller Hist'!E:E,'Same Seller Hist'!I:I) -> 7.4941997e+18 | F92: =_xlfn.XLOOKUP(C92,'Same Seller Hist'!E:E,'Same Seller Hist'!H:H) -> Domus Utilidades | G92: Lifestyle | H92: 1289.5161 | I92: 37754.633 | J92: =_xlfn.IFNA(_xlfn.XLOOKUP(F92,'Fastmoss 500'!D:D,'Fastmoss 500'!O:O),0) -> 0 | K92: =_xlfn.IFNA(_xlfn.XLOOKUP(F92,'Fastmoss 500'!D:D,'Fastmoss 500'!N:N),0) -> 0 | L92: Shp 500 | M92: =IF(L92="Shp 500","Sim",IF(ISNA(_xlfn.XLOOKUP(C92,'Shp 500'!D:D,'Shp 500'!D:D)),"Não","Sim")) -> Sim | N92: =IF(L92="Fastmoss 500","Sim",IF(ISNA(_xlfn.XLOOKUP(_xlfn.XLOOKUP(C92,'Same Seller Hist'!E:E,'Same Seller Hist'!H:H),'Fastmoss 500'!D:D,'Fastmoss 500'!D:D)),"Não","Sim")) -> Não | O92: =IF(AND(M92="Sim",N92="Sim"),"Sim","Não") -> Não | P92: =IF(I92>K92,"Sim","Não") -> Sim | Q92: =COUNTIFS(C:C,C92) -> 1
C93: 1278493331 | D93: CASA FULL | E93: =_xlfn.XLOOKUP(C93,'Same Seller Hist'!E:E,'Same Seller Hist'!I:I) -> 7.4941169e+18 | F93: =_xlfn.XLOOKUP(C93,'Same Seller Hist'!E:E,'Same Seller Hist'!H:H) -> Casa Full Utilidades Ltda | G93: CN | H93: 1278.129 | I93: 6577.2765 | J93: =_xlfn.IFNA(_xlfn.XLOOKUP(F93,'Fastmoss 500'!D:D,'Fastmoss 500'!O:O),0) -> 0 | K93: =_xlfn.IFNA(_xlfn.XLOOKUP(F93,'Fastmoss 500'!D:D,'Fastmoss 500'!N:N),0) -> 0 | L93: Shp 500 | M93: =IF(L93="Shp 500","Sim",IF(ISNA(_xlfn.XLOOKUP(C93,'Shp 500'!D:D,'Shp 500'!D:D)),"Não","Sim")) -> Sim | N93: =IF(L93="Fastmoss 500","Sim",IF(ISNA(_xlfn.XLOOKUP(_xlfn.XLOOKUP(C93,'Same Seller Hist'!E:E,'Same Seller Hist'!H:H),'Fastmoss 500'!D:D,'Fastmoss 500'!D:D)),"Não","Sim")) -> Não | O93: =IF(AND(M93="Sim",N93="Sim"),"Sim","Não") -> Não | P93: =IF(I93>K93,"Sim","Não") -> Sim | Q93: =COUNTIFS(C:C,C93) -> 1
C94: 570502401 | D94: Vest Bela Lingerie | E94: =_xlfn.XLOOKUP(C94,'Same Seller Hist'!E:E,'Same Seller Hist'!I:I) -> 7.4942185e+18 | F94: =_xlfn.XLOOKUP(C94,'Same Seller Hist'!E:E,'Same Seller Hist'!H:H) -> Bella Veste Moda Shop | G94: Fashion | H94: 1266.5161 | I94: 4357.185 | J94: =_xlfn.IFNA(_xlfn.XLOOKUP(F94,'Fastmoss 500'!D:D,'Fastmoss 500'!O:O),0) -> 0 | K94: =_xlfn.IFNA(_xlfn.XLOOKUP(F94,'Fastmoss 500'!D:D,'Fastmoss 500'!N:N),0) -> 0 | L94: Shp 500 | M94: =IF(L94="Shp 500","Sim",IF(ISNA(_xlfn.XLOOKUP(C94,'Shp 500'!D:D,'Shp 500'!D:D)),"Não","Sim")) -> Sim | N94: =IF(L94="Fastmoss 500","Sim",IF(ISNA(_xlfn.XLOOKUP(_xlfn.XLOOKUP(C94,'Same Seller Hist'!E:E,'Same Seller Hist'!H:H),'Fastmoss 500'!D:D,'Fastmoss 500'!D:D)),"Não","Sim")) -> Não | O94: =IF(AND(M94="Sim",N94="Sim"),"Sim","Não") -> Não | P94: =IF(I94>K94,"Sim","Não") -> Sim | Q94: =COUNTIFS(C:C,C94) -> 1
C95: 436723291 | D95: DUDUSHOP OFICIAL | E95: =_xlfn.XLOOKUP(C95,'Same Seller Hist'!E:E,'Same Seller Hist'!I:I) -> 7.496182e+18 | F95: =_xlfn.XLOOKUP(C95,'Same Seller Hist'!E:E,'Same Seller Hist'!H:H) -> DUDUSHOP BR | G95: FMCG | H95: 1249.5161 | I95: 7577.0929 | J95: =_xlfn.IFNA(_xlfn.XLOOKUP(F95,'Fastmoss 500'!D:D,'Fastmoss 500'!O:O),0) -> 0 | K95: =_xlfn.IFNA(_xlfn.XLOOKUP(F95,'Fastmoss 500'!D:D,'Fastmoss 500'!N:N),0) -> 0 | L95: Shp 500 | M95: =IF(L95="Shp 500","Sim",IF(ISNA(_xlfn.XLOOKUP(C95,'Shp 500'!D:D,'Shp 500'!D:D)),"Não","Sim")) -> Sim | N95: =IF(L95="Fastmoss 500","Sim",IF(ISNA(_xlfn.XLOOKUP(_xlfn.XLOOKUP(C95,'Same Seller Hist'!E:E,'Same Seller Hist'!H:H),'Fastmoss 500'!D:D,'Fastmoss 500'!D:D)),"Não","Sim")) -> Não | O95: =IF(AND(M95="Sim",N95="Sim"),"Sim","Não") -> Não | P95: =IF(I95>K95,"Sim","Não") -> Sim | Q95: =COUNTIFS(C:C,C95) -> 1
C96: 376022922 | D96: Selfridge.store | E96: =_xlfn.XLOOKUP(C96,'Same Seller Hist'!E:E,'Same Seller Hist'!I:I) -> 7.4962392e+18 | F96: =_xlfn.XLOOKUP(C96,'Same Seller Hist'!E:E,'Same Seller Hist'!H:H) -> Selfridge.Store.BR | G96: CN | H96: 1240.8387 | I96: 7320.8881 | J96: =_xlfn.IFNA(_xlfn.XLOOKUP(F96,'Fastmoss 500'!D:D,'Fastmoss 500'!O:O),0) -> 0 | K96: =_xlfn.IFNA(_xlfn.XLOOKUP(F96,'Fastmoss 500'!D:D,'Fastmoss 500'!N:N),0) -> 0 | L96: Shp 500 | M96: =IF(L96="Shp 500","Sim",IF(ISNA(_xlfn.XLOOKUP(C96,'Shp 500'!D:D,'Shp 500'!D:D)),"Não","Sim")) -> Sim | N96: =IF(L96="Fastmoss 500","Sim",IF(ISNA(_xlfn.XLOOKUP(_xlfn.XLOOKUP(C96,'Same Seller Hist'!E:E,'Same Seller Hist'!H:H),'Fastmoss 500'!D:D,'Fastmoss 500'!D:D)),"Não","Sim")) -> Não | O96: =IF(AND(M96="Sim",N96="Sim"),"Sim","Não") -> Não | P96: =IF(I96>K96,"Sim","Não") -> Sim | Q96: =COUNTIFS(C:C,C96) -> 1
C97: 502619181 | D97: NIVEA OFICIAL | E97: =_xlfn.XLOOKUP(C97,'Same Seller Hist'!E:E,'Same Seller Hist'!I:I) -> 7.4961832e+18 | F97: =_xlfn.XLOOKUP(C97,'Same Seller Hist'!E:E,'Same Seller Hist'!H:H) -> NIVEA Brasil | G97: FMCG | H97: 1200.4516 | I97: 7160.856 | J97: =_xlfn.IFNA(_xlfn.XLOOKUP(F97,'Fastmoss 500'!D:D,'Fastmoss 500'!O:O),0) -> 0 | K97: =_xlfn.IFNA(_xlfn.XLOOKUP(F97,'Fastmoss 500'!D:D,'Fastmoss 500'!N:N),0) -> 0 | L97: Shp 500 | M97: =IF(L97="Shp 500","Sim",IF(ISNA(_xlfn.XLOOKUP(C97,'Shp 500'!D:D,'Shp 500'!D:D)),"Não","Sim")) -> Sim | N97: =IF(L97="Fastmoss 500","Sim",IF(ISNA(_xlfn.XLOOKUP(_xlfn.XLOOKUP(C97,'Same Seller Hist'!E:E,'Same Seller Hist'!H:H),'Fastmoss 500'!D:D,'Fastmoss 500'!D:D)),"Não","Sim")) -> Não | O97: =IF(AND(M97="Sim",N97="Sim"),"Sim","Não") -> Não | P97: =IF(I97>K97,"Sim","Não") -> Sim | Q97: =COUNTIFS(C:C,C97) -> 1
C98: 298953477 | D98: PALUECOM | E98: =_xlfn.XLOOKUP(C98,'Same Seller Hist'!E:E,'Same Seller Hist'!I:I) -> 7.4961873e+18 | F98: =_xlfn.XLOOKUP(C98,'Same Seller Hist'!E:E,'Same Seller Hist'!H:H) -> PALU ECOM | G98: FMCG | H98: 1182.2258 | I98: 7398.579 | J98: =_xlfn.IFNA(_xlfn.XLOOKUP(F98,'Fastmoss 500'!D:D,'Fastmoss 500'!O:O),0) -> 0 | K98: =_xlfn.IFNA(_xlfn.XLOOKUP(F98,'Fastmoss 500'!D:D,'Fastmoss 500'!N:N),0) -> 0 | L98: Shp 500 | M98: =IF(L98="Shp 500","Sim",IF(ISNA(_xlfn.XLOOKUP(C98,'Shp 500'!D:D,'Shp 500'!D:D)),"Não","Sim")) -> Sim | N98: =IF(L98="Fastmoss 500","Sim",IF(ISNA(_xlfn.XLOOKUP(_xlfn.XLOOKUP(C98,'Same Seller Hist'!E:E,'Same Seller Hist'!H:H),'Fastmoss 500'!D:D,'Fastmoss 500'!D:D)),"Não","Sim")) -> Não | O98: =IF(AND(M98="Sim",N98="Sim"),"Sim","Não") -> Não | P98: =IF(I98>K98,"Sim","Não") -> Sim | Q98: =COUNTIFS(C:C,C98) -> 1
C99: 1165620003 | D99: Hello Look Here | E99: =_xlfn.XLOOKUP(C99,'Same Seller Hist'!E:E,'Same Seller Hist'!I:I) -> 0 | F99: =_xlfn.XLOOKUP(C99,'Same Seller Hist'!E:E,'Same Seller Hist'!H:H) -> 0 | G99: ELHA | H99: 1178.4516 | I99: 6066.4722 | J99: =_xlfn.IFNA(_xlfn.XLOOKUP(F99,'Fastmoss 500'!D:D,'Fastmoss 500'!O:O),0) -> 0 | K99: =_xlfn.IFNA(_xlfn.XLOOKUP(F99,'Fastmoss 500'!D:D,'Fastmoss 500'!N:N),0) -> 0 | L99: Shp 500 | M99: =IF(L99="Shp 500","Sim",IF(ISNA(_xlfn.XLOOKUP(C99,'Shp 500'!D:D,'Shp 500'!D:D)),"Não","Sim")) -> Sim | N99: =IF(L99="Fastmoss 500","Sim",IF(ISNA(_xlfn.XLOOKUP(_xlfn.XLOOKUP(C99,'Same Seller Hist'!E:E,'Same Seller Hist'!H:H),'Fastmoss 500'!D:D,'Fastmoss 500'!D:D)),"Não","Sim")) -> Não | O99: =IF(AND(M99="Sim",N99="Sim"),"Sim","Não") -> Não | P99: =IF(I99>K99,"Sim","Não") -> Sim | Q99: =COUNTIFS(C:C,C99) -> 1
C100: 352674932 | D100: LEVE HOME | E100: =_xlfn.XLOOKUP(C100,'Same Seller Hist'!E:E,'Same Seller Hist'!I:I) -> 7.4961634e+18 | F100: =_xlfn.XLOOKUP(C100,'Same Seller Hist'!E:E,'Same Seller Hist'!H:H) -> LEVE HOME | G100: CN | H100: 1174.6452 | I100: 6858.6248 | J100: =_xlfn.IFNA(_xlfn.XLOOKUP(F100,'Fastmoss 500'!D:D,'Fastmoss 500'!O:O),0) -> 0 | K100: =_xlfn.IFNA(_xlfn.XLOOKUP(F100,'Fastmoss 500'!D:D,'Fastmoss 500'!N:N),0) -> 0 | L100: Shp 500 | M100: =IF(L100="Shp 500","Sim",IF(ISNA(_xlfn.XLOOKUP(C100,'Shp 500'!D:D,'Shp 500'!D:D)),"Não","Sim")) -> Sim | N100: =IF(L100="Fastmoss 500","Sim",IF(ISNA(_xlfn.XLOOKUP(_xlfn.XLOOKUP(C100,'Same Seller Hist'!E:E,'Same Seller Hist'!H:H),'Fastmoss 500'!D:D,'Fastmoss 500'!D:D)),"Não","Sim")) -> Não | O100: =IF(AND(M100="Sim",N100="Sim"),"Sim","Não") -> Não | P100: =IF(I100>K100,"Sim","Não") -> Sim | Q100: =COUNTIFS(C:C,C100) -> 1
... C108: 1023760886 | D108: petpremier | E108: =_xlfn.XLOOKUP(C108,'Same Seller Hist'!E:E,'Same Seller Hist'!I:I) -> 7.4961864e+18 | F108: =_xlfn.XLOOKUP(C108,'Same Seller Hist'!E:E,'Same Seller Hist'!H:H) -> Petpremier | G108: FMCG | H108: 1136.8065 | I108: 18020.796 | J108: =_xlfn.IFNA(_xlfn.XLOOKUP(F108,'Fastmoss 500'!D:D,'Fastmoss 500'!O:O),0) -> 0 | K108: =_xlfn.IFNA(_xlfn.XLOOKUP(F108,'Fastmoss 500'!D:D,'Fastmoss 500'!N:N),0) -> 0 | L108: Shp 500 | M108: =IF(L108="Shp 500","Sim",IF(ISNA(_xlfn.XLOOKUP(C108,'Shp 500'!D:D,'Shp 500'!D:D)),"Não","Sim")) -> Sim | N108: =IF(L108="Fastmoss 500","Sim",IF(ISNA(_xlfn.XLOOKUP(_xlfn.XLOOKUP(C108,'Same Seller Hist'!E:E,'Same Seller Hist'!H:H),'Fastmoss 500'!D:D,'Fastmoss 500'!D:D)),"Não","Sim")) -> Não | O108: =IF(AND(M108="Sim",N108="Sim"),"Sim","Não") -> Não | P108: =IF(I108>K108,"Sim","Não") -> Sim | Q108: =COUNTIFS(C:C,C108) -> 1
C109: =_xlfn.XLOOKUP(F109,'Same Seller Hist'!H:H,'Same Seller Hist'!E:E) -> 406098813 | D109: =_xlfn.XLOOKUP(F109,'Same Seller Hist'!H:H,'Same Seller Hist'!D:D) -> Fbo.store | E109: =_xlfn.XLOOKUP(F109,'Same Seller Hist'!H:H,'Same Seller Hist'!I:I) -> 7.4962608e+18 | F109: Fbo.store | G109: =_xlfn.XLOOKUP(C109,'Same Seller Hist'!E:E,'Same Seller Hist'!F:F) -> Lifestyle | H109: =_xlfn.IFNA(_xlfn.XLOOKUP(C109,'Shp 500'!D:D,'Shp 500'!I:I),0) -> 877.67742 | I109: =_xlfn.IFNA(_xlfn.XLOOKUP(C109,'Shp 500'!D:D,'Shp 500'!J:J),0) -> 8582.4832 | J109: 361.29032 | K109: 12112.903 | L109: Fastmoss 500 | M109: =IF(L109="Shp 500","Sim",IF(ISNA(_xlfn.XLOOKUP(C109,'Shp 500'!D:D,'Shp 500'!D:D)),"Não","Sim")) -> Sim | N109: =IF(L109="Fastmoss 500","Sim",IF(ISNA(_xlfn.XLOOKUP(_xlfn.XLOOKUP(C109,'Same Seller Hist'!E:E,'Same Seller Hist'!H:H),'Fastmoss 500'!D:D,'Fastmoss 500'!D:D)),"Não","Sim")) -> Sim | O109: =IF(AND(M109="Sim",N109="Sim"),"Sim","Não") -> Sim | P109: =IF(I109>K109,"Sim","Não") -> Não | Q109: =COUNTIFS(C:C,C109) -> 2
C110: 409164022 | D110: Neverdie Store | E110: =_xlfn.XLOOKUP(C110,'Same Seller Hist'!E:E,'Same Seller Hist'!I:I) -> 7.4961532e+18 | F110: =_xlfn.XLOOKUP(C110,'Same Seller Hist'!E:E,'Same Seller Hist'!H:H) -> Neverdie Store.br | G110: CN | H110: 2243.4516 | I110: 11390.064 | J110: =_xlfn.IFNA(_xlfn.XLOOKUP(F110,'Fastmoss 500'!D:D,'Fastmoss 500'!O:O),0) -> 1741.9355 | K110: =_xlfn.IFNA(_xlfn.XLOOKUP(F110,'Fastmoss 500'!D:D,'Fastmoss 500'!N:N),0) -> 32258.065 | L110: Shp 500 | M110: =IF(L110="Shp 500","Sim",IF(ISNA(_xlfn.XLOOKUP(C110,'Shp 500'!D:D,'Shp 500'!D:D)),"Não","Sim")) -> Sim | N110: =IF(L110="Fastmoss 500","Sim",IF(ISNA(_xlfn.XLOOKUP(_xlfn.XLOOKUP(C110,'Same Seller Hist'!E:E,'Same Seller Hist'!H:H),'Fastmoss 500'!D:D,'Fastmoss 500'!D:D)),"Não","Sim")) -> Sim | O110: =IF(AND(M110="Sim",N110="Sim"),"Sim","Não") -> Sim | P110: =IF(I110>K110,"Sim","Não") -> Não | Q110: =COUNTIFS(C:C,C110) -> 2
C111: =_xlfn.XLOOKUP(F111,'Same Seller Hist'!H:H,'Same Seller Hist'!E:E) -> 409164022 | D111: =_xlfn.XLOOKUP(F111,'Same Seller Hist'!H:H,'Same Seller Hist'!D:D) -> Neverdie Store.br | E111: =_xlfn.XLOOKUP(F111,'Same Seller Hist'!H:H,'Same Seller Hist'!I:I) -> 7.4961532e+18 | F111: Neverdie Store.br | G111: =_xlfn.XLOOKUP(C111,'Same Seller Hist'!E:E,'Same Seller Hist'!F:F) -> Lifestyle | H111: =_xlfn.IFNA(_xlfn.XLOOKUP(C111,'Shp 500'!D:D,'Shp 500'!I:I),0) -> 2243.4516 | I111: =_xlfn.IFNA(_xlfn.XLOOKUP(C111,'Shp 500'!D:D,'Shp 500'!J:J),0) -> 11390.064 | J111: 1741.9355 | K111: 32258.065 | L111: Fastmoss 500 | M111: =IF(L111="Shp 500","Sim",IF(ISNA(_xlfn.XLOOKUP(C111,'Shp 500'!D:D,'Shp 500'!D:D)),"Não","Sim")) -> Sim | N111: =IF(L111="Fastmoss 500","Sim",IF(ISNA(_xlfn.XLOOKUP(_xlfn.XLOOKUP(C111,'Same Seller Hist'!E:E,'Same Seller Hist'!H:H),'Fastmoss 500'!D:D,'Fastmoss 500'!D:D)),"Não","Sim")) -> Sim | O111: =IF(AND(M111="Sim",N111="Sim"),"Sim","Não") -> Sim | P111: =IF(I111>K111,"Sim","Não") -> Não | Q111: =COUNTIFS(C:C,C111) -> 2
C112: 413762733 | D112: ALAN.FONTE.888 | E112: =_xlfn.XLOOKUP(C112,'Same Seller Hist'!E:E,'Same Seller Hist'!I:I) -> 7.4961624e+18 | F112: =_xlfn.XLOOKUP(C112,'Same Seller Hist'!E:E,'Same Seller Hist'!H:H) -> ALAN FONTE | G112: CN | H112: 1043.1613 | I112: 12148.092 | J112: =_xlfn.IFNA(_xlfn.XLOOKUP(F112,'Fastmoss 500'!D:D,'Fastmoss 500'!O:O),0) -> 280.64516 | K112: =_xlfn.IFNA(_xlfn.XLOOKUP(F112,'Fastmoss 500'!D:D,'Fastmoss 500'!N:N),0) -> 14412.903 | L112: Shp 500 | M112: =IF(L112="Shp 500","Sim",IF(ISNA(_xlfn.XLOOKUP(C112,'Shp 500'!D:D,'Shp 500'!D:D)),"Não","Sim")) -> Sim | N112: =IF(L112="Fastmoss 500","Sim",IF(ISNA(_xlfn.XLOOKUP(_xlfn.XLOOKUP(C112,'Same Seller Hist'!E:E,'Same Seller Hist'!H:H),'Fastmoss 500'!D:D,'Fastmoss 500'!D:D)),"Não","Sim")) -> Sim | O112: =IF(AND(M112="Sim",N112="Sim"),"Sim","Não") -> Sim | P112: =IF(I112>K112,"Sim","Não") -> Não | Q112: =COUNTIFS(C:C,C112) -> 2
...

Sheet Validate

Sheet TTS to Shp
B3: From TTS to Shopee (Input do Kaique)
B4: Mes atual
C7: grass_month | D7: shop_name_tts | E7: shop_id_tts | F7: category | G7: adnmv_usd_tts | H7: net_ado_tts | I7: match | J7: shop_name_shp | K7: shop_id_shp

Sheet Shp to TTS
B3: From Shopee to TTS (Input do Kaique)
B4: Mes atual
C7: grass_month | D7: shop_name_shp | E7: shop_id_shp | F7: category | G7: adnmv_usd_shp | H7: net_ado_shp | I7: match | J7: ação | K7: shop_name_tts | L7: shop_id_tts | M7: vendas (não é ado) | N7: receita (não é adnmv_usd)

Sheet Shp 500
B3: TOP-500 SELLERS FASTMOSS
C7: grass_month | D7: shop_id | E7: shop_name | F7: cluster | G7: is_chinese_seller | H7: is_managed_seller | I7: net_ado | J7: net_adnmv_usd | K7: rank_ado | L7: match | M7: atividade
C8: 45992 | D8: 1006215031 | E8: Choice Oficial | F8: Fashion | G8: 0 | H8: 1 | I8: 77674.774 | J8: 286189.98 | K8: 1 | L8: =IF(ISNA(_xlfn.XLOOKUP(D8,'Same Seller Hist'!E:E,'Same Seller Hist'!E:E)),"Não","Sim") -> Não | M8: =_xlfn.IFNA(_xlfn.XLOOKUP(D8,'Same Seller Hist'!E:E,'Same Seller Hist'!M:M),"Não Match") -> Não Match
C9: 45992 | D9: 391739739 | E9: ANJ.GG store | F9: CN | G9: 1 | H9: 1 | I9: 6695.3226 | J9: 52809.985 | K9: 2 | L9: =IF(ISNA(_xlfn.XLOOKUP(D9,'Same Seller Hist'!E:E,'Same Seller Hist'!E:E)),"Não","Sim") -> Sim | M9: =_xlfn.IFNA(_xlfn.XLOOKUP(D9,'Same Seller Hist'!E:E,'Same Seller Hist'!M:M),"Não Match") -> Ativo
C10: 45992 | D10: 616222685 | E10: Salon Line | F10: FMCG | G10: 0 | H10: 1 | I10: 5865.1935 | J10: 37595.714 | K10: 3 | L10: =IF(ISNA(_xlfn.XLOOKUP(D10,'Same Seller Hist'!E:E,'Same Seller Hist'!E:E)),"Não","Sim") -> Sim | M10: =_xlfn.IFNA(_xlfn.XLOOKUP(D10,'Same Seller Hist'!E:E,'Same Seller Hist'!M:M),"Não Match") -> Ativo
C11: 45992 | D11: 426378412 | E11: Lovito Loja Oficial | F11: Fashion | G11: 0 | H11: 0 | I11: 5217.5484 | J11: 50635.703 | K11: 4 | L11: =IF(ISNA(_xlfn.XLOOKUP(D11,'Same Seller Hist'!E:E,'Same Seller Hist'!E:E)),"Não","Sim") -> Não | M11: =_xlfn.IFNA(_xlfn.XLOOKUP(D11,'Same Seller Hist'!E:E,'Same Seller Hist'!M:M),"Não Match") -> Não Match
C12: 45992 | D12: 552896405 | E12: Casa_Completa_Enxovais | F12: Lifestyle | G12: 0 | H12: 1 | I12: 5043.8387 | J12: 53289.304 | K12: 5 | L12: =IF(ISNA(_xlfn.XLOOKUP(D12,'Same Seller Hist'!E:E,'Same Seller Hist'!E:E)),"Não","Sim") -> Sim | M12: =_xlfn.IFNA(_xlfn.XLOOKUP(D12,'Same Seller Hist'!E:E,'Same Seller Hist'!M:M),"Não Match") -> Ativo
C13: 45992 | D13: 974102638 | E13: Loja 128 | F13: CN | G13: 1 | H13: 1 | I13: 4870.1613 | J13: 49065.871 | K13: 6 | L13: =IF(ISNA(_xlfn.XLOOKUP(D13,'Same Seller Hist'!E:E,'Same Seller Hist'!E:E)),"Não","Sim") -> Sim | M13: =_xlfn.IFNA(_xlfn.XLOOKUP(D13,'Same Seller Hist'!E:E,'Same Seller Hist'!M:M),"Não Match") -> Ativo
C14: 45992 | D14: 400311012 | E14: Marisa.store | F14: CN | G14: 1 | H14: 1 | I14: 4771.9677 | J14: 26969.905 | K14: 7 | L14: =IF(ISNA(_xlfn.XLOOKUP(D14,'Same Seller Hist'!E:E,'Same Seller Hist'!E:E)),"Não","Sim") -> Não | M14: =_xlfn.IFNA(_xlfn.XLOOKUP(D14,'Same Seller Hist'!E:E,'Same Seller Hist'!M:M),"Não Match") -> Não Match
C15: 45992 | D15: 526625785 | E15: Ming.store | F15: CN | G15: 1 | H15: 1 | I15: 4614.4839 | J15: 32376.695 | K15: 8 | L15: =IF(ISNA(_xlfn.XLOOKUP(D15,'Same Seller Hist'!E:E,'Same Seller Hist'!E:E)),"Não","Sim") -> Não | M15: =_xlfn.IFNA(_xlfn.XLOOKUP(D15,'Same Seller Hist'!E:E,'Same Seller Hist'!M:M),"Não Match") -> Não Match
C16: 45992 | D16: 811879342 | E16: Britânia Oficial | F16: ELHA | G16: 0 | H16: 1 | I16: 4605.871 | J16: 117662.57 | K16: 9 | L16: =IF(ISNA(_xlfn.XLOOKUP(D16,'Same Seller Hist'!E:E,'Same Seller Hist'!E:E)),"Não","Sim") -> Não | M16: =_xlfn.IFNA(_xlfn.XLOOKUP(D16,'Same Seller Hist'!E:E,'Same Seller Hist'!M:M),"Não Match") -> Não Match
C17: 45992 | D17: 362859393 | E17: ALFA MERCEARIA.BR | F17: CN | G17: 1 | H17: 0 | I17: 4604.9355 | J17: 14928.731 | K17: 10 | L17: =IF(ISNA(_xlfn.XLOOKUP(D17,'Same Seller Hist'!E:E,'Same Seller Hist'!E:E)),"Não","Sim") -> Sim | M17: =_xlfn.IFNA(_xlfn.XLOOKUP(D17,'Same Seller Hist'!E:E,'Same Seller Hist'!M:M),"Não Match") -> Ativo
C18: 45992 | D18: 455834389 | E18: CHOCOBRAZ EMBALAGENS | F18: FMCG | G18: 0 | H18: 1 | I18: 4345.9677 | J18: 27679.726 | K18: 11 | L18: =IF(ISNA(_xlfn.XLOOKUP(D18,'Same Seller Hist'!E:E,'Same Seller Hist'!E:E)),"Não","Sim") -> Não | M18: =_xlfn.IFNA(_xlfn.XLOOKUP(D18,'Same Seller Hist'!E:E,'Same Seller Hist'!M:M),"Não Match") -> Não Match
C19: 45992 | D19: 1045085918 | E19: Droga Clara | F19: FMCG | G19: 0 | H19: 1 | I19: 4299.4839 | J19: 22995.675 | K19: 12 | L19: =IF(ISNA(_xlfn.XLOOKUP(D19,'Same Seller Hist'!E:E,'Same Seller Hist'!E:E)),"Não","Sim") -> Sim | M19: =_xlfn.IFNA(_xlfn.XLOOKUP(D19,'Same Seller Hist'!E:E,'Same Seller Hist'!M:M),"Não Match") -> Ativo
... C507: 45992 | D507: 405539356 | E507: Arial Tech | F507: CN | G507: 1 | H507: 1 | I507: 814.03226 | J507: 7555.3751 | K507: 500 | L507: =IF(ISNA(_xlfn.XLOOKUP(D507,'Same Seller Hist'!E:E,'Same Seller Hist'!E:E)),"Não","Sim") -> Não | M507: =_xlfn.IFNA(_xlfn.XLOOKUP(D507,'Same Seller Hist'!E:E,'Same Seller Hist'!M:M),"Não Match") -> Não Match

Sheet Fastmoss 500
B3: TOP-500 SELLERS FASTMOSS
C7: grass_month | D7: shop_name | E7: category | F7: sales | G7: revenue | H7: sales_scale | I7: total_sales | J7: revenue_scale | K7: total_revenue | L7: dollar_rate | M7: days_month | N7: adnmv_usd | O7: net_ado | P7: asp_usd | Q7: match | R7: atividade
C8: 45992 | D8: Always Fit Suplementos | E8: Health | F8: 182.4k | G8: R$9.4m | H8: =RIGHT(F8,1) -> k | I8: =VALUE(SUBSTITUTE(_xlfn.REGEXREPLACE(F8,"[^0-9.]",""),".",",")) * IF(H8="m",1000000,IF(H8="k",1000,"Erro")) -> 182400 | J8: =RIGHT(G8,1) -> m | K8: =VALUE(SUBSTITUTE(_xlfn.REGEXREPLACE(G8,"[^0-9.]",""),".",",")) * IF(J8="m",1000000,IF(J8="k",1000,"Erro")) -> 9400000 | L8: 5.3 | M8: =DAY(EOMONTH(C8,0)) -> 31 | N8: =K8/M8 -> 303225.81 | O8: =I8/M8 -> 5883.871 | P8: =N8/O8 -> 51.535088 | Q8: =IF(ISNA(_xlfn.XLOOKUP(D8,'Same Seller Hist'!H:H,'Same Seller Hist'!H:H)),"Não","Sim") -> Sim | R8: =_xlfn.IFNA(_xlfn.XLOOKUP(D8,'Same Seller Hist'!D:D,'Same Seller Hist'!M:M),"Não Existe") -> Ativo
C9: 45992 | D9: Grupo On Line Editora | E9: Books, Magazines & Audio | F9: 110.6k | G9: R$3.3m | H9: =RIGHT(F9,1) -> k | I9: =VALUE(SUBSTITUTE(_xlfn.REGEXREPLACE(F9,"[^0-9.]",""),".",",")) * IF(H9="m",1000000,IF(H9="k",1000,"Erro")) -> 110600 | J9: =RIGHT(G9,1) -> m | K9: =VALUE(SUBSTITUTE(_xlfn.REGEXREPLACE(G9,"[^0-9.]",""),".",",")) * IF(J9="m",1000000,IF(J9="k",1000,"Erro")) -> 3300000 | L9: 5.3 | M9: =DAY(EOMONTH(C9,0)) -> 31 | N9: =K9/M9 -> 106451.61 | O9: =I9/M9 -> 3567.7419 | P9: =N9/O9 -> 29.837251 | Q9: =IF(ISNA(_xlfn.XLOOKUP(D9,'Same Seller Hist'!H:H,'Same Seller Hist'!H:H)),"Não","Sim") -> Sim | R9: =_xlfn.IFNA(_xlfn.XLOOKUP(D9,'Same Seller Hist'!D:D,'Same Seller Hist'!M:M),"Não Existe") -> Ativo
C10: 45992 | D10: loli brasil shop | E10: Automotive & Motorcycle | F10: 109.1k | G10: R$2.2m | H10: =RIGHT(F10,1) -> k | I10: =VALUE(SUBSTITUTE(_xlfn.REGEXREPLACE(F10,"[^0-9.]",""),".",",")) * IF(H10="m",1000000,IF(H10="k",1000,"Erro")) -> 109100 | J10: =RIGHT(G10,1) -> m | K10: =VALUE(SUBSTITUTE(_xlfn.REGEXREPLACE(G10,"[^0-9.]",""),".",",")) * IF(J10="m",1000000,IF(J10="k",1000,"Erro")) -> 2200000 | L10: 5.3 | M10: =DAY(EOMONTH(C10,0)) -> 31 | N10: =K10/M10 -> 70967.742 | O10: =I10/M10 -> 3519.3548 | P10: =N10/O10 -> 20.164986 | Q10: =IF(ISNA(_xlfn.XLOOKUP(D10,'Same Seller Hist'!H:H,'Same Seller Hist'!H:H)),"Não","Sim") -> Não | R10: =_xlfn.IFNA(_xlfn.XLOOKUP(D10,'Same Seller Hist'!D:D,'Same Seller Hist'!M:M),"Não Existe") -> Ativo
C11: 45992 | D11: LUNA SHOP_BRASIL | E11: Luggage & Bags | F11: 102.1k | G11: R$2.9m | H11: =RIGHT(F11,1) -> k | I11: =VALUE(SUBSTITUTE(_xlfn.REGEXREPLACE(F11,"[^0-9.]",""),".",",")) * IF(H11="m",1000000,IF(H11="k",1000,"Erro")) -> 102100 | J11: =RIGHT(G11,1) -> m | K11: =VALUE(SUBSTITUTE(_xlfn.REGEXREPLACE(G11,"[^0-9.]",""),".",",")) * IF(J11="m",1000000,IF(J11="k",1000,"Erro")) -> 2900000 | L11: 5.3 | M11: =DAY(EOMONTH(C11,0)) -> 31 | N11: =K11/M11 -> 93548.387 | O11: =I11/M11 -> 3293.5484 | P11: =N11/O11 -> 28.403526 | Q11: =IF(ISNA(_xlfn.XLOOKUP(D11,'Same Seller Hist'!H:H,'Same Seller Hist'!H:H)),"Não","Sim") -> Sim | R11: =_xlfn.IFNA(_xlfn.XLOOKUP(D11,'Same Seller Hist'!D:D,'Same Seller Hist'!M:M),"Não Existe") -> Ativo
C12: 45992 | D12: Express.Loja | E12: Beauty & Personal Care | F12: 79.1k | G12: R$1.3m | H12: =RIGHT(F12,1) -> k | I12: =VALUE(SUBSTITUTE(_xlfn.REGEXREPLACE(F12,"[^0-9.]",""),".",",")) * IF(H12="m",1000000,IF(H12="k",1000,"Erro")) -> 79100 | J12: =RIGHT(G12,1) -> m | K12: =VALUE(SUBSTITUTE(_xlfn.REGEXREPLACE(G12,"[^0-9.]",""),".",",")) * IF(J12="m",1000000,IF(J12="k",1000,"Erro")) -> 1300000 | L12: 5.3 | M12: =DAY(EOMONTH(C12,0)) -> 31 | N12: =K12/M12 -> 41935.484 | O12: =I12/M12 -> 2551.6129 | P12: =N12/O12 -> 16.434893 | Q12: =IF(ISNA(_xlfn.XLOOKUP(D12,'Same Seller Hist'!H:H,'Same Seller Hist'!H:H)),"Não","Sim") -> Sim | R12: =_xlfn.IFNA(_xlfn.XLOOKUP(D12,'Same Seller Hist'!D:D,'Same Seller Hist'!M:M),"Não Existe") -> Ativo
C13: 45992 | D13: DAFUSHOP BRASIL | E13: Beauty & Personal Care | F13: 69.8k | G13: R$4.3m | H13: =RIGHT(F13,1) -> k | I13: =VALUE(SUBSTITUTE(_xlfn.REGEXREPLACE(F13,"[^0-9.]",""),".",",")) * IF(H13="m",1000000,IF(H13="k",1000,"Erro")) -> 69800 | J13: =RIGHT(G13,1) -> m | K13: =VALUE(SUBSTITUTE(_xlfn.REGEXREPLACE(G13,"[^0-9.]",""),".",",")) * IF(J13="m",1000000,IF(J13="k",1000,"Erro")) -> 4300000 | L13: 5.3 | M13: =DAY(EOMONTH(C13,0)) -> 31 | N13: =K13/M13 -> 138709.68 | O13: =I13/M13 -> 2251.6129 | P13: =N13/O13 -> 61.604585 | Q13: =IF(ISNA(_xlfn.XLOOKUP(D13,'Same Seller Hist'!H:H,'Same Seller Hist'!H:H)),"Não","Sim") -> Sim | R13: =_xlfn.IFNA(_xlfn.XLOOKUP(D13,'Same Seller Hist'!D:D,'Same Seller Hist'!M:M),"Não Existe") -> Ativo
C14: 45992 | D14: DW SHOP13 | E14: Beauty & Personal Care | F14: 65.3k | G14: R$2.5m | H14: =RIGHT(F14,1) -> k | I14: =VALUE(SUBSTITUTE(_xlfn.REGEXREPLACE(F14,"[^0-9.]",""),".",",")) * IF(H14="m",1000000,IF(H14="k",1000,"Erro")) -> 65300 | J14: =RIGHT(G14,1) -> m | K14: =VALUE(SUBSTITUTE(_xlfn.REGEXREPLACE(G14,"[^0-9.]",""),".",",")) * IF(J14="m",1000000,IF(J14="k",1000,"Erro")) -> 2500000 | L14: 5.3 | M14: =DAY(EOMONTH(C14,0)) -> 31 | N14: =K14/M14 -> 80645.161 | O14: =I14/M14 -> 2106.4516 | P14: =N14/O14 -> 38.284839 | Q14: =IF(ISNA(_xlfn.XLOOKUP(D14,'Same Seller Hist'!H:H,'Same Seller Hist'!H:H)),"Não","Sim") -> Não | R14: =_xlfn.IFNA(_xlfn.XLOOKUP(D14,'Same Seller Hist'!D:D,'Same Seller Hist'!M:M),"Não Existe") -> Não Existe
C15: 45992 | D15: Barbour's Beauty | E15: Beauty & Personal Care | F15: 63.2k | G15: R$3.5m | H15: =RIGHT(F15,1) -> k | I15: =VALUE(SUBSTITUTE(_xlfn.REGEXREPLACE(F15,"[^0-9.]",""),".",",")) * IF(H15="m",1000000,IF(H15="k",1000,"Erro")) -> 63200 | J15: =RIGHT(G15,1) -> m | K15: =VALUE(SUBSTITUTE(_xlfn.REGEXREPLACE(G15,"[^0-9.]",""),".",",")) * IF(J15="m",1000000,IF(J15="k",1000,"Erro")) -> 3500000 | L15: 5.3 | M15: =DAY(EOMONTH(C15,0)) -> 31 | N15: =K15/M15 -> 112903.23 | O15: =I15/M15 -> 2038.7097 | P15: =N15/O15 -> 55.379747 | Q15: =IF(ISNA(_xlfn.XLOOKUP(D15,'Same Seller Hist'!H:H,'Same Seller Hist'!H:H)),"Não","Sim") -> Sim | R15: =_xlfn.IFNA(_xlfn.XLOOKUP(D15,'Same Seller Hist'!D:D,'Same Seller Hist'!M:M),"Não Existe") -> Ativo
C16: 45992 | D16: Z&D Lingerie | E16: Womenswear & Underwear | F16: 62.3k | G16: R$1.6m | H16: =RIGHT(F16,1) -> k | I16: =VALUE(SUBSTITUTE(_xlfn.REGEXREPLACE(F16,"[^0-9.]",""),".",",")) * IF(H16="m",1000000,IF(H16="k",1000,"Erro")) -> 62300 | J16: =RIGHT(G16,1) -> m | K16: =VALUE(SUBSTITUTE(_xlfn.REGEXREPLACE(G16,"[^0-9.]",""),".",",")) * IF(J16="m",1000000,IF(J16="k",1000,"Erro")) -> 1600000 | L16: 5.3 | M16: =DAY(EOMONTH(C16,0)) -> 31 | N16: =K16/M16 -> 51612.903 | O16: =I16/M16 -> 2009.6774 | P16: =N16/O16 -> 25.682183 | Q16: =IF(ISNA(_xlfn.XLOOKUP(D16,'Same Seller Hist'!H:H,'Same Seller Hist'!H:H)),"Não","Sim") -> Não | R16: =_xlfn.IFNA(_xlfn.XLOOKUP(D16,'Same Seller Hist'!D:D,'Same Seller Hist'!M:M),"Não Existe") -> Ativo
C17: 45992 | D17: Bodyaction | E17: Health | F17: 60.7k | G17: R$5.4m | H17: =RIGHT(F17,1) -> k | I17: =VALUE(SUBSTITUTE(_xlfn.REGEXREPLACE(F17,"[^0-9.]",""),".",",")) * IF(H17="m",1000000,IF(H17="k",1000,"Erro")) -> 60700 | J17: =RIGHT(G17,1) -> m | K17: =VALUE(SUBSTITUTE(_xlfn.REGEXREPLACE(G17,"[^0-9.]",""),".",",")) * IF(J17="m",1000000,IF(J17="k",1000,"Erro")) -> 5400000 | L17: 5.3 | M17: =DAY(EOMONTH(C17,0)) -> 31 | N17: =K17/M17 -> 174193.55 | O17: =I17/M17 -> 1958.0645 | P17: =N17/O17 -> 88.962109 | Q17: =IF(ISNA(_xlfn.XLOOKUP(D17,'Same Seller Hist'!H:H,'Same Seller Hist'!H:H)),"Não","Sim") -> Sim | R17: =_xlfn.IFNA(_xlfn.XLOOKUP(D17,'Same Seller Hist'!D:D,'Same Seller Hist'!M:M),"Não Existe") -> Ativo
C18: 45992 | D18: LEO BUY SHOP | E18: Phones & Electronics | F18: 60.1k | G18: R$4.3m | H18: =RIGHT(F18,1) -> k | I18: =VALUE(SUBSTITUTE(_xlfn.REGEXREPLACE(F18,"[^0-9.]",""),".",",")) * IF(H18="m",1000000,IF(H18="k",1000,"Erro")) -> 60100 | J18: =RIGHT(G18,1) -> m | K18: =VALUE(SUBSTITUTE(_xlfn.REGEXREPLACE(G18,"[^0-9.]",""),".",",")) * IF(J18="m",1000000,IF(J18="k",1000,"Erro")) -> 4300000 | L18: 5.3 | M18: =DAY(EOMONTH(C18,0)) -> 31 | N18: =K18/M18 -> 138709.68 | O18: =I18/M18 -> 1938.7097 | P18: =N18/O18 -> 71.547421 | Q18: =IF(ISNA(_xlfn.XLOOKUP(D18,'Same Seller Hist'!H:H,'Same Seller Hist'!H:H)),"Não","Sim") -> Sim | R18: =_xlfn.IFNA(_xlfn.XLOOKUP(D18,'Same Seller Hist'!D:D,'Same Seller Hist'!M:M),"Não Existe") -> Ativo
C19: 45992 | D19: New Shop BR | E19: Luggage & Bags | F19: 54.0k | G19: R$2.2m | H19: =RIGHT(F19,1) -> k | I19: =VALUE(SUBSTITUTE(_xlfn.REGEXREPLACE(F19,"[^0-9.]",""),".",",")) * IF(H19="m",1000000,IF(H19="k",1000,"Erro")) -> 54000 | J19: =RIGHT(G19,1) -> m | K19: =VALUE(SUBSTITUTE(_xlfn.REGEXREPLACE(G19,"[^0-9.]",""),".",",")) * IF(J19="m",1000000,IF(J19="k",1000,"Erro")) -> 2200000 | L19: 5.3 | M19: =DAY(EOMONTH(C19,0)) -> 31 | N19: =K19/M19 -> 70967.742 | O19: =I19/M19 -> 1741.9355 | P19: =N19/O19 -> 40.740741 | Q19: =IF(ISNA(_xlfn.XLOOKUP(D19,'Same Seller Hist'!H:H,'Same Seller Hist'!H:H)),"Não","Sim") -> Não | R19: =_xlfn.IFNA(_xlfn.XLOOKUP(D19,'Same Seller Hist'!D:D,'Same Seller Hist'!M:M),"Não Existe") -> Não Existe
... C507: 45992 | D507: Forever Liss | E507: Beauty & Personal Care | F507: 6.2k | G507: R$234.4k | H507: =RIGHT(F507,1) -> k | I507: =VALUE(SUBSTITUTE(_xlfn.REGEXREPLACE(F507,"[^0-9.]",""),".",",")) * IF(H507="m",1000000,IF(H507="k",1000,"Erro")) -> 6200 | J507: =RIGHT(G507,1) -> k | K507: =VALUE(SUBSTITUTE(_xlfn.REGEXREPLACE(G507,"[^0-9.]",""),".",",")) * IF(J507="m",1000000,IF(J507="k",1000,"Erro")) -> 234400 | L507: 5.3 | M507: =DAY(EOMONTH(C507,0)) -> 31 | N507: =K507/M507 -> 7561.2903 | O507: =I507/M507 -> 200 | P507: =N507/O507 -> 37.806452 | Q507: =IF(ISNA(_xlfn.XLOOKUP(D507,'Same Seller Hist'!H:H,'Same Seller Hist'!H:H)),"Não","Sim") -> Sim | R507: =_xlfn.IFNA(_xlfn.XLOOKUP(D507,'Same Seller Hist'!D:D,'Same Seller Hist'!M:M),"Não Existe") -> Ativo

Sheet Same Seller Hist
B3: REGISTRO HISTÓRICO DE SAME-SELLERS COM TTS
C7: grass_month | D7: shop_name_shp | E7: shop_id_shopee | F7: cluster_shopee | G7: top_shopee | H7: shop_name_tts | I7: shop_id_tts | J7: category_tts | K7: top_tts | L7: shop_link_tts | M7: activity
D8: LUJIA | E8: 1001582190 | F8: Fashion | H8: LUJIA | I8: 7.4961845e+18 | J8: Beauty & Personal Care | L8: https://vt.tiktok.com/ZSfemCtBE/?page=TikTokShop | M8: Ativo
D9: Arara Store. | E9: 1005980154 | F9: ELHA | H9: Arara Store. | I9: 7.4941693e+18 | M9: Ativo
